Workbook
Name Clientes: Clientes!$A$3:$A$643
Name Grupos: 'Datos Maestros'!$K$2:$K$65
Name ListaProductos: Precios!$B$2:$B$836
Name Negocios: 'Datos Maestros'!$P$2:$P$14
Name NombreProductos: 'Productos - Inventario'!$A$1:$A$130
Name Pesos: 'Datos Maestros'!$H$2:$H$9
Name Productos: 'Datos Maestros'!$J$2:$J$65
Name ProductosInventario: 'Productos - Inventario'!$A$2:$A$130
Name Proveedores: 'Datos Maestros'!$A$2:$A$17
Name StatusEntrega: 'Datos Maestros'!$R$2:$R$15
Name StatusPago: 'Datos Maestros'!$T$2:$T$16
Name Unidades: 'Datos Maestros'!$F$2:$F$7
Name Vendedores: 'Datos Maestros'!$C$2:$C$23

Sheet Estructura
A1: Estructura | C1: Datos
A2: DROP TABLE DETALLES_DOCUMENTO CASCADE CONSTRAINTS; | C2: TRUNCATE TABLE DETALLES_DOCUMENTO;
A3: DROP TABLE DOCUMENTOS CASCADE CONSTRAINTS; | C3: TRUNCATE TABLE DOCUMENTOS;
A4: DROP TABLE CLIENTES CASCADE CONSTRAINTS; | C4: TRUNCATE TABLE CLIENTES;
A5: DROP TABLE EMPLEADOS CASCADE CONSTRAINTS; | C5: TRUNCATE TABLE EMPLEADOS;
A6: DROP TABLE PRECIOS CASCADE CONSTRAINTS; | C6: TRUNCATE TABLE PRECIOS;
A7: DROP TABLE PRODUCTOS CASCADE CONSTRAINTS; | C7: TRUNCATE TABLE PRODUCTOS;
A8: DROP TABLE COMUNAS CASCADE CONSTRAINTS; | C8: TRUNCATE TABLE COMUNAS;
A9: DROP TABLE REGIONES CASCADE CONSTRAINTS; | C9: TRUNCATE TABLE REGIONES;
A10: DROP TABLE TIPOS_DOCUMENTO CASCADE CONSTRAINTS; | C10: TRUNCATE TABLE TIPOS_DOCUMENTO;

Sheet REGIONES
A1: Id_Region | B1: Nombre | C1: Script
A2: 1 | B2: Región de Tarapacá | C2: =CONCATENATE("INSERT INTO REGIONES (ID_REGION, NOMBRE) VALUES (",A2,",","'",B2,"');") -> INSERT INTO REGIONES (ID_REGION, NOMBRE) VALUES (1,'Región de Tarapacá');
A3: 2 | B3: Región de Antofagasta | C3: =CONCATENATE("INSERT INTO REGIONES (ID_REGION, NOMBRE) VALUES (",A3,",","'",B3,"');") -> INSERT INTO REGIONES (ID_REGION, NOMBRE) VALUES (2,'Región de Antofagasta');
A4: 3 | B4: Región de Atacama | C4: =CONCATENATE("INSERT INTO REGIONES (ID_REGION, NOMBRE) VALUES (",A4,",","'",B4,"');") -> INSERT INTO REGIONES (ID_REGION, NOMBRE) VALUES (3,'Región de Atacama');
A5: 4 | B5: Región de Coquimbo | C5: =CONCATENATE("INSERT INTO REGIONES (ID_REGION, NOMBRE) VALUES (",A5,",","'",B5,"');") -> INSERT INTO REGIONES (ID_REGION, NOMBRE) VALUES (4,'Región de Coquimbo');
A6: 5 | B6: Región de Valparaíso | C6: =CONCATENATE("INSERT INTO REGIONES (ID_REGION, NOMBRE) VALUES (",A6,",","'",B6,"');") -> INSERT INTO REGIONES (ID_REGION, NOMBRE) VALUES (5,'Región de Valparaíso');
A7: 6 | B7: Región del Libertador General Bernardo OHiggins | C7: =CONCATENATE("INSERT INTO REGIONES (ID_REGION, NOMBRE) VALUES (",A7,",","'",B7,"');") -> INSERT INTO REGIONES (ID_REGION, NOMBRE) VALUES (6,'Región del Libertador General Bernardo OHiggins');
A8: 7 | B8: Región del Maule | C8: =CONCATENATE("INSERT INTO REGIONES (ID_REGION, NOMBRE) VALUES (",A8,",","'",B8,"');") -> INSERT INTO REGIONES (ID_REGION, NOMBRE) VALUES (7,'Región del Maule');
A9: 8 | B9: Región del Biobío | C9: =CONCATENATE("INSERT INTO REGIONES (ID_REGION, NOMBRE) VALUES (",A9,",","'",B9,"');") -> INSERT INTO REGIONES (ID_REGION, NOMBRE) VALUES (8,'Región del Biobío');
A10: 9 | B10: Región de La Araucanía | C10: =CONCATENATE("INSERT INTO REGIONES (ID_REGION, NOMBRE) VALUES (",A10,",","'",B10,"');") -> INSERT INTO REGIONES (ID_REGION, NOMBRE) VALUES (9,'Región de La Araucanía');
A11: 10 | B11: Región de Los Lagos | C11: =CONCATENATE("INSERT INTO REGIONES (ID_REGION, NOMBRE) VALUES (",A11,",","'",B11,"');") -> INSERT INTO REGIONES (ID_REGION, NOMBRE) VALUES (10,'Región de Los Lagos');
A12: 11 | B12: Región de Aysén del General Carlos Ibáñez del Campo | C12: =CONCATENATE("INSERT INTO REGIONES (ID_REGION, NOMBRE) VALUES (",A12,",","'",B12,"');") -> INSERT INTO REGIONES (ID_REGION, NOMBRE) VALUES (11,'Región de Aysén del General Carlos Ibáñez del Campo');
A13: 12 | B13: Región de Magallanes y de la Antártica Chilena | C13: =CONCATENATE("INSERT INTO REGIONES (ID_REGION, NOMBRE) VALUES (",A13,",","'",B13,"');") -> INSERT INTO REGIONES (ID_REGION, NOMBRE) VALUES (12,'Región de Magallanes y de la Antártica Chilena');
... A17: 16 | B17: Región de Ñuble | C17: =CONCATENATE("INSERT INTO REGIONES (ID_REGION, NOMBRE) VALUES (",A17,",","'",B17,"');") -> INSERT INTO REGIONES (ID_REGION, NOMBRE) VALUES (16,'Región de Ñuble ');
C18: COMMIT;

Sheet COMUNAS
A1: Id_Comuna | B1: Nombre | C1: Id_Region | D1: Script
A2: 1101 | B2: Iquique | C2: =IF(LEN(A2)=5, LEFT(A2,2),LEFT(A2,1)) -> 1 | D2: =CONCATENATE( "INSERT INTO COMUNAS (ID_COMUNA,NOMBRE,ID_REGION) VALUES (",A2,",'",B2,"',",C2,");") -> INSERT INTO COMUNAS (ID_COMUNA,NOMBRE,ID_REGION) VALUES (1101,'Iquique',1);
A3: 1107 | B3: Alto Hospicio | C3: =IF(LEN(A3)=5,LEFT(A3,2),LEFT(A3,1)) -> 1 | D3: =CONCATENATE( "INSERT INTO COMUNAS (ID_COMUNA,NOMBRE,ID_REGION) VALUES (",A3,",'",B3,"',",C3,");") -> INSERT INTO COMUNAS (ID_COMUNA,NOMBRE,ID_REGION) VALUES (1107,'Alto Hospicio',1);
A4: 1401 | B4: Pozo Almonte | C4: =IF(LEN(A4)=5,LEFT(A4,2),LEFT(A4,1)) -> 1 | D4: =CONCATENATE( "INSERT INTO COMUNAS (ID_COMUNA,NOMBRE,ID_REGION) VALUES (",A4,",'",B4,"',",C4,");") -> INSERT INTO COMUNAS (ID_COMUNA,NOMBRE,ID_REGION) VALUES (1401,'Pozo Almonte',1);
A5: 1402 | B5: Camiña | C5: =IF(LEN(A5)=5,LEFT(A5,2),LEFT(A5,1)) -> 1 | D5: =CONCATENATE( "INSERT INTO COMUNAS (ID_COMUNA,NOMBRE,ID_REGION) VALUES (",A5,",'",B5,"',",C5,");") -> INSERT INTO COMUNAS (ID_COMUNA,NOMBRE,ID_REGION) VALUES (1402,'Camiña',1);
A6: 1403 | B6: Colchane | C6: =IF(LEN(A6)=5,LEFT(A6,2),LEFT(A6,1)) -> 1 | D6: =CONCATENATE( "INSERT INTO COMUNAS (ID_COMUNA,NOMBRE,ID_REGION) VALUES (",A6,",'",B6,"',",C6,");") -> INSERT INTO COMUNAS (ID_COMUNA,NOMBRE,ID_REGION) VALUES (1403,'Colchane',1);
A7: 1404 | B7: Huara | C7: =IF(LEN(A7)=5,LEFT(A7,2),LEFT(A7,1)) -> 1 | D7: =CONCATENATE( "INSERT INTO COMUNAS (ID_COMUNA,NOMBRE,ID_REGION) VALUES (",A7,",'",B7,"',",C7,");") -> INSERT INTO COMUNAS (ID_COMUNA,NOMBRE,ID_REGION) VALUES (1404,'Huara',1);
A8: 1405 | B8: Pica | C8: =IF(LEN(A8)=5,LEFT(A8,2),LEFT(A8,1)) -> 1 | D8: =CONCATENATE( "INSERT INTO COMUNAS (ID_COMUNA,NOMBRE,ID_REGION) VALUES (",A8,",'",B8,"',",C8,");") -> INSERT INTO COMUNAS (ID_COMUNA,NOMBRE,ID_REGION) VALUES (1405,'Pica',1);
A9: 2101 | B9: Antofagasta | C9: =IF(LEN(A9)=5,LEFT(A9,2),LEFT(A9,1)) -> 2 | D9: =CONCATENATE( "INSERT INTO COMUNAS (ID_COMUNA,NOMBRE,ID_REGION) VALUES (",A9,",'",B9,"',",C9,");") -> INSERT INTO COMUNAS (ID_COMUNA,NOMBRE,ID_REGION) VALUES (2101,'Antofagasta',2);
A10: 2102 | B10: Mejillones | C10: =IF(LEN(A10)=5,LEFT(A10,2),LEFT(A10,1)) -> 2 | D10: =CONCATENATE( "INSERT INTO COMUNAS (ID_COMUNA,NOMBRE,ID_REGION) VALUES (",A10,",'",B10,"',",C10,");") -> INSERT INTO COMUNAS (ID_COMUNA,NOMBRE,ID_REGION) VALUES (2102,'Mejillones',2);
A11: 2103 | B11: Sierra Gorda | C11: =IF(LEN(A11)=5,LEFT(A11,2),LEFT(A11,1)) -> 2 | D11: =CONCATENATE( "INSERT INTO COMUNAS (ID_COMUNA,NOMBRE,ID_REGION) VALUES (",A11,",'",B11,"',",C11,");") -> INSERT INTO COMUNAS (ID_COMUNA,NOMBRE,ID_REGION) VALUES (2103,'Sierra Gorda',2);
A12: 2104 | B12: Taltal | C12: =IF(LEN(A12)=5,LEFT(A12,2),LEFT(A12,1)) -> 2 | D12: =CONCATENATE( "INSERT INTO COMUNAS (ID_COMUNA,NOMBRE,ID_REGION) VALUES (",A12,",'",B12,"',",C12,");") -> INSERT INTO COMUNAS (ID_COMUNA,NOMBRE,ID_REGION) VALUES (2104,'Taltal',2);
A13: 2201 | B13: Calama | C13: =IF(LEN(A13)=5,LEFT(A13,2),LEFT(A13,1)) -> 2 | D13: =CONCATENATE( "INSERT INTO COMUNAS (ID_COMUNA,NOMBRE,ID_REGION) VALUES (",A13,",'",B13,"',",C13,");") -> INSERT INTO COMUNAS (ID_COMUNA,NOMBRE,ID_REGION) VALUES (2201,'Calama',2);
A14: 2202 | B14: Ollague | C14: =IF(LEN(A14)=5,LEFT(A14,2),LEFT(A14,1)) -> 2 | D14: =CONCATENATE( "INSERT INTO COMUNAS (ID_COMUNA,NOMBRE,ID_REGION) VALUES (",A14,",'",B14,"',",C14,");") -> INSERT INTO COMUNAS (ID_COMUNA,NOMBRE,ID_REGION) VALUES (2202,'Ollague',2);
... A346: 15202 | B346: General Lagos | C346: =IF(LEN(A346)=5,LEFT(A346,2),LEFT(A346,1)) -> 15 | D346: =CONCATENATE( "INSERT INTO COMUNAS (ID_COMUNA,NOMBRE,ID_REGION) VALUES (",A346,",'",B346,"',",C346,");") -> INSERT INTO COMUNAS (ID_COMUNA,NOMBRE,ID_REGION) VALUES (15202,'General Lagos',15);
D347: COMMIT;

Sheet TIPOS_DOCUMENTO
A1: Id_Tipo | B1: Descripcion | C1: Script
A2: 1 | B2: Boleta de Venta | C2: =CONCATENATE("INSERT INTO TIPOS_DOCUMENTO(ID_TIPO,DESCRIPCION) VALUES(",A2,",'",B2,"');") -> INSERT INTO TIPOS_DOCUMENTO(ID_TIPO,DESCRIPCION) VALUES(1,'Boleta de Venta');
A3: 2 | B3: Factura de Venta | C3: =CONCATENATE("INSERT INTO TIPOS_DOCUMENTO(ID_TIPO,DESCRIPCION) VALUES(",A3,",'",B3,"');") -> INSERT INTO TIPOS_DOCUMENTO(ID_TIPO,DESCRIPCION) VALUES(2,'Factura de Venta');
A4: 3 | B4: Nota de Crédito | C4: =CONCATENATE("INSERT INTO TIPOS_DOCUMENTO(ID_TIPO,DESCRIPCION) VALUES(",A4,",'",B4,"');") -> INSERT INTO TIPOS_DOCUMENTO(ID_TIPO,DESCRIPCION) VALUES(3,'Nota de Crédito');
C5: COMMIT;

Sheet EMPLEADOS
A1: Rut_Empleado | B1: Primer_Nombre | C1: Segundo_Nombre | D1: Apellido_Paterno | E1: Apellido_Materno | F1: Direccion | G1: Correo | H1: Fecha_Nacimiento | I1: Id_Comuna | J1: Id_Region | K1: Script
A2: 14526149-K | B2: Fernando | C2: Amaro | D2: Figueroa | E2: Aguirre | F2: Avenida Departamental 111 | G2: Fernando.Figueroa@cayrap.cl | H2: 05-07-1981 | I2: 13110 | J2: 13 | K2: =CONCATENATE("INSERT INTO EMPLEADOS (RUT_EMPLEADO, PRIMER_NOMBRE, SEGUNDO_NOMBRE, APELLIDO_PATERNO, APELLIDO_MATERNO, DIRECCION, CORREO, FECHA_NACIMIENTO, ID_COMUNA, ID_REGION) VALUES (","'",A2,"','",B2,"','",C2,"','",D2,"','",E2,"','",F2,"','",G2,"',","TO_DATE('",H2,"','DD/MM/YYYY'),",I2,",",J2,");") -> INSERT INTO EMPLEADOS (RUT_EMPLEADO, PRIMER_NOMBRE, SEGUNDO_NOMBRE, APELLIDO_PATERNO, APELLIDO_MATERNO, DIRECCION, CORREO, FECHA_NACIMIENTO, ID_COMUNA, ID_REGION) VALUES ('14526149-K','Fernando','Amaro','Figueroa','Aguirre','Avenida Departamental 111','Fernando.Figueroa@cayrap.cl',TO_DATE('05-07-1981','DD/MM/YYYY'),13110,13);
A3: 17866360-7 | B3: Amalia | C3: Elena | D3: Herrera | E3: Santelices | F3: Calle Nonato Coo 345 | G3: Amalia.Herrera@cayrap.cl | H3: 24-02-1992 | I3: 13201 | J3: 13 | K3: =CONCATENATE("INSERT INTO EMPLEADOS (RUT_EMPLEADO, PRIMER_NOMBRE, SEGUNDO_NOMBRE, APELLIDO_PATERNO, APELLIDO_MATERNO, DIRECCION, CORREO, FECHA_NACIMIENTO, ID_COMUNA, ID_REGION) VALUES (","'",A3,"','",B3,"','",C3,"','",D3,"','",E3,"','",F3,"','",G3,"',","TO_DATE('",H3,"','DD/MM/YYYY'),",I3,",",J3,");") -> INSERT INTO EMPLEADOS (RUT_EMPLEADO, PRIMER_NOMBRE, SEGUNDO_NOMBRE, APELLIDO_PATERNO, APELLIDO_MATERNO, DIRECCION, CORREO, FECHA_NACIMIENTO, ID_COMUNA, ID_REGION) VALUES ('17866360-7','Amalia','Elena','Herrera','Santelices','Calle Nonato Coo 345','Amalia.Herrera@cayrap.cl',TO_DATE('24-02-1992','DD/MM/YYYY'),13201,13);
A4: 19145461-8 | B4: Camila | C4: Andrea | D4: Herrera | E4: Parra | F4: Los Plátanos 3130 | G4: Camila.Herrera@cayrap.cl | H4: 17-04-1996 | I4: 13118 | J4: 13 | K4: =CONCATENATE("INSERT INTO EMPLEADOS (RUT_EMPLEADO, PRIMER_NOMBRE, SEGUNDO_NOMBRE, APELLIDO_PATERNO, APELLIDO_MATERNO, DIRECCION, CORREO, FECHA_NACIMIENTO, ID_COMUNA, ID_REGION) VALUES (","'",A4,"','",B4,"','",C4,"','",D4,"','",E4,"','",F4,"','",G4,"',","TO_DATE('",H4,"','DD/MM/YYYY'),",I4,",",J4,");") -> INSERT INTO EMPLEADOS (RUT_EMPLEADO, PRIMER_NOMBRE, SEGUNDO_NOMBRE, APELLIDO_PATERNO, APELLIDO_MATERNO, DIRECCION, CORREO, FECHA_NACIMIENTO, ID_COMUNA, ID_REGION) VALUES ('19145461-8','Camila','Andrea','Herrera','Parra','Los Plátanos 3130','Camila.Herrera@cayrap.cl',TO_DATE('17-04-1996','DD/MM/YYYY'),13118,13);
A5: 11383327-0 | B5: Claudia | C5: Alejandra | D5: Herrera | E5: Nuñez | F5: Avenida Concha y Toro 3452 | G5: Claudia.Herrera@cayrap.cl | H5: 07-04-1969 | I5: 13201 | J5: 13 | K5: =CONCATENATE("INSERT INTO EMPLEADOS (RUT_EMPLEADO, PRIMER_NOMBRE, SEGUNDO_NOMBRE, APELLIDO_PATERNO, APELLIDO_MATERNO, DIRECCION, CORREO, FECHA_NACIMIENTO, ID_COMUNA, ID_REGION) VALUES (","'",A5,"','",B5,"','",C5,"','",D5,"','",E5,"','",F5,"','",G5,"',","TO_DATE('",H5,"','DD/MM/YYYY'),",I5,",",J5,");") -> INSERT INTO EMPLEADOS (RUT_EMPLEADO, PRIMER_NOMBRE, SEGUNDO_NOMBRE, APELLIDO_PATERNO, APELLIDO_MATERNO, DIRECCION, CORREO, FECHA_NACIMIENTO, ID_COMUNA, ID_REGION) VALUES ('11383327-0','Claudia','Alejandra','Herrera','Nuñez','Avenida Concha y Toro 3452','Claudia.Herrera@cayrap.cl',TO_DATE('07-04-1969','DD/MM/YYYY'),13201,13);
A6: 10554261-5 | B6: Juan | C6: Carlos | D6: Herrera | E6: Fernandez | F6: Diagonal Santa Irene 3015 | G6: Juan.Herrera@cayrap.cl | H6: 11-09-1968 | I6: 13110 | J6: 13 | K6: =CONCATENATE("INSERT INTO EMPLEADOS (RUT_EMPLEADO, PRIMER_NOMBRE, SEGUNDO_NOMBRE, APELLIDO_PATERNO, APELLIDO_MATERNO, DIRECCION, CORREO, FECHA_NACIMIENTO, ID_COMUNA, ID_REGION) VALUES (","'",A6,"','",B6,"','",C6,"','",D6,"','",E6,"','",F6,"','",G6,"',","TO_DATE('",H6,"','DD/MM/YYYY'),",I6,",",J6,");") -> INSERT INTO EMPLEADOS (RUT_EMPLEADO, PRIMER_NOMBRE, SEGUNDO_NOMBRE, APELLIDO_PATERNO, APELLIDO_MATERNO, DIRECCION, CORREO, FECHA_NACIMIENTO, ID_COMUNA, ID_REGION) VALUES ('10554261-5','Juan','Carlos','Herrera','Fernandez','Diagonal Santa Irene 3015','Juan.Herrera@cayrap.cl',TO_DATE('11-09-1968','DD/MM/YYYY'),13110,13);
A7: 13748252-5 | B7: Soledad | C7: Ester | D7: Saavedra | E7: Gonzalez | F7: Avenida Santa Rosa 2606 | G7: Soledad.Saavedra@cayrap.cl | H7: 11-08-1974 | I7: 13129 | J7: 13 | K7: =CONCATENATE("INSERT INTO EMPLEADOS (RUT_EMPLEADO, PRIMER_NOMBRE, SEGUNDO_NOMBRE, APELLIDO_PATERNO, APELLIDO_MATERNO, DIRECCION, CORREO, FECHA_NACIMIENTO, ID_COMUNA, ID_REGION) VALUES (","'",A7,"','",B7,"','",C7,"','",D7,"','",E7,"','",F7,"','",G7,"',","TO_DATE('",H7,"','DD/MM/YYYY'),",I7,",",J7,");") -> INSERT INTO EMPLEADOS (RUT_EMPLEADO, PRIMER_NOMBRE, SEGUNDO_NOMBRE, APELLIDO_PATERNO, APELLIDO_MATERNO, DIRECCION, CORREO, FECHA_NACIMIENTO, ID_COMUNA, ID_REGION) VALUES ('13748252-5','Soledad','Ester','Saavedra','Gonzalez','Avenida Santa Rosa 2606','Soledad.Saavedra@cayrap.cl',TO_DATE('11-08-1974','DD/MM/YYYY'),13129,13);
K8: COMMIT;

Sheet CLIENTES_BD
D1: Elementos a Considerar
D2: En la empresa CayRAP, los clientes que tienen rut son EMPRESAS y si no tiene rut es persona natural, por lo tanto ,no sirve la actual PK de la tabla CLIENTES. Es por ello que se realizaran lo siguientes ajustes en el Modelo | I2: Script
D3: 1) | E3: Borrar la relación (FK) con la tabla DOCUMENTOS | I3: ALTER TABLE DOCUMENTOS DROP CONSTRAINT CLIENTE_FK_DOCUMENTO;
D4: 2) | E4: Eliminar actual PK de la tabla CLIENTES | I4: ALTER TABLE CLIENTES DROP PRIMARY KEY;
D5: 3) | E5: Crear el campo ID_CLIENTE en la tabla CLIENTES | I5: ALTER TABLE CLIENTES ADD ID_CLIENTE NUMBER(10) GENERATED ALWAYS AS IDENTITY MINVALUE 1 MAXVALUE 9999999999;
D6: 4) | E6: Ajustar el atributo RUT_CLIENTE para que sea opcional | I6: ALTER TABLE CLIENTES MODIFY RUT_CLIENTE VARCHAR2(15) NULL;
D7: 5) | E7: Eliminar el campo RUT_CLIENTE de la tabla DOCUMENTOS | I7: ALTER TABLE DOCUMENTOS DROP COLUMN RUT_CLIENTE ;
D8: 6) | E8: Crear el campo ID_CLIENTE en la tabla DOCUMENTOS | I8: ALTER TABLE DOCUMENTOS ADD ID_CLIENTE NUMBER(10) NOT NULL;
D9: 7) | E9: Utilizar el campo ID_CLIENTE como PK de la tabla CLIENTES | I9: ALTER TABLE CLIENTES ADD PRIMARY KEY (ID_CLIENTE);
D10: 8) | E10: Crear la relacion(FK) con la tabla DOCUMENTOS | I10: ALTER TABLE DOCUMENTOS ADD CONSTRAINT CLIENTE_FK_DOCUMENTO FOREIGN KEY (ID_CLIENTE) REFERENCES CLIENTES (ID_CLIENTE);
D11: 9) | E11: Crear los registros en la tabla CLIENTES | I11: Ejecutar script de creación de registros
B16: Asignacion Automatica
A17: Cliente | B17: Id_Cliente | C17: Rut_Cliente | D17: Razon_Social | E17: Direccion | F17: Id_Comuna | G17: Id_Region | H17: Fecha_Nacimiento | I17: Script
A18: =Clientes!A3 -> Abuelita Lorenzo | B18: 1 | C18: =IF(ISBLANK(Clientes!L3),"NULL",CONCATENATE("'",Clientes!L3,"'")) -> NULL | D18: =CONCATENATE("'",Clientes!A3,"'") -> 'Abuelita Lorenzo' | E18: =IF(ISBLANK(Clientes!C3),"'Sin Direccion'",CONCATENATE("'",MID(Clientes!C3,1,95),"'")) -> 'Marcela Paz 8334' | F18: 13101 | G18: 13 | H18: 29-11-1967 | I18: =CONCATENATE("INSERT INTO CLIENTES(RUT_CLIENTE,RAZON_SOCIAL,DIRECCION,ID_COMUNA,ID_REGION,FECHA_NACIMIENTO) VALUES (",C18,",",D18,",",E18,",",F18,",",G18,",","TO_DATE('",H18,"','DD-MM-YYYY'));") -> INSERT INTO CLIENTES(RUT_CLIENTE,RAZON_SOCIAL,DIRECCION,ID_COMUNA,ID_REGION,FECHA_NACIMIENTO) VALUES (NULL,'Abuelita Lorenzo','Marcela Paz 8334',13101,13,TO_DATE('29-11-1967','DD-MM-YYYY'));
A19: =Clientes!A4 -> Elizabeth Leyton | B19: =B18+1 -> 2 | C19: =IF(ISBLANK(Clientes!L4),"NULL",CONCATENATE("'",Clientes!L4,"'")) -> NULL | D19: =CONCATENATE("'",Clientes!A4,"'") -> 'Elizabeth Leyton' | E19: =IF(ISBLANK(Clientes!C4),"'Sin Direccion'",CONCATENATE("'",MID(Clientes!C4,1,95),"'")) -> 'San Vicente de Paul 8186 la florida jardín alto' | F19: 13102 | G19: 13 | H19: 29-11-1967 | I19: =CONCATENATE("INSERT INTO CLIENTES(RUT_CLIENTE,RAZON_SOCIAL,DIRECCION,ID_COMUNA,ID_REGION,FECHA_NACIMIENTO) VALUES (",C19,",",D19,",",E19,",",F19,",",G19,",","TO_DATE('",H19,"','DD-MM-YYYY'));") -> INSERT INTO CLIENTES(RUT_CLIENTE,RAZON_SOCIAL,DIRECCION,ID_COMUNA,ID_REGION,FECHA_NACIMIENTO) VALUES (NULL,'Elizabeth Leyton','San Vicente de Paul 8186 la florida jardín alto',13102,13,TO_DATE('29-11-1967','DD-MM-YYYY'));
A20: =Clientes!A5 -> Marcelo Clerc | B20: =B19+1 -> 3 | C20: =IF(ISBLANK(Clientes!L5),"NULL",CONCATENATE("'",Clientes!L5,"'")) -> NULL | D20: =CONCATENATE("'",Clientes!A5,"'") -> 'Marcelo Clerc' | E20: =IF(ISBLANK(Clientes!C5),"'Sin Direccion'",CONCATENATE("'",MID(Clientes!C5,1,95),"'")) -> 'Rungue 8615 / Doblar en Santa Julia a mano derecha' | F20: 13103 | G20: 13 | H20: 29-11-1967 | I20: =CONCATENATE("INSERT INTO CLIENTES(RUT_CLIENTE,RAZON_SOCIAL,DIRECCION,ID_COMUNA,ID_REGION,FECHA_NACIMIENTO) VALUES (",C20,",",D20,",",E20,",",F20,",",G20,",","TO_DATE('",H20,"','DD-MM-YYYY'));") -> INSERT INTO CLIENTES(RUT_CLIENTE,RAZON_SOCIAL,DIRECCION,ID_COMUNA,ID_REGION,FECHA_NACIMIENTO) VALUES (NULL,'Marcelo Clerc','Rungue 8615 / Doblar en Santa Julia a mano derecha',13103,13,TO_DATE('29-11-1967','DD-MM-YYYY'));
A21: =Clientes!A6 -> Lorena - Quilpolemu 7170 | B21: =B20+1 -> 4 | C21: =IF(ISBLANK(Clientes!L6),"NULL",CONCATENATE("'",Clientes!L6,"'")) -> NULL | D21: =CONCATENATE("'",Clientes!A6,"'") -> 'Lorena - Quilpolemu 7170' | E21: =IF(ISBLANK(Clientes!C6),"'Sin Direccion'",CONCATENATE("'",MID(Clientes!C6,1,95),"'")) -> 'Quilpolemu 7170' | F21: 13104 | G21: 13 | H21: 29-11-1967 | I21: =CONCATENATE("INSERT INTO CLIENTES(RUT_CLIENTE,RAZON_SOCIAL,DIRECCION,ID_COMUNA,ID_REGION,FECHA_NACIMIENTO) VALUES (",C21,",",D21,",",E21,",",F21,",",G21,",","TO_DATE('",H21,"','DD-MM-YYYY'));") -> INSERT INTO CLIENTES(RUT_CLIENTE,RAZON_SOCIAL,DIRECCION,ID_COMUNA,ID_REGION,FECHA_NACIMIENTO) VALUES (NULL,'Lorena - Quilpolemu 7170','Quilpolemu 7170',13104,13,TO_DATE('29-11-1967','DD-MM-YYYY'));
A22: =Clientes!A7 -> Sandra Arriagada | B22: =B21+1 -> 5 | C22: =IF(ISBLANK(Clientes!L7),"NULL",CONCATENATE("'",Clientes!L7,"'")) -> NULL | D22: =CONCATENATE("'",Clientes!A7,"'") -> 'Sandra Arriagada' | E22: =IF(ISBLANK(Clientes!C7),"'Sin Direccion'",CONCATENATE("'",MID(Clientes!C7,1,95),"'")) -> 'Tacora 9421' | F22: 13105 | G22: 13 | H22: 29-11-1967 | I22: =CONCATENATE("INSERT INTO CLIENTES(RUT_CLIENTE,RAZON_SOCIAL,DIRECCION,ID_COMUNA,ID_REGION,FECHA_NACIMIENTO) VALUES (",C22,",",D22,",",E22,",",F22,",",G22,",","TO_DATE('",H22,"','DD-MM-YYYY'));") -> INSERT INTO CLIENTES(RUT_CLIENTE,RAZON_SOCIAL,DIRECCION,ID_COMUNA,ID_REGION,FECHA_NACIMIENTO) VALUES (NULL,'Sandra Arriagada','Tacora 9421',13105,13,TO_DATE('29-11-1967','DD-MM-YYYY'));
A23: =Clientes!A8 -> Yoli - Palena 2953 | B23: =B22+1 -> 6 | C23: =IF(ISBLANK(Clientes!L8),"NULL",CONCATENATE("'",Clientes!L8,"'")) -> NULL | D23: =CONCATENATE("'",Clientes!A8,"'") -> 'Yoli - Palena 2953' | E23: =IF(ISBLANK(Clientes!C8),"'Sin Direccion'",CONCATENATE("'",MID(Clientes!C8,1,95),"'")) -> 'Palena 2953' | F23: 13106 | G23: 13 | H23: 29-11-1967 | I23: =CONCATENATE("INSERT INTO CLIENTES(RUT_CLIENTE,RAZON_SOCIAL,DIRECCION,ID_COMUNA,ID_REGION,FECHA_NACIMIENTO) VALUES (",C23,",",D23,",",E23,",",F23,",",G23,",","TO_DATE('",H23,"','DD-MM-YYYY'));") -> INSERT INTO CLIENTES(RUT_CLIENTE,RAZON_SOCIAL,DIRECCION,ID_COMUNA,ID_REGION,FECHA_NACIMIENTO) VALUES (NULL,'Yoli - Palena 2953','Palena 2953',13106,13,TO_DATE('29-11-1967','DD-MM-YYYY'));
A24: =Clientes!A9 -> Pamela Medina - Palena 2656 | B24: =B23+1 -> 7 | C24: =IF(ISBLANK(Clientes!L9),"NULL",CONCATENATE("'",Clientes!L9,"'")) -> NULL | D24: =CONCATENATE("'",Clientes!A9,"'") -> 'Pamela Medina - Palena 2656' | E24: =IF(ISBLANK(Clientes!C9),"'Sin Direccion'",CONCATENATE("'",MID(Clientes!C9,1,95),"'")) -> 'Palena 2656' | F24: 13107 | G24: 13 | H24: 29-11-1967 | I24: =CONCATENATE("INSERT INTO CLIENTES(RUT_CLIENTE,RAZON_SOCIAL,DIRECCION,ID_COMUNA,ID_REGION,FECHA_NACIMIENTO) VALUES (",C24,",",D24,",",E24,",",F24,",",G24,",","TO_DATE('",H24,"','DD-MM-YYYY'));") -> INSERT INTO CLIENTES(RUT_CLIENTE,RAZON_SOCIAL,DIRECCION,ID_COMUNA,ID_REGION,FECHA_NACIMIENTO) VALUES (NULL,'Pamela Medina - Palena 2656','Palena 2656',13107,13,TO_DATE('29-11-1967','DD-MM-YYYY'));
A25: =Clientes!A10 -> Pilar Ortiz | B25: =B24+1 -> 8 | C25: =IF(ISBLANK(Clientes!L10),"NULL",CONCATENATE("'",Clientes!L10,"'")) -> NULL | D25: =CONCATENATE("'",Clientes!A10,"'") -> 'Pilar Ortiz' | E25: =IF(ISBLANK(Clientes!C10),"'Sin Direccion'",CONCATENATE("'",MID(Clientes!C10,1,95),"'")) -> 'San agustin 8165' | F25: 13108 | G25: 13 | H25: 29-11-1967 | I25: =CONCATENATE("INSERT INTO CLIENTES(RUT_CLIENTE,RAZON_SOCIAL,DIRECCION,ID_COMUNA,ID_REGION,FECHA_NACIMIENTO) VALUES (",C25,",",D25,",",E25,",",F25,",",G25,",","TO_DATE('",H25,"','DD-MM-YYYY'));") -> INSERT INTO CLIENTES(RUT_CLIENTE,RAZON_SOCIAL,DIRECCION,ID_COMUNA,ID_REGION,FECHA_NACIMIENTO) VALUES (NULL,'Pilar Ortiz','San agustin 8165',13108,13,TO_DATE('29-11-1967','DD-MM-YYYY'));
A26: =Clientes!A11 -> TRAVEL ABROAD EXPERIENCE S.P.A | B26: =B25+1 -> 9 | C26: =IF(ISBLANK(Clientes!L11),"NULL",CONCATENATE("'",Clientes!L11,"'")) -> '77890961-8' | D26: =CONCATENATE("'",Clientes!A11,"'") -> 'TRAVEL ABROAD EXPERIENCE S.P.A' | E26: =IF(ISBLANK(Clientes!C11),"'Sin Direccion'",CONCATENATE("'",MID(Clientes!C11,1,95),"'")) -> 'Avenida Suecia 0155, oficina 304, Providencia' | F26: 13109 | G26: 13 | H26: 29-11-1967 | I26: =CONCATENATE("INSERT INTO CLIENTES(RUT_CLIENTE,RAZON_SOCIAL,DIRECCION,ID_COMUNA,ID_REGION,FECHA_NACIMIENTO) VALUES (",C26,",",D26,",",E26,",",F26,",",G26,",","TO_DATE('",H26,"','DD-MM-YYYY'));") -> INSERT INTO CLIENTES(RUT_CLIENTE,RAZON_SOCIAL,DIRECCION,ID_COMUNA,ID_REGION,FECHA_NACIMIENTO) VALUES ('77890961-8','TRAVEL ABROAD EXPERIENCE S.P.A','Avenida Suecia 0155, oficina 304, Providencia',13109,13,TO_DATE('29-11-1967','DD-MM-YYYY'));
A27: =Clientes!A12 -> Giselle Rojas | B27: =B26+1 -> 10 | C27: =IF(ISBLANK(Clientes!L12),"NULL",CONCATENATE("'",Clientes!L12,"'")) -> NULL | D27: =CONCATENATE("'",Clientes!A12,"'") -> 'Giselle Rojas' | E27: =IF(ISBLANK(Clientes!C12),"'Sin Direccion'",CONCATENATE("'",MID(Clientes!C12,1,95),"'")) -> 'Vicente Huidobro 8268 la florida' | F27: 13110 | G27: 13 | H27: 29-11-1967 | I27: =CONCATENATE("INSERT INTO CLIENTES(RUT_CLIENTE,RAZON_SOCIAL,DIRECCION,ID_COMUNA,ID_REGION,FECHA_NACIMIENTO) VALUES (",C27,",",D27,",",E27,",",F27,",",G27,",","TO_DATE('",H27,"','DD-MM-YYYY'));") -> INSERT INTO CLIENTES(RUT_CLIENTE,RAZON_SOCIAL,DIRECCION,ID_COMUNA,ID_REGION,FECHA_NACIMIENTO) VALUES (NULL,'Giselle Rojas','Vicente Huidobro 8268 la florida',13110,13,TO_DATE('29-11-1967','DD-MM-YYYY'));
A28: =Clientes!A13 -> Soledad Gingko Amarillo 8807 | B28: =B27+1 -> 11 | C28: =IF(ISBLANK(Clientes!L13),"NULL",CONCATENATE("'",Clientes!L13,"'")) -> NULL | D28: =CONCATENATE("'",Clientes!A13,"'") -> 'Soledad Gingko Amarillo 8807 ' | E28: =IF(ISBLANK(Clientes!C13),"'Sin Direccion'",CONCATENATE("'",MID(Clientes!C13,1,95),"'")) -> 'Gingko Amarillo #8807' | F28: 13111 | G28: 13 | H28: 29-11-1967 | I28: =CONCATENATE("INSERT INTO CLIENTES(RUT_CLIENTE,RAZON_SOCIAL,DIRECCION,ID_COMUNA,ID_REGION,FECHA_NACIMIENTO) VALUES (",C28,",",D28,",",E28,",",F28,",",G28,",","TO_DATE('",H28,"','DD-MM-YYYY'));") -> INSERT INTO CLIENTES(RUT_CLIENTE,RAZON_SOCIAL,DIRECCION,ID_COMUNA,ID_REGION,FECHA_NACIMIENTO) VALUES (NULL,'Soledad Gingko Amarillo 8807 ','Gingko Amarillo #8807',13111,13,TO_DATE('29-11-1967','DD-MM-YYYY'));
A29: =Clientes!A14 -> Luisa - Bosque Chileno 2418 | B29: =B28+1 -> 12 | C29: =IF(ISBLANK(Clientes!L14),"NULL",CONCATENATE("'",Clientes!L14,"'")) -> NULL | D29: =CONCATENATE("'",Clientes!A14,"'") -> 'Luisa - Bosque Chileno 2418' | E29: =IF(ISBLANK(Clientes!C14),"'Sin Direccion'",CONCATENATE("'",MID(Clientes!C14,1,95),"'")) -> 'Bosque Chileno 2418' | F29: 13112 | G29: 13 | H29: 29-11-1967 | I29: =CONCATENATE("INSERT INTO CLIENTES(RUT_CLIENTE,RAZON_SOCIAL,DIRECCION,ID_COMUNA,ID_REGION,FECHA_NACIMIENTO) VALUES (",C29,",",D29,",",E29,",",F29,",",G29,",","TO_DATE('",H29,"','DD-MM-YYYY'));") -> INSERT INTO CLIENTES(RUT_CLIENTE,RAZON_SOCIAL,DIRECCION,ID_COMUNA,ID_REGION,FECHA_NACIMIENTO) VALUES (NULL,'Luisa - Bosque Chileno 2418','Bosque Chileno 2418',13112,13,TO_DATE('29-11-1967','DD-MM-YYYY'));
A30: =Clientes!A15 -> Poli Azocar | B30: =B29+1 -> 13 | C30: =IF(ISBLANK(Clientes!L15),"NULL",CONCATENATE("'",Clientes!L15,"'")) -> NULL | D30: =CONCATENATE("'",Clientes!A15,"'") -> 'Poli Azocar' | E30: =IF(ISBLANK(Clientes!C15),"'Sin Direccion'",CONCATENATE("'",MID(Clientes!C15,1,95),"'")) -> 'Portezuelo de colina 0870' | F30: 13113 | G30: 13 | H30: 29-11-1967 | I30: =CONCATENATE("INSERT INTO CLIENTES(RUT_CLIENTE,RAZON_SOCIAL,DIRECCION,ID_COMUNA,ID_REGION,FECHA_NACIMIENTO) VALUES (",C30,",",D30,",",E30,",",F30,",",G30,",","TO_DATE('",H30,"','DD-MM-YYYY'));") -> INSERT INTO CLIENTES(RUT_CLIENTE,RAZON_SOCIAL,DIRECCION,ID_COMUNA,ID_REGION,FECHA_NACIMIENTO) VALUES (NULL,'Poli Azocar','Portezuelo de colina 0870',13113,13,TO_DATE('29-11-1967','DD-MM-YYYY'));
... A505: =Clientes!A490 -> Daca Pastelería | B505: =B504+1 -> 488 | C505: =IF(ISBLANK(Clientes!L490),"NULL",CONCATENATE("'",Clientes!L490,"'")) -> '77588015-5' | D505: =CONCATENATE("'",Clientes!A490,"'") -> 'Daca Pastelería' | E505: =IF(ISBLANK(Clientes!C490),"'Sin Direccion'",CONCATENATE("'",MID(Clientes!C490,1,95),"'")) -> 'Rojas Magallanes 055 frente a la estación' | F505: 13120 | G505: 13 | H505: 29-11-1967 | I505: =CONCATENATE("INSERT INTO CLIENTES(RUT_CLIENTE,RAZON_SOCIAL,DIRECCION,ID_COMUNA,ID_REGION,FECHA_NACIMIENTO) VALUES (",C505,",",D505,",",E505,",",F505,",",G505,",","TO_DATE('",H505,"','DD-MM-YYYY'));") -> INSERT INTO CLIENTES(RUT_CLIENTE,RAZON_SOCIAL,DIRECCION,ID_COMUNA,ID_REGION,FECHA_NACIMIENTO) VALUES ('77588015-5','Daca Pastelería','Rojas Magallanes 055 frente a la estación',13120,13,TO_DATE('29-11-1967','DD-MM-YYYY'));
A506: =Clientes!A491 -> 0 | I506: COMMIT;

Sheet PRODUCTOS
A1: x | B1: Id_Producto | C1: Nombre | D1: Script
A2: =MID(Precios!B2,1,60) -> 2 Bandeja HUEVOS EXTRA 30 Huevos | B2: 1 | C2: =CONCATENATE("'",MID(Precios!B2,1,60),"'") -> '2 Bandeja HUEVOS EXTRA 30 Huevos' | D2: =CONCATENATE("INSERT INTO PRODUCTOS (ID_PRODUCTO,NOMBRE) VALUES (",B2,",",C2,");") -> INSERT INTO PRODUCTOS (ID_PRODUCTO,NOMBRE) VALUES (1,'2 Bandeja HUEVOS EXTRA 30 Huevos');
A3: =MID(Precios!B3,1,60) -> TE CEYLAN PREMIUN 100 bolsas | B3: =B2+1 -> 2 | C3: =CONCATENATE("'",MID(Precios!B3,1,60),"'") -> 'TE CEYLAN PREMIUN 100 bolsas' | D3: =CONCATENATE("INSERT INTO PRODUCTOS (ID_PRODUCTO,NOMBRE) VALUES (",B3,",",C3,");") -> INSERT INTO PRODUCTOS (ID_PRODUCTO,NOMBRE) VALUES (2,'TE CEYLAN PREMIUN 100 bolsas');
A4: =MID(Precios!B4,1,60) -> Natura List Alulosa 90ml | B4: =B3+1 -> 3 | C4: =CONCATENATE("'",MID(Precios!B4,1,60),"'") -> 'Natura List Alulosa 90ml' | D4: =CONCATENATE("INSERT INTO PRODUCTOS (ID_PRODUCTO,NOMBRE) VALUES (",B4,",",C4,");") -> INSERT INTO PRODUCTOS (ID_PRODUCTO,NOMBRE) VALUES (3,'Natura List Alulosa 90ml');
A5: =MID(Precios!B5,1,60) -> Recarga Nescafé 130grs | B5: =B4+1 -> 4 | C5: =CONCATENATE("'",MID(Precios!B5,1,60),"'") -> 'Recarga Nescafé 130grs' | D5: =CONCATENATE("INSERT INTO PRODUCTOS (ID_PRODUCTO,NOMBRE) VALUES (",B5,",",C5,");") -> INSERT INTO PRODUCTOS (ID_PRODUCTO,NOMBRE) VALUES (4,'Recarga Nescafé 130grs');
A6: =MID(Precios!B6,1,60) -> 2 x Film Embalaje 1,7kg (1,4kg Neto/350 Metros aprox.) | B6: =B5+1 -> 5 | C6: =CONCATENATE("'",MID(Precios!B6,1,60),"'") -> '2 x Film Embalaje 1,7kg (1,4kg Neto/350 Metros aprox.)' | D6: =CONCATENATE("INSERT INTO PRODUCTOS (ID_PRODUCTO,NOMBRE) VALUES (",B6,",",C6,");") -> INSERT INTO PRODUCTOS (ID_PRODUCTO,NOMBRE) VALUES (5,'2 x Film Embalaje 1,7kg (1,4kg Neto/350 Metros aprox.)');
A7: =MID(Precios!B7,1,60) -> 2 x Queso Rueda Cabra / 200 gramos) | B7: =B6+1 -> 6 | C7: =CONCATENATE("'",MID(Precios!B7,1,60),"'") -> '2 x Queso Rueda Cabra / 200 gramos)' | D7: =CONCATENATE("INSERT INTO PRODUCTOS (ID_PRODUCTO,NOMBRE) VALUES (",B7,",",C7,");") -> INSERT INTO PRODUCTOS (ID_PRODUCTO,NOMBRE) VALUES (6,'2 x Queso Rueda Cabra / 200 gramos)');
A8: =MID(Precios!B8,1,60) -> 2 x Queso Rueda Sabores / 200 gramos) | B8: =B7+1 -> 7 | C8: =CONCATENATE("'",MID(Precios!B8,1,60),"'") -> '2 x Queso Rueda Sabores / 200 gramos)' | D8: =CONCATENATE("INSERT INTO PRODUCTOS (ID_PRODUCTO,NOMBRE) VALUES (",B8,",",C8,");") -> INSERT INTO PRODUCTOS (ID_PRODUCTO,NOMBRE) VALUES (7,'2 x Queso Rueda Sabores / 200 gramos)');
A9: =MID(Precios!B9,1,60) -> 3 Bandeja HUEVOS EXTRA 30 Huevos | B9: =B8+1 -> 8 | C9: =CONCATENATE("'",MID(Precios!B9,1,60),"'") -> '3 Bandeja HUEVOS EXTRA 30 Huevos' | D9: =CONCATENATE("INSERT INTO PRODUCTOS (ID_PRODUCTO,NOMBRE) VALUES (",B9,",",C9,");") -> INSERT INTO PRODUCTOS (ID_PRODUCTO,NOMBRE) VALUES (8,'3 Bandeja HUEVOS EXTRA 30 Huevos');
A10: =MID(Precios!B10,1,60) -> 3 Toalla Jumbo OVELLA D/H / 100 metros | B10: =B9+1 -> 9 | C10: =CONCATENATE("'",MID(Precios!B10,1,60),"'") -> '3 Toalla Jumbo OVELLA D/H / 100 metros' | D10: =CONCATENATE("INSERT INTO PRODUCTOS (ID_PRODUCTO,NOMBRE) VALUES (",B10,",",C10,");") -> INSERT INTO PRODUCTOS (ID_PRODUCTO,NOMBRE) VALUES (9,'3 Toalla Jumbo OVELLA D/H / 100 metros');
A11: =MID(Precios!B11,1,60) -> Paños Cocina Fibra (30x50 cm) | B11: =B10+1 -> 10 | C11: =CONCATENATE("'",MID(Precios!B11,1,60),"'") -> 'Paños Cocina Fibra (30x50 cm)' | D11: =CONCATENATE("INSERT INTO PRODUCTOS (ID_PRODUCTO,NOMBRE) VALUES (",B11,",",C11,");") -> INSERT INTO PRODUCTOS (ID_PRODUCTO,NOMBRE) VALUES (10,'Paños Cocina Fibra (30x50 cm)');
A12: =MID(Precios!B12,1,60) -> Pack 3 Paños Cocina Fibra (30x50 cm) | B12: =B11+1 -> 11 | C12: =CONCATENATE("'",MID(Precios!B12,1,60),"'") -> 'Pack 3 Paños Cocina Fibra (30x50 cm)' | D12: =CONCATENATE("INSERT INTO PRODUCTOS (ID_PRODUCTO,NOMBRE) VALUES (",B12,",",C12,");") -> INSERT INTO PRODUCTOS (ID_PRODUCTO,NOMBRE) VALUES (11,'Pack 3 Paños Cocina Fibra (30x50 cm)');
A13: =MID(Precios!B13,1,60) -> Guantes Latex Talle M | B13: =B12+1 -> 12 | C13: =CONCATENATE("'",MID(Precios!B13,1,60),"'") -> 'Guantes Latex Talle M' | D13: =CONCATENATE("INSERT INTO PRODUCTOS (ID_PRODUCTO,NOMBRE) VALUES (",B13,",",C13,");") -> INSERT INTO PRODUCTOS (ID_PRODUCTO,NOMBRE) VALUES (12,'Guantes Latex Talle M');
A14: =MID(Precios!B14,1,60) -> Guantes Latex Talle S | B14: =B13+1 -> 13 | C14: =CONCATENATE("'",MID(Precios!B14,1,60),"'") -> 'Guantes Latex Talle S' | D14: =CONCATENATE("INSERT INTO PRODUCTOS (ID_PRODUCTO,NOMBRE) VALUES (",B14,",",C14,");") -> INSERT INTO PRODUCTOS (ID_PRODUCTO,NOMBRE) VALUES (13,'Guantes Latex Talle S');
... A388: =MID(Precios!B388,1,60) -> Wyn 750 cc | B388: =B387+1 -> 387 | C388: =CONCATENATE("'",MID(Precios!B388,1,60),"'") -> 'Wyn 750 cc' | D388: =CONCATENATE("INSERT INTO PRODUCTOS (ID_PRODUCTO,NOMBRE) VALUES (",B388,",",C388,");") -> INSERT INTO PRODUCTOS (ID_PRODUCTO,NOMBRE) VALUES (387,'Wyn 750 cc');
A389: =MID(Precios!B389,1,60) | D389: COMMIT;

Sheet PRECIOS_BD
A1: Fecha_Inicio | B1: Fecha_Fin | C1: Precio | D1: Id_Producto | E1: Script
A2: 01-01-2025 | B2: 31-12-2025 | C2: =ROUND(Precios!M2,0) -> 18639 | D2: 1 | E2: =CONCATENATE("INSERT INTO PRECIOS (FECHA_INICIO, FECHA_FIN,PRECIO,ID_PRODUCTO) VALUES ( TO_DATE(","'",A2,"'",",'DD-MM-YYYY')",", TO_DATE(","'",B2,"'",",'DD-MM-YYYY')",",",C2,",",D2,");") -> INSERT INTO PRECIOS (FECHA_INICIO, FECHA_FIN,PRECIO,ID_PRODUCTO) VALUES ( TO_DATE('01-01-2025','DD-MM-YYYY'), TO_DATE('31-12-2025','DD-MM-YYYY'),18639,1);
A3: 01-01-2025 | B3: 31-12-2025 | C3: =ROUND(Precios!M3,0) -> 5000 | D3: =D2+1 -> 2 | E3: =CONCATENATE("INSERT INTO PRECIOS (FECHA_INICIO, FECHA_FIN,PRECIO,ID_PRODUCTO) VALUES ( TO_DATE(","'",A3,"'",",'DD-MM-YYYY')",", TO_DATE(","'",B3,"'",",'DD-MM-YYYY')",",",C3,",",D3,");") -> INSERT INTO PRECIOS (FECHA_INICIO, FECHA_FIN,PRECIO,ID_PRODUCTO) VALUES ( TO_DATE('01-01-2025','DD-MM-YYYY'), TO_DATE('31-12-2025','DD-MM-YYYY'),5000,2);
A4: 01-01-2025 | B4: 31-12-2025 | C4: =ROUND(Precios!M4,0) -> 2300 | D4: =D3+1 -> 3 | E4: =CONCATENATE("INSERT INTO PRECIOS (FECHA_INICIO, FECHA_FIN,PRECIO,ID_PRODUCTO) VALUES ( TO_DATE(","'",A4,"'",",'DD-MM-YYYY')",", TO_DATE(","'",B4,"'",",'DD-MM-YYYY')",",",C4,",",D4,");") -> INSERT INTO PRECIOS (FECHA_INICIO, FECHA_FIN,PRECIO,ID_PRODUCTO) VALUES ( TO_DATE('01-01-2025','DD-MM-YYYY'), TO_DATE('31-12-2025','DD-MM-YYYY'),2300,3);
A5: 01-01-2025 | B5: 31-12-2025 | C5: =ROUND(Precios!M5,0) -> 5000 | D5: =D4+1 -> 4 | E5: =CONCATENATE("INSERT INTO PRECIOS (FECHA_INICIO, FECHA_FIN,PRECIO,ID_PRODUCTO) VALUES ( TO_DATE(","'",A5,"'",",'DD-MM-YYYY')",", TO_DATE(","'",B5,"'",",'DD-MM-YYYY')",",",C5,",",D5,");") -> INSERT INTO PRECIOS (FECHA_INICIO, FECHA_FIN,PRECIO,ID_PRODUCTO) VALUES ( TO_DATE('01-01-2025','DD-MM-YYYY'), TO_DATE('31-12-2025','DD-MM-YYYY'),5000,4);
A6: 01-01-2025 | B6: 31-12-2025 | C6: =ROUND(Precios!M6,0) -> 11000 | D6: =D5+1 -> 5 | E6: =CONCATENATE("INSERT INTO PRECIOS (FECHA_INICIO, FECHA_FIN,PRECIO,ID_PRODUCTO) VALUES ( TO_DATE(","'",A6,"'",",'DD-MM-YYYY')",", TO_DATE(","'",B6,"'",",'DD-MM-YYYY')",",",C6,",",D6,");") -> INSERT INTO PRECIOS (FECHA_INICIO, FECHA_FIN,PRECIO,ID_PRODUCTO) VALUES ( TO_DATE('01-01-2025','DD-MM-YYYY'), TO_DATE('31-12-2025','DD-MM-YYYY'),11000,5);
A7: 01-01-2025 | B7: 31-12-2025 | C7: =ROUND(Precios!M7,0) -> 9400 | D7: =D6+1 -> 6 | E7: =CONCATENATE("INSERT INTO PRECIOS (FECHA_INICIO, FECHA_FIN,PRECIO,ID_PRODUCTO) VALUES ( TO_DATE(","'",A7,"'",",'DD-MM-YYYY')",", TO_DATE(","'",B7,"'",",'DD-MM-YYYY')",",",C7,",",D7,");") -> INSERT INTO PRECIOS (FECHA_INICIO, FECHA_FIN,PRECIO,ID_PRODUCTO) VALUES ( TO_DATE('01-01-2025','DD-MM-YYYY'), TO_DATE('31-12-2025','DD-MM-YYYY'),9400,6);
A8: 01-01-2025 | B8: 31-12-2025 | C8: =ROUND(Precios!M8,0) -> 7000 | D8: =D7+1 -> 7 | E8: =CONCATENATE("INSERT INTO PRECIOS (FECHA_INICIO, FECHA_FIN,PRECIO,ID_PRODUCTO) VALUES ( TO_DATE(","'",A8,"'",",'DD-MM-YYYY')",", TO_DATE(","'",B8,"'",",'DD-MM-YYYY')",",",C8,",",D8,");") -> INSERT INTO PRECIOS (FECHA_INICIO, FECHA_FIN,PRECIO,ID_PRODUCTO) VALUES ( TO_DATE('01-01-2025','DD-MM-YYYY'), TO_DATE('31-12-2025','DD-MM-YYYY'),7000,7);
A9: 01-01-2025 | B9: 31-12-2025 | C9: =ROUND(Precios!M9,0) -> 27620 | D9: =D8+1 -> 8 | E9: =CONCATENATE("INSERT INTO PRECIOS (FECHA_INICIO, FECHA_FIN,PRECIO,ID_PRODUCTO) VALUES ( TO_DATE(","'",A9,"'",",'DD-MM-YYYY')",", TO_DATE(","'",B9,"'",",'DD-MM-YYYY')",",",C9,",",D9,");") -> INSERT INTO PRECIOS (FECHA_INICIO, FECHA_FIN,PRECIO,ID_PRODUCTO) VALUES ( TO_DATE('01-01-2025','DD-MM-YYYY'), TO_DATE('31-12-2025','DD-MM-YYYY'),27620,8);
A10: 01-01-2025 | B10: 31-12-2025 | C10: =ROUND(Precios!M10,0) -> 10900 | D10: =D9+1 -> 9 | E10: =CONCATENATE("INSERT INTO PRECIOS (FECHA_INICIO, FECHA_FIN,PRECIO,ID_PRODUCTO) VALUES ( TO_DATE(","'",A10,"'",",'DD-MM-YYYY')",", TO_DATE(","'",B10,"'",",'DD-MM-YYYY')",",",C10,",",D10,");") -> INSERT INTO PRECIOS (FECHA_INICIO, FECHA_FIN,PRECIO,ID_PRODUCTO) VALUES ( TO_DATE('01-01-2025','DD-MM-YYYY'), TO_DATE('31-12-2025','DD-MM-YYYY'),10900,9);
A11: 01-01-2025 | B11: 31-12-2025 | C11: =ROUND(Precios!M11,0) -> 1000 | D11: =D10+1 -> 10 | E11: =CONCATENATE("INSERT INTO PRECIOS (FECHA_INICIO, FECHA_FIN,PRECIO,ID_PRODUCTO) VALUES ( TO_DATE(","'",A11,"'",",'DD-MM-YYYY')",", TO_DATE(","'",B11,"'",",'DD-MM-YYYY')",",",C11,",",D11,");") -> INSERT INTO PRECIOS (FECHA_INICIO, FECHA_FIN,PRECIO,ID_PRODUCTO) VALUES ( TO_DATE('01-01-2025','DD-MM-YYYY'), TO_DATE('31-12-2025','DD-MM-YYYY'),1000,10);
A12: 01-01-2025 | B12: 31-12-2025 | C12: =ROUND(Precios!M12,0) -> 2500 | D12: =D11+1 -> 11 | E12: =CONCATENATE("INSERT INTO PRECIOS (FECHA_INICIO, FECHA_FIN,PRECIO,ID_PRODUCTO) VALUES ( TO_DATE(","'",A12,"'",",'DD-MM-YYYY')",", TO_DATE(","'",B12,"'",",'DD-MM-YYYY')",",",C12,",",D12,");") -> INSERT INTO PRECIOS (FECHA_INICIO, FECHA_FIN,PRECIO,ID_PRODUCTO) VALUES ( TO_DATE('01-01-2025','DD-MM-YYYY'), TO_DATE('31-12-2025','DD-MM-YYYY'),2500,11);
A13: 01-01-2025 | B13: 31-12-2025 | C13: =ROUND(Precios!M13,0) -> 700 | D13: =D12+1 -> 12 | E13: =CONCATENATE("INSERT INTO PRECIOS (FECHA_INICIO, FECHA_FIN,PRECIO,ID_PRODUCTO) VALUES ( TO_DATE(","'",A13,"'",",'DD-MM-YYYY')",", TO_DATE(","'",B13,"'",",'DD-MM-YYYY')",",",C13,",",D13,");") -> INSERT INTO PRECIOS (FECHA_INICIO, FECHA_FIN,PRECIO,ID_PRODUCTO) VALUES ( TO_DATE('01-01-2025','DD-MM-YYYY'), TO_DATE('31-12-2025','DD-MM-YYYY'),700,12);
A14: 01-01-2025 | B14: 31-12-2025 | C14: =ROUND(Precios!M14,0) -> 700 | D14: =D13+1 -> 13 | E14: =CONCATENATE("INSERT INTO PRECIOS (FECHA_INICIO, FECHA_FIN,PRECIO,ID_PRODUCTO) VALUES ( TO_DATE(","'",A14,"'",",'DD-MM-YYYY')",", TO_DATE(","'",B14,"'",",'DD-MM-YYYY')",",",C14,",",D14,");") -> INSERT INTO PRECIOS (FECHA_INICIO, FECHA_FIN,PRECIO,ID_PRODUCTO) VALUES ( TO_DATE('01-01-2025','DD-MM-YYYY'), TO_DATE('31-12-2025','DD-MM-YYYY'),700,13);
... A388: 01-01-2025 | B388: 31-12-2025 | C388: =ROUND(Precios!M388,0) -> 1500 | D388: =D387+1 -> 387 | E388: =CONCATENATE("INSERT INTO PRECIOS (FECHA_INICIO, FECHA_FIN,PRECIO,ID_PRODUCTO) VALUES ( TO_DATE(","'",A388,"'",",'DD-MM-YYYY')",", TO_DATE(","'",B388,"'",",'DD-MM-YYYY')",",",C388,",",D388,");") -> INSERT INTO PRECIOS (FECHA_INICIO, FECHA_FIN,PRECIO,ID_PRODUCTO) VALUES ( TO_DATE('01-01-2025','DD-MM-YYYY'), TO_DATE('31-12-2025','DD-MM-YYYY'),1500,387);
E389: COMMIT;

Sheet DOCUMENTOS
F3: Valores
A4: Id_Tipo | B4: Nro_Documento | C4: Fecha_Emision | D4: Rut_Empleado | E4: Id_Cliente | F4: Total Bruto | G4: Total Neto | H4: Total Iva | I4: Id_Tipo | J4: Script
A5: 1 | B5: 1 | C5: 02-01-2025 | D5: 14526149-K | E5: 108 | F5: 10600 | G5: 8908 | H5: 1692 | I5: 1 | J5: =CONCATENATE("INSERT INTO DOCUMENTOS (NRO_DOCUMENTO,FECHA_EMISION,TOTAL_BRUTO,TOTAL_NETO,TOTAL_IVA, ID_TIPO, RUT_EMPLEADO, ID_CLIENTE) VALUES(",B5,",","TO_DATE('",C5,"'",",'DD-MM-YYYY'),",F5,",",G5,",",H5,",",I5,",","'",D5,"',",E5,");") -> INSERT INTO DOCUMENTOS (NRO_DOCUMENTO,FECHA_EMISION,TOTAL_BRUTO,TOTAL_NETO,TOTAL_IVA, ID_TIPO, RUT_EMPLEADO, ID_CLIENTE) VALUES(1,TO_DATE('02-01-2025','DD-MM-YYYY'),10600,8908,1692,1,'14526149-K',108);
B6: 2 | C6: 02-01-2025 | D6: 14526149-K | E6: 110 | F6: 14000 | G6: 11765 | H6: 2235 | I6: 1 | J6: =CONCATENATE("INSERT INTO DOCUMENTOS (NRO_DOCUMENTO,FECHA_EMISION,TOTAL_BRUTO,TOTAL_NETO,TOTAL_IVA, ID_TIPO, RUT_EMPLEADO, ID_CLIENTE) VALUES(",B6,",","TO_DATE('",C6,"'",",'DD-MM-YYYY'),",F6,",",G6,",",H6,",",I6,",","'",D6,"',",E6,");") -> INSERT INTO DOCUMENTOS (NRO_DOCUMENTO,FECHA_EMISION,TOTAL_BRUTO,TOTAL_NETO,TOTAL_IVA, ID_TIPO, RUT_EMPLEADO, ID_CLIENTE) VALUES(2,TO_DATE('02-01-2025','DD-MM-YYYY'),14000,11765,2235,1,'14526149-K',110);
B7: 3 | C7: 02-01-2025 | D7: 14526149-K | E7: 111 | F7: 15500 | G7: 13025 | H7: 2475 | I7: 1 | J7: =CONCATENATE("INSERT INTO DOCUMENTOS (NRO_DOCUMENTO,FECHA_EMISION,TOTAL_BRUTO,TOTAL_NETO,TOTAL_IVA, ID_TIPO, RUT_EMPLEADO, ID_CLIENTE) VALUES(",B7,",","TO_DATE('",C7,"'",",'DD-MM-YYYY'),",F7,",",G7,",",H7,",",I7,",","'",D7,"',",E7,");") -> INSERT INTO DOCUMENTOS (NRO_DOCUMENTO,FECHA_EMISION,TOTAL_BRUTO,TOTAL_NETO,TOTAL_IVA, ID_TIPO, RUT_EMPLEADO, ID_CLIENTE) VALUES(3,TO_DATE('02-01-2025','DD-MM-YYYY'),15500,13025,2475,1,'14526149-K',111);
B8: 4 | C8: 02-01-2025 | D8: 14526149-K | E8: 116 | F8: 20900 | G8: 17562 | H8: 3338 | I8: 1 | J8: =CONCATENATE("INSERT INTO DOCUMENTOS (NRO_DOCUMENTO,FECHA_EMISION,TOTAL_BRUTO,TOTAL_NETO,TOTAL_IVA, ID_TIPO, RUT_EMPLEADO, ID_CLIENTE) VALUES(",B8,",","TO_DATE('",C8,"'",",'DD-MM-YYYY'),",F8,",",G8,",",H8,",",I8,",","'",D8,"',",E8,");") -> INSERT INTO DOCUMENTOS (NRO_DOCUMENTO,FECHA_EMISION,TOTAL_BRUTO,TOTAL_NETO,TOTAL_IVA, ID_TIPO, RUT_EMPLEADO, ID_CLIENTE) VALUES(4,TO_DATE('02-01-2025','DD-MM-YYYY'),20900,17562,3338,1,'14526149-K',116);
B9: 5 | C9: 02-01-2025 | D9: 14526149-K | E9: 119 | F9: 12000 | G9: 10084 | H9: 1916 | I9: 1 | J9: =CONCATENATE("INSERT INTO DOCUMENTOS (NRO_DOCUMENTO,FECHA_EMISION,TOTAL_BRUTO,TOTAL_NETO,TOTAL_IVA, ID_TIPO, RUT_EMPLEADO, ID_CLIENTE) VALUES(",B9,",","TO_DATE('",C9,"'",",'DD-MM-YYYY'),",F9,",",G9,",",H9,",",I9,",","'",D9,"',",E9,");") -> INSERT INTO DOCUMENTOS (NRO_DOCUMENTO,FECHA_EMISION,TOTAL_BRUTO,TOTAL_NETO,TOTAL_IVA, ID_TIPO, RUT_EMPLEADO, ID_CLIENTE) VALUES(5,TO_DATE('02-01-2025','DD-MM-YYYY'),12000,10084,1916,1,'14526149-K',119);
B10: 6 | C10: 02-01-2025 | D10: 14526149-K | E10: 166 | F10: 7250 | G10: 6092 | H10: 1158 | I10: 1 | J10: =CONCATENATE("INSERT INTO DOCUMENTOS (NRO_DOCUMENTO,FECHA_EMISION,TOTAL_BRUTO,TOTAL_NETO,TOTAL_IVA, ID_TIPO, RUT_EMPLEADO, ID_CLIENTE) VALUES(",B10,",","TO_DATE('",C10,"'",",'DD-MM-YYYY'),",F10,",",G10,",",H10,",",I10,",","'",D10,"',",E10,");") -> INSERT INTO DOCUMENTOS (NRO_DOCUMENTO,FECHA_EMISION,TOTAL_BRUTO,TOTAL_NETO,TOTAL_IVA, ID_TIPO, RUT_EMPLEADO, ID_CLIENTE) VALUES(6,TO_DATE('02-01-2025','DD-MM-YYYY'),7250,6092,1158,1,'14526149-K',166);
B11: 7 | C11: 02-01-2025 | D11: 14526149-K | E11: 219 | F11: 26490 | G11: 22260 | H11: 4230 | I11: 1 | J11: =CONCATENATE("INSERT INTO DOCUMENTOS (NRO_DOCUMENTO,FECHA_EMISION,TOTAL_BRUTO,TOTAL_NETO,TOTAL_IVA, ID_TIPO, RUT_EMPLEADO, ID_CLIENTE) VALUES(",B11,",","TO_DATE('",C11,"'",",'DD-MM-YYYY'),",F11,",",G11,",",H11,",",I11,",","'",D11,"',",E11,");") -> INSERT INTO DOCUMENTOS (NRO_DOCUMENTO,FECHA_EMISION,TOTAL_BRUTO,TOTAL_NETO,TOTAL_IVA, ID_TIPO, RUT_EMPLEADO, ID_CLIENTE) VALUES(7,TO_DATE('02-01-2025','DD-MM-YYYY'),26490,22260,4230,1,'14526149-K',219);
B12: 8 | C12: 02-01-2025 | D12: 14526149-K | E12: 353 | F12: 19990 | G12: 16798 | H12: 3192 | I12: 1 | J12: =CONCATENATE("INSERT INTO DOCUMENTOS (NRO_DOCUMENTO,FECHA_EMISION,TOTAL_BRUTO,TOTAL_NETO,TOTAL_IVA, ID_TIPO, RUT_EMPLEADO, ID_CLIENTE) VALUES(",B12,",","TO_DATE('",C12,"'",",'DD-MM-YYYY'),",F12,",",G12,",",H12,",",I12,",","'",D12,"',",E12,");") -> INSERT INTO DOCUMENTOS (NRO_DOCUMENTO,FECHA_EMISION,TOTAL_BRUTO,TOTAL_NETO,TOTAL_IVA, ID_TIPO, RUT_EMPLEADO, ID_CLIENTE) VALUES(8,TO_DATE('02-01-2025','DD-MM-YYYY'),19990,16798,3192,1,'14526149-K',353);
B13: 9 | C13: 02-01-2025 | D13: 14526149-K | E13: 374 | F13: 10500 | G13: 8824 | H13: 1676 | I13: 1 | J13: =CONCATENATE("INSERT INTO DOCUMENTOS (NRO_DOCUMENTO,FECHA_EMISION,TOTAL_BRUTO,TOTAL_NETO,TOTAL_IVA, ID_TIPO, RUT_EMPLEADO, ID_CLIENTE) VALUES(",B13,",","TO_DATE('",C13,"'",",'DD-MM-YYYY'),",F13,",",G13,",",H13,",",I13,",","'",D13,"',",E13,");") -> INSERT INTO DOCUMENTOS (NRO_DOCUMENTO,FECHA_EMISION,TOTAL_BRUTO,TOTAL_NETO,TOTAL_IVA, ID_TIPO, RUT_EMPLEADO, ID_CLIENTE) VALUES(9,TO_DATE('02-01-2025','DD-MM-YYYY'),10500,8824,1676,1,'14526149-K',374);
B14: 10 | C14: 02-01-2025 | D14: 14526149-K | E14: 446 | F14: 11500 | G14: 9664 | H14: 1836 | I14: 1 | J14: =CONCATENATE("INSERT INTO DOCUMENTOS (NRO_DOCUMENTO,FECHA_EMISION,TOTAL_BRUTO,TOTAL_NETO,TOTAL_IVA, ID_TIPO, RUT_EMPLEADO, ID_CLIENTE) VALUES(",B14,",","TO_DATE('",C14,"'",",'DD-MM-YYYY'),",F14,",",G14,",",H14,",",I14,",","'",D14,"',",E14,");") -> INSERT INTO DOCUMENTOS (NRO_DOCUMENTO,FECHA_EMISION,TOTAL_BRUTO,TOTAL_NETO,TOTAL_IVA, ID_TIPO, RUT_EMPLEADO, ID_CLIENTE) VALUES(10,TO_DATE('02-01-2025','DD-MM-YYYY'),11500,9664,1836,1,'14526149-K',446);
B15: 11 | C15: 02-01-2025 | D15: 14526149-K | E15: 457 | F15: 15500 | G15: 13025 | H15: 2475 | I15: 1 | J15: =CONCATENATE("INSERT INTO DOCUMENTOS (NRO_DOCUMENTO,FECHA_EMISION,TOTAL_BRUTO,TOTAL_NETO,TOTAL_IVA, ID_TIPO, RUT_EMPLEADO, ID_CLIENTE) VALUES(",B15,",","TO_DATE('",C15,"'",",'DD-MM-YYYY'),",F15,",",G15,",",H15,",",I15,",","'",D15,"',",E15,");") -> INSERT INTO DOCUMENTOS (NRO_DOCUMENTO,FECHA_EMISION,TOTAL_BRUTO,TOTAL_NETO,TOTAL_IVA, ID_TIPO, RUT_EMPLEADO, ID_CLIENTE) VALUES(11,TO_DATE('02-01-2025','DD-MM-YYYY'),15500,13025,2475,1,'14526149-K',457);
B16: 12 | C16: 02-01-2025 | D16: 14526149-K | E16: 469 | F16: 6500 | G16: 5462 | H16: 1038 | I16: 1 | J16: =CONCATENATE("INSERT INTO DOCUMENTOS (NRO_DOCUMENTO,FECHA_EMISION,TOTAL_BRUTO,TOTAL_NETO,TOTAL_IVA, ID_TIPO, RUT_EMPLEADO, ID_CLIENTE) VALUES(",B16,",","TO_DATE('",C16,"'",",'DD-MM-YYYY'),",F16,",",G16,",",H16,",",I16,",","'",D16,"',",E16,");") -> INSERT INTO DOCUMENTOS (NRO_DOCUMENTO,FECHA_EMISION,TOTAL_BRUTO,TOTAL_NETO,TOTAL_IVA, ID_TIPO, RUT_EMPLEADO, ID_CLIENTE) VALUES(12,TO_DATE('02-01-2025','DD-MM-YYYY'),6500,5462,1038,1,'14526149-K',469);
B17: 13 | C17: 02-01-2025 | D17: 14526149-K | E17: 470 | F17: 6900 | G17: 5798 | H17: 1102 | I17: 1 | J17: =CONCATENATE("INSERT INTO DOCUMENTOS (NRO_DOCUMENTO,FECHA_EMISION,TOTAL_BRUTO,TOTAL_NETO,TOTAL_IVA, ID_TIPO, RUT_EMPLEADO, ID_CLIENTE) VALUES(",B17,",","TO_DATE('",C17,"'",",'DD-MM-YYYY'),",F17,",",G17,",",H17,",",I17,",","'",D17,"',",E17,");") -> INSERT INTO DOCUMENTOS (NRO_DOCUMENTO,FECHA_EMISION,TOTAL_BRUTO,TOTAL_NETO,TOTAL_IVA, ID_TIPO, RUT_EMPLEADO, ID_CLIENTE) VALUES(13,TO_DATE('02-01-2025','DD-MM-YYYY'),6900,5798,1102,1,'14526149-K',470);
... B1559: 1555 | C1559: 18-09-2025 | D1559: 14526149-K | E1559: 166 | F1559: 11000 | G1559: 9244 | H1559: 1756 | I1559: 1 | J1559: =CONCATENATE("INSERT INTO DOCUMENTOS (NRO_DOCUMENTO,FECHA_EMISION,TOTAL_BRUTO,TOTAL_NETO,TOTAL_IVA, ID_TIPO, RUT_EMPLEADO, ID_CLIENTE) VALUES(",B1559,",","TO_DATE('",C1559,"'",",'DD-MM-YYYY'),",F1559,",",G1559,",",H1559,",",I1559,",","'",D1559,"',",E1559,");") -> INSERT INTO DOCUMENTOS (NRO_DOCUMENTO,FECHA_EMISION,TOTAL_BRUTO,TOTAL_NETO,TOTAL_IVA, ID_TIPO, RUT_EMPLEADO, ID_CLIENTE) VALUES(1555,TO_DATE('18-09-2025','DD-MM-YYYY'),11000,9244,1756,1,'14526149-K',166);
A1560: 2 | B1560: 1 | C1560: 04-01-2025 | D1560: 14526149-K | E1560: 413 | F1560: 116990 | G1560: 98311 | H1560: 18679 | I1560: 2 | J1560: =CONCATENATE("INSERT INTO DOCUMENTOS (NRO_DOCUMENTO,FECHA_EMISION,TOTAL_BRUTO,TOTAL_NETO,TOTAL_IVA, ID_TIPO, RUT_EMPLEADO, ID_CLIENTE) VALUES(",B1560,",","TO_DATE('",C1560,"'",",'DD-MM-YYYY'),",F1560,",",G1560,",",H1560,",",I1560,",","'",D1560,"',",E1560,");") -> INSERT INTO DOCUMENTOS (NRO_DOCUMENTO,FECHA_EMISION,TOTAL_BRUTO,TOTAL_NETO,TOTAL_IVA, ID_TIPO, RUT_EMPLEADO, ID_CLIENTE) VALUES(1,TO_DATE('04-01-2025','DD-MM-YYYY'),116990,98311,18679,2,'14526149-K',413);
B1561: 2 | C1561: 06-01-2025 | D1561: 14526149-K | E1561: 185 | F1561: 117100 | G1561: 98404 | H1561: 18696 | I1561: 2 | J1561: =CONCATENATE("INSERT INTO DOCUMENTOS (NRO_DOCUMENTO,FECHA_EMISION,TOTAL_BRUTO,TOTAL_NETO,TOTAL_IVA, ID_TIPO, RUT_EMPLEADO, ID_CLIENTE) VALUES(",B1561,",","TO_DATE('",C1561,"'",",'DD-MM-YYYY'),",F1561,",",G1561,",",H1561,",",I1561,",","'",D1561,"',",E1561,");") -> INSERT INTO DOCUMENTOS (NRO_DOCUMENTO,FECHA_EMISION,TOTAL_BRUTO,TOTAL_NETO,TOTAL_IVA, ID_TIPO, RUT_EMPLEADO, ID_CLIENTE) VALUES(2,TO_DATE('06-01-2025','DD-MM-YYYY'),117100,98404,18696,2,'14526149-K',185);
B1562: 3 | C1562: 08-01-2025 | D1562: 14526149-K | E1562: 125 | F1562: 63852 | G1562: 53658 | H1562: 10194 | I1562: 2 | J1562: =CONCATENATE("INSERT INTO DOCUMENTOS (NRO_DOCUMENTO,FECHA_EMISION,TOTAL_BRUTO,TOTAL_NETO,TOTAL_IVA, ID_TIPO, RUT_EMPLEADO, ID_CLIENTE) VALUES(",B1562,",","TO_DATE('",C1562,"'",",'DD-MM-YYYY'),",F1562,",",G1562,",",H1562,",",I1562,",","'",D1562,"',",E1562,");") -> INSERT INTO DOCUMENTOS (NRO_DOCUMENTO,FECHA_EMISION,TOTAL_BRUTO,TOTAL_NETO,TOTAL_IVA, ID_TIPO, RUT_EMPLEADO, ID_CLIENTE) VALUES(3,TO_DATE('08-01-2025','DD-MM-YYYY'),63852,53658,10194,2,'14526149-K',125);
B1563: 4 | C1563: 11-01-2025 | D1563: 14526149-K | E1563: 203 | F1563: 6000 | G1563: 5042 | H1563: 958 | I1563: 2 | J1563: =CONCATENATE("INSERT INTO DOCUMENTOS (NRO_DOCUMENTO,FECHA_EMISION,TOTAL_BRUTO,TOTAL_NETO,TOTAL_IVA, ID_TIPO, RUT_EMPLEADO, ID_CLIENTE) VALUES(",B1563,",","TO_DATE('",C1563,"'",",'DD-MM-YYYY'),",F1563,",",G1563,",",H1563,",",I1563,",","'",D1563,"',",E1563,");") -> INSERT INTO DOCUMENTOS (NRO_DOCUMENTO,FECHA_EMISION,TOTAL_BRUTO,TOTAL_NETO,TOTAL_IVA, ID_TIPO, RUT_EMPLEADO, ID_CLIENTE) VALUES(4,TO_DATE('11-01-2025','DD-MM-YYYY'),6000,5042,958,2,'14526149-K',203);
B1564: 5 | C1564: 15-01-2025 | D1564: 14526149-K | E1564: 203 | F1564: 38990 | G1564: 32764 | H1564: 6226 | I1564: 2 | J1564: =CONCATENATE("INSERT INTO DOCUMENTOS (NRO_DOCUMENTO,FECHA_EMISION,TOTAL_BRUTO,TOTAL_NETO,TOTAL_IVA, ID_TIPO, RUT_EMPLEADO, ID_CLIENTE) VALUES(",B1564,",","TO_DATE('",C1564,"'",",'DD-MM-YYYY'),",F1564,",",G1564,",",H1564,",",I1564,",","'",D1564,"',",E1564,");") -> INSERT INTO DOCUMENTOS (NRO_DOCUMENTO,FECHA_EMISION,TOTAL_BRUTO,TOTAL_NETO,TOTAL_IVA, ID_TIPO, RUT_EMPLEADO, ID_CLIENTE) VALUES(5,TO_DATE('15-01-2025','DD-MM-YYYY'),38990,32764,6226,2,'14526149-K',203);
B1565: 6 | C1565: 20-01-2025 | D1565: 14526149-K | E1565: 413 | F1565: 126490 | G1565: 106294 | H1565: 20196 | I1565: 2 | J1565: =CONCATENATE("INSERT INTO DOCUMENTOS (NRO_DOCUMENTO,FECHA_EMISION,TOTAL_BRUTO,TOTAL_NETO,TOTAL_IVA, ID_TIPO, RUT_EMPLEADO, ID_CLIENTE) VALUES(",B1565,",","TO_DATE('",C1565,"'",",'DD-MM-YYYY'),",F1565,",",G1565,",",H1565,",",I1565,",","'",D1565,"',",E1565,");") -> INSERT INTO DOCUMENTOS (NRO_DOCUMENTO,FECHA_EMISION,TOTAL_BRUTO,TOTAL_NETO,TOTAL_IVA, ID_TIPO, RUT_EMPLEADO, ID_CLIENTE) VALUES(6,TO_DATE('20-01-2025','DD-MM-YYYY'),126490,106294,20196,2,'14526149-K',413);
B1566: 7 | C1566: 23-01-2025 | D1566: 14526149-K | E1566: 203 | F1566: 3500 | G1566: 2941 | H1566: 559 | I1566: 2 | J1566: =CONCATENATE("INSERT INTO DOCUMENTOS (NRO_DOCUMENTO,FECHA_EMISION,TOTAL_BRUTO,TOTAL_NETO,TOTAL_IVA, ID_TIPO, RUT_EMPLEADO, ID_CLIENTE) VALUES(",B1566,",","TO_DATE('",C1566,"'",",'DD-MM-YYYY'),",F1566,",",G1566,",",H1566,",",I1566,",","'",D1566,"',",E1566,");") -> INSERT INTO DOCUMENTOS (NRO_DOCUMENTO,FECHA_EMISION,TOTAL_BRUTO,TOTAL_NETO,TOTAL_IVA, ID_TIPO, RUT_EMPLEADO, ID_CLIENTE) VALUES(7,TO_DATE('23-01-2025','DD-MM-YYYY'),3500,2941,559,2,'14526149-K',203);
B1567: 8 | C1567: 07-02-2025 | D1567: 14526149-K | E1567: 203 | F1567: 31300 | G1567: 26302 | H1567: 4998 | I1567: 2 | J1567: =CONCATENATE("INSERT INTO DOCUMENTOS (NRO_DOCUMENTO,FECHA_EMISION,TOTAL_BRUTO,TOTAL_NETO,TOTAL_IVA, ID_TIPO, RUT_EMPLEADO, ID_CLIENTE) VALUES(",B1567,",","TO_DATE('",C1567,"'",",'DD-MM-YYYY'),",F1567,",",G1567,",",H1567,",",I1567,",","'",D1567,"',",E1567,");") -> INSERT INTO DOCUMENTOS (NRO_DOCUMENTO,FECHA_EMISION,TOTAL_BRUTO,TOTAL_NETO,TOTAL_IVA, ID_TIPO, RUT_EMPLEADO, ID_CLIENTE) VALUES(8,TO_DATE('07-02-2025','DD-MM-YYYY'),31300,26302,4998,2,'14526149-K',203);
B1568: 9 | C1568: 09-02-2025 | D1568: 14526149-K | E1568: 125 | F1568: 245200 | G1568: 206051 | H1568: 39149 | I1568: 2 | J1568: =CONCATENATE("INSERT INTO DOCUMENTOS (NRO_DOCUMENTO,FECHA_EMISION,TOTAL_BRUTO,TOTAL_NETO,TOTAL_IVA, ID_TIPO, RUT_EMPLEADO, ID_CLIENTE) VALUES(",B1568,",","TO_DATE('",C1568,"'",",'DD-MM-YYYY'),",F1568,",",G1568,",",H1568,",",I1568,",","'",D1568,"',",E1568,");") -> INSERT INTO DOCUMENTOS (NRO_DOCUMENTO,FECHA_EMISION,TOTAL_BRUTO,TOTAL_NETO,TOTAL_IVA, ID_TIPO, RUT_EMPLEADO, ID_CLIENTE) VALUES(9,TO_DATE('09-02-2025','DD-MM-YYYY'),245200,206051,39149,2,'14526149-K',125);
B1569: 10 | C1569: 12-02-2025 | D1569: 14526149-K | E1569: 180 | F1569: 4400 | G1569: 3697 | H1569: 703 | I1569: 2 | J1569: =CONCATENATE("INSERT INTO DOCUMENTOS (NRO_DOCUMENTO,FECHA_EMISION,TOTAL_BRUTO,TOTAL_NETO,TOTAL_IVA, ID_TIPO, RUT_EMPLEADO, ID_CLIENTE) VALUES(",B1569,",","TO_DATE('",C1569,"'",",'DD-MM-YYYY'),",F1569,",",G1569,",",H1569,",",I1569,",","'",D1569,"',",E1569,");") -> INSERT INTO DOCUMENTOS (NRO_DOCUMENTO,FECHA_EMISION,TOTAL_BRUTO,TOTAL_NETO,TOTAL_IVA, ID_TIPO, RUT_EMPLEADO, ID_CLIENTE) VALUES(10,TO_DATE('12-02-2025','DD-MM-YYYY'),4400,3697,703,2,'14526149-K',180);
B1570: 11 | C1570: 12-02-2025 | D1570: 14526149-K | E1570: 413 | F1570: 91990 | G1570: 77303 | H1570: 14687 | I1570: 2 | J1570: =CONCATENATE("INSERT INTO DOCUMENTOS (NRO_DOCUMENTO,FECHA_EMISION,TOTAL_BRUTO,TOTAL_NETO,TOTAL_IVA, ID_TIPO, RUT_EMPLEADO, ID_CLIENTE) VALUES(",B1570,",","TO_DATE('",C1570,"'",",'DD-MM-YYYY'),",F1570,",",G1570,",",H1570,",",I1570,",","'",D1570,"',",E1570,");") -> INSERT INTO DOCUMENTOS (NRO_DOCUMENTO,FECHA_EMISION,TOTAL_BRUTO,TOTAL_NETO,TOTAL_IVA, ID_TIPO, RUT_EMPLEADO, ID_CLIENTE) VALUES(11,TO_DATE('12-02-2025','DD-MM-YYYY'),91990,77303,14687,2,'14526149-K',413);
B1571: 12 | C1571: 14-02-2025 | D1571: 14526149-K | E1571: 203 | F1571: 51490 | G1571: 43268 | H1571: 8222 | I1571: 2 | J1571: =CONCATENATE("INSERT INTO DOCUMENTOS (NRO_DOCUMENTO,FECHA_EMISION,TOTAL_BRUTO,TOTAL_NETO,TOTAL_IVA, ID_TIPO, RUT_EMPLEADO, ID_CLIENTE) VALUES(",B1571,",","TO_DATE('",C1571,"'",",'DD-MM-YYYY'),",F1571,",",G1571,",",H1571,",",I1571,",","'",D1571,"',",E1571,");") -> INSERT INTO DOCUMENTOS (NRO_DOCUMENTO,FECHA_EMISION,TOTAL_BRUTO,TOTAL_NETO,TOTAL_IVA, ID_TIPO, RUT_EMPLEADO, ID_CLIENTE) VALUES(12,TO_DATE('14-02-2025','DD-MM-YYYY'),51490,43268,8222,2,'14526149-K',203);
B1572: 13 | C1572: 20-02-2025 | D1572: 14526149-K | E1572: 180 | F1572: 7300 | G1572: 6135 | H1572: 1165 | I1572: 2 | J1572: =CONCATENATE("INSERT INTO DOCUMENTOS (NRO_DOCUMENTO,FECHA_EMISION,TOTAL_BRUTO,TOTAL_NETO,TOTAL_IVA, ID_TIPO, RUT_EMPLEADO, ID_CLIENTE) VALUES(",B1572,",","TO_DATE('",C1572,"'",",'DD-MM-YYYY'),",F1572,",",G1572,",",H1572,",",I1572,",","'",D1572,"',",E1572,");") -> INSERT INTO DOCUMENTOS (NRO_DOCUMENTO,FECHA_EMISION,TOTAL_BRUTO,TOTAL_NETO,TOTAL_IVA, ID_TIPO, RUT_EMPLEADO, ID_CLIENTE) VALUES(13,TO_DATE('20-02-2025','DD-MM-YYYY'),7300,6135,1165,2,'14526149-K',180);
... B1634: 75 | C1634: 16-09-2025 | D1634: 14526149-K | E1634: 203 | F1634: 63450 | G1634: 53320 | H1634: 10130 | I1634: 2 | J1634: =CONCATENATE("INSERT INTO DOCUMENTOS (NRO_DOCUMENTO,FECHA_EMISION,TOTAL_BRUTO,TOTAL_NETO,TOTAL_IVA, ID_TIPO, RUT_EMPLEADO, ID_CLIENTE) VALUES(",B1634,",","TO_DATE('",C1634,"'",",'DD-MM-YYYY'),",F1634,",",G1634,",",H1634,",",I1634,",","'",D1634,"',",E1634,");") -> INSERT INTO DOCUMENTOS (NRO_DOCUMENTO,FECHA_EMISION,TOTAL_BRUTO,TOTAL_NETO,TOTAL_IVA, ID_TIPO, RUT_EMPLEADO, ID_CLIENTE) VALUES(75,TO_DATE('16-09-2025','DD-MM-YYYY'),63450,53320,10130,2,'14526149-K',203);
A1635: Total general | F1635: 35929330 | G1635: 30193012 | H1635: 5736318 | J1635: COMMIT;

Sheet DETALLE_DOCUMENTOS
A1: Id_Tipo | B1: Nro_Documento | C1: Fecha_Emision | D1: Rut_Empleado | E1: Id_Cliente | F1: Id_Producto | G1: Cantidad | H1: Precio | I1: Valor Bruto | J1: Valor Neto | K1: Valor Iva | L1: Script
A2: 1 | B2: 1 | C2: 02-01-2025 | D2: 14526149-K | E2: 108 | F2: 329 | G2: 1 | H2: 5500 | I2: 5500 | J2: 4622 | K2: 878 | L2: =CONCATENATE("INSERT INTO DETALLES_DOCUMENTO(NRO_DOCUMENTO,ID_TIPO,ID_PRODUCTO,CANTIDAD,PRECIO,VALOR_BRUTO,VALOR_NETO,VALOR_IVA) VALUES(",B2,",",A2,",",F2,",",G2,",",H2,",",I2,",",J2,",",K2,");") -> INSERT INTO DETALLES_DOCUMENTO(NRO_DOCUMENTO,ID_TIPO,ID_PRODUCTO,CANTIDAD,PRECIO,VALOR_BRUTO,VALOR_NETO,VALOR_IVA) VALUES(1,1,329,1,5500,5500,4622,878);
A3: 1 | B3: 1 | C3: 02-01-2025 | D3: 14526149-K | E3: 108 | F3: 382 | G3: 1 | H3: 2600 | I3: 2600 | J3: 2185 | K3: 415 | L3: =CONCATENATE("INSERT INTO DETALLES_DOCUMENTO(NRO_DOCUMENTO,ID_TIPO,ID_PRODUCTO,CANTIDAD,PRECIO,VALOR_BRUTO,VALOR_NETO,VALOR_IVA) VALUES(",B3,",",A3,",",F3,",",G3,",",H3,",",I3,",",J3,",",K3,");") -> INSERT INTO DETALLES_DOCUMENTO(NRO_DOCUMENTO,ID_TIPO,ID_PRODUCTO,CANTIDAD,PRECIO,VALOR_BRUTO,VALOR_NETO,VALOR_IVA) VALUES(1,1,382,1,2600,2600,2185,415);
A4: 1 | B4: 1 | C4: 02-01-2025 | D4: 14526149-K | E4: 108 | F4: 191 | G4: 1 | H4: 2500 | I4: 2500 | J4: 2101 | K4: 399 | L4: =CONCATENATE("INSERT INTO DETALLES_DOCUMENTO(NRO_DOCUMENTO,ID_TIPO,ID_PRODUCTO,CANTIDAD,PRECIO,VALOR_BRUTO,VALOR_NETO,VALOR_IVA) VALUES(",B4,",",A4,",",F4,",",G4,",",H4,",",I4,",",J4,",",K4,");") -> INSERT INTO DETALLES_DOCUMENTO(NRO_DOCUMENTO,ID_TIPO,ID_PRODUCTO,CANTIDAD,PRECIO,VALOR_BRUTO,VALOR_NETO,VALOR_IVA) VALUES(1,1,191,1,2500,2500,2101,399);
A5: 1 | B5: 2 | C5: 02-01-2025 | D5: 14526149-K | E5: 110 | F5: 296 | G5: 2 | H5: 7000 | I5: 14000 | J5: 11765 | K5: 2235 | L5: =CONCATENATE("INSERT INTO DETALLES_DOCUMENTO(NRO_DOCUMENTO,ID_TIPO,ID_PRODUCTO,CANTIDAD,PRECIO,VALOR_BRUTO,VALOR_NETO,VALOR_IVA) VALUES(",B5,",",A5,",",F5,",",G5,",",H5,",",I5,",",J5,",",K5,");") -> INSERT INTO DETALLES_DOCUMENTO(NRO_DOCUMENTO,ID_TIPO,ID_PRODUCTO,CANTIDAD,PRECIO,VALOR_BRUTO,VALOR_NETO,VALOR_IVA) VALUES(2,1,296,2,7000,14000,11765,2235);
A6: 1 | B6: 3 | C6: 02-01-2025 | D6: 14526149-K | E6: 111 | F6: 230 | G6: 1 | H6: 15500 | I6: 15500 | J6: 13025 | K6: 2475 | L6: =CONCATENATE("INSERT INTO DETALLES_DOCUMENTO(NRO_DOCUMENTO,ID_TIPO,ID_PRODUCTO,CANTIDAD,PRECIO,VALOR_BRUTO,VALOR_NETO,VALOR_IVA) VALUES(",B6,",",A6,",",F6,",",G6,",",H6,",",I6,",",J6,",",K6,");") -> INSERT INTO DETALLES_DOCUMENTO(NRO_DOCUMENTO,ID_TIPO,ID_PRODUCTO,CANTIDAD,PRECIO,VALOR_BRUTO,VALOR_NETO,VALOR_IVA) VALUES(3,1,230,1,15500,15500,13025,2475);
A7: 1 | B7: 4 | C7: 02-01-2025 | D7: 14526149-K | E7: 116 | F7: 370 | G7: 1 | H7: 4000 | I7: 4000 | J7: 3361 | K7: 639 | L7: =CONCATENATE("INSERT INTO DETALLES_DOCUMENTO(NRO_DOCUMENTO,ID_TIPO,ID_PRODUCTO,CANTIDAD,PRECIO,VALOR_BRUTO,VALOR_NETO,VALOR_IVA) VALUES(",B7,",",A7,",",F7,",",G7,",",H7,",",I7,",",J7,",",K7,");") -> INSERT INTO DETALLES_DOCUMENTO(NRO_DOCUMENTO,ID_TIPO,ID_PRODUCTO,CANTIDAD,PRECIO,VALOR_BRUTO,VALOR_NETO,VALOR_IVA) VALUES(4,1,370,1,4000,4000,3361,639);
A8: 1 | B8: 4 | C8: 02-01-2025 | D8: 14526149-K | E8: 116 | F8: 383 | G8: 2 | H8: 4800 | I8: 9600 | J8: 8067 | K8: 1533 | L8: =CONCATENATE("INSERT INTO DETALLES_DOCUMENTO(NRO_DOCUMENTO,ID_TIPO,ID_PRODUCTO,CANTIDAD,PRECIO,VALOR_BRUTO,VALOR_NETO,VALOR_IVA) VALUES(",B8,",",A8,",",F8,",",G8,",",H8,",",I8,",",J8,",",K8,");") -> INSERT INTO DETALLES_DOCUMENTO(NRO_DOCUMENTO,ID_TIPO,ID_PRODUCTO,CANTIDAD,PRECIO,VALOR_BRUTO,VALOR_NETO,VALOR_IVA) VALUES(4,1,383,2,4800,9600,8067,1533);
A9: 1 | B9: 4 | C9: 02-01-2025 | D9: 14526149-K | E9: 116 | F9: 165 | G9: 1 | H9: 2000 | I9: 2000 | J9: 1681 | K9: 319 | L9: =CONCATENATE("INSERT INTO DETALLES_DOCUMENTO(NRO_DOCUMENTO,ID_TIPO,ID_PRODUCTO,CANTIDAD,PRECIO,VALOR_BRUTO,VALOR_NETO,VALOR_IVA) VALUES(",B9,",",A9,",",F9,",",G9,",",H9,",",I9,",",J9,",",K9,");") -> INSERT INTO DETALLES_DOCUMENTO(NRO_DOCUMENTO,ID_TIPO,ID_PRODUCTO,CANTIDAD,PRECIO,VALOR_BRUTO,VALOR_NETO,VALOR_IVA) VALUES(4,1,165,1,2000,2000,1681,319);
A10: 1 | B10: 4 | C10: 02-01-2025 | D10: 14526149-K | E10: 116 | F10: 157 | G10: 1 | H10: 4300 | I10: 4300 | J10: 3613 | K10: 687 | L10: =CONCATENATE("INSERT INTO DETALLES_DOCUMENTO(NRO_DOCUMENTO,ID_TIPO,ID_PRODUCTO,CANTIDAD,PRECIO,VALOR_BRUTO,VALOR_NETO,VALOR_IVA) VALUES(",B10,",",A10,",",F10,",",G10,",",H10,",",I10,",",J10,",",K10,");") -> INSERT INTO DETALLES_DOCUMENTO(NRO_DOCUMENTO,ID_TIPO,ID_PRODUCTO,CANTIDAD,PRECIO,VALOR_BRUTO,VALOR_NETO,VALOR_IVA) VALUES(4,1,157,1,4300,4300,3613,687);
A11: 1 | B11: 4 | C11: 02-01-2025 | D11: 14526149-K | E11: 116 | F11: 29 | G11: 1 | H11: 1000 | I11: 1000 | J11: 840 | K11: 160 | L11: =CONCATENATE("INSERT INTO DETALLES_DOCUMENTO(NRO_DOCUMENTO,ID_TIPO,ID_PRODUCTO,CANTIDAD,PRECIO,VALOR_BRUTO,VALOR_NETO,VALOR_IVA) VALUES(",B11,",",A11,",",F11,",",G11,",",H11,",",I11,",",J11,",",K11,");") -> INSERT INTO DETALLES_DOCUMENTO(NRO_DOCUMENTO,ID_TIPO,ID_PRODUCTO,CANTIDAD,PRECIO,VALOR_BRUTO,VALOR_NETO,VALOR_IVA) VALUES(4,1,29,1,1000,1000,840,160);
A12: 1 | B12: 5 | C12: 02-01-2025 | D12: 14526149-K | E12: 119 | F12: 329 | G12: 1 | H12: 5500 | I12: 5500 | J12: 4622 | K12: 878 | L12: =CONCATENATE("INSERT INTO DETALLES_DOCUMENTO(NRO_DOCUMENTO,ID_TIPO,ID_PRODUCTO,CANTIDAD,PRECIO,VALOR_BRUTO,VALOR_NETO,VALOR_IVA) VALUES(",B12,",",A12,",",F12,",",G12,",",H12,",",I12,",",J12,",",K12,");") -> INSERT INTO DETALLES_DOCUMENTO(NRO_DOCUMENTO,ID_TIPO,ID_PRODUCTO,CANTIDAD,PRECIO,VALOR_BRUTO,VALOR_NETO,VALOR_IVA) VALUES(5,1,329,1,5500,5500,4622,878);
A13: 1 | B13: 5 | C13: 02-01-2025 | D13: 14526149-K | E13: 119 | F13: 143 | G13: 1 | H13: 6500 | I13: 6500 | J13: 5462 | K13: 1038 | L13: =CONCATENATE("INSERT INTO DETALLES_DOCUMENTO(NRO_DOCUMENTO,ID_TIPO,ID_PRODUCTO,CANTIDAD,PRECIO,VALOR_BRUTO,VALOR_NETO,VALOR_IVA) VALUES(",B13,",",A13,",",F13,",",G13,",",H13,",",I13,",",J13,",",K13,");") -> INSERT INTO DETALLES_DOCUMENTO(NRO_DOCUMENTO,ID_TIPO,ID_PRODUCTO,CANTIDAD,PRECIO,VALOR_BRUTO,VALOR_NETO,VALOR_IVA) VALUES(5,1,143,1,6500,6500,5462,1038);
... A3617: 2 | B3617: 75 | C3617: 16-09-2025 | D3617: 14526149-K | E3617: 203 | F3617: 171 | G3617: 1 | H3617: 3700 | I3617: 3700 | J3617: 3109 | K3617: 591 | L3617: =CONCATENATE("INSERT INTO DETALLES_DOCUMENTO(NRO_DOCUMENTO,ID_TIPO,ID_PRODUCTO,CANTIDAD,PRECIO,VALOR_BRUTO,VALOR_NETO,VALOR_IVA) VALUES(",B3617,",",A3617,",",F3617,",",G3617,",",H3617,",",I3617,",",J3617,",",K3617,");") -> INSERT INTO DETALLES_DOCUMENTO(NRO_DOCUMENTO,ID_TIPO,ID_PRODUCTO,CANTIDAD,PRECIO,VALOR_BRUTO,VALOR_NETO,VALOR_IVA) VALUES(75,2,171,1,3700,3700,3109,591);
L3618: COMMIT;

Sheet Ventas
A1: Negocio | B1: Vendedor | C1: Fecha Venta | D1: Cliente(a) | E1: Lista Producto | F1: Cantidad | G1: Precio Venta | H1: Total | I1: Status Entrega | J1: Status Pago | K1: Tipo Documento | L1: Número Documento | M1: Precio Neto | N1: Total Venta Neto | O1: Iva | P1: Observacion | Q1: Año | R1: Periodo | S1: Producto Real | T1: Peso Real | V1: Utilidad Bruta | W1: Utilidad Neta | X1: Comision | Y1: Semana | Z1: Dia Venta | AA1: Clasificacion Cliente | AB1: Tipo Cliente | AC1: Sector Cliente | AD1: Comision Pagada | AE1: Medio Pago Comision | AF1: Inventario | AG1: Mes | AH1: Tipo Registro | AI1: Negocio | AJ1: Producto | AK1: Cantidad
A2: Quesos | B2: Fernando Figueroa | C2: 45918 | D2: Fabiola Rojas | E2: Queso Mantecoso / 1000 gramos | F2: 1 | G2: =VLOOKUP(E2,Precios!B$2:N$941,12,FALSE) -> 11000.014 | H2: =G2*F2 -> 11000.014 | I2: Pendiente | J2: Pendiente | K2: Boleta | M2: =G2/1.19 -> 9243.7095 | N2: =H2/1.19 -> 9243.7095 | O2: =H2-N2 -> 1756.3048 | Q2: =YEAR(C2) -> 2025 | R2: =VLOOKUP(MONTH(C2),'Datos Maestros'!M$2:N$14,2,FALSE) -> 45536 | S2: =VLOOKUP(E2,Precios!B$2:W$941,3,FALSE) -> Queso Mantecoso | T2: =VLOOKUP(E2,Precios!B$2:N$941,4,FALSE)*F2 -> 1000 | V2: =VLOOKUP(E2,Precios!B$2:N$941,13,FALSE)*F2 -> 2806.1129 | W2: =V2-X2 -> 2806.1129 | X2: =VLOOKUP(B2,'Datos Maestros'!$C$2:$D$7,2,FALSE)*V2 -> 0 | Y2: =C2-WEEKDAY(C2)+ IF(WEEKDAY(C2)=1,-5,2) -> 45915 | Z2: | | AA2: =VLOOKUP(D2,Clientes!$A$2:$J$486,9,FALSE) -> Regular | AB2: =VLOOKUP(D2,Clientes!$A$2:$K$486,11,FALSE) -> Persona Natural | AC2: =VLOOKUP(D2,Clientes!$A$2:$B$486,2,FALSE) -> Jardin del Eden | AF2: Si | AG2: =R2 -> 45536 | AH2: Ventas | AI2: =A2 -> Quesos | AJ2: =VLOOKUP(E2,Precios!Z$2:AA$941,2,FALSE) -> Queso RUNCA Mantecoso | AK2: =VLOOKUP(E2,Precios!Z$2:BB$941,3,FALSE)*F2 -> -1
A3: Quesos | B3: Fernando Figueroa | C3: 45917 | D3: Fresia Denebola 1064 | E3: Queso Mantecoso / 1000 gramos | F3: 1 | G3: =VLOOKUP(E3,Precios!B$2:N$941,12,FALSE) -> 11000.014 | H3: =G3*F3 -> 11000.014 | I3: Pendiente | J3: Pendiente | K3: Boleta | M3: =G3/1.19 -> 9243.7095 | N3: =H3/1.19 -> 9243.7095 | O3: =H3-N3 -> 1756.3048 | Q3: =YEAR(C3) -> 2025 | R3: =VLOOKUP(MONTH(C3),'Datos Maestros'!M$2:N$14,2,FALSE) -> 45536 | S3: =VLOOKUP(E3,Precios!B$2:W$941,3,FALSE) -> Queso Mantecoso | T3: =VLOOKUP(E3,Precios!B$2:N$941,4,FALSE)*F3 -> 1000 | V3: =VLOOKUP(E3,Precios!B$2:N$941,13,FALSE)*F3 -> 2806.1129 | W3: =V3-X3 -> 2806.1129 | X3: =VLOOKUP(B3,'Datos Maestros'!$C$2:$D$7,2,FALSE)*V3 -> 0 | Y3: =C3-WEEKDAY(C3)+ IF(WEEKDAY(C3)=1,-5,2) -> 45915 | Z3: | | AA3: =VLOOKUP(D3,Clientes!$A$2:$J$486,9,FALSE) -> Frecuente | AB3: =VLOOKUP(D3,Clientes!$A$2:$K$486,11,FALSE) -> Persona Natural | AC3: =VLOOKUP(D3,Clientes!$A$2:$B$486,2,FALSE) -> Sector Diego Portales | AF3: Si | AG3: =R3 -> 45536 | AH3: Ventas | AI3: =A3 -> Quesos | AJ3: =VLOOKUP(E3,Precios!Z$2:AA$941,2,FALSE) -> Queso RUNCA Mantecoso | AK3: =VLOOKUP(E3,Precios!Z$2:BB$941,3,FALSE)*F3 -> -1
A4: Huevos | B4: Fernando Figueroa | C4: 45917 | D4: Carolina Aros | E4: HUEVOS EXTRA 30 Huevos | F4: 1 | G4: =VLOOKUP(E4,Precios!B$2:N$941,12,FALSE) -> 8000.1832 | H4: =G4*F4 -> 8000.1832 | I4: Pendiente | J4: Pendiente | K4: Boleta | M4: =G4/1.19 -> 6722.843 | N4: =H4/1.19 -> 6722.843 | O4: =H4-N4 -> 1277.3402 | Q4: =YEAR(C4) -> 2025 | R4: =VLOOKUP(MONTH(C4),'Datos Maestros'!M$2:N$14,2,FALSE) -> 45536 | S4: =VLOOKUP(E4,Precios!B$2:W$941,3,FALSE) -> Huevos EXTRA | T4: =VLOOKUP(E4,Precios!B$2:N$941,4,FALSE)*F4 -> 0 | V4: =VLOOKUP(E4,Precios!B$2:N$941,13,FALSE)*F4 -> 1151.623 | W4: =V4-X4 -> 1151.623 | X4: =VLOOKUP(B4,'Datos Maestros'!$C$2:$D$7,2,FALSE)*V4 -> 0 | Y4: =C4-WEEKDAY(C4)+ IF(WEEKDAY(C4)=1,-5,2) -> 45915 | Z4: | | AA4: =VLOOKUP(D4,Clientes!$A$2:$J$486,9,FALSE) -> Frecuente | AB4: =VLOOKUP(D4,Clientes!$A$2:$K$486,11,FALSE) -> Persona Natural | AC4: =VLOOKUP(D4,Clientes!$A$2:$B$486,2,FALSE) -> Sector Colombia | AF4: Si | AG4: =R4 -> 45536 | AH4: Ventas | AI4: =A4 -> Huevos | AJ4: =VLOOKUP(E4,Precios!Z$2:AA$941,2,FALSE) -> Bandeja Huevos EXTRA | AK4: =VLOOKUP(E4,Precios!Z$2:BB$941,3,FALSE)*F4 -> -1
A5: Quesos | B5: Fernando Figueroa | C5: 45917 | D5: Carolina Aros | E5: Queso Mantecoso / 500 gramos | F5: 1 | G5: =VLOOKUP(E5,Precios!B$2:N$941,12,FALSE) -> 6000.1548 | H5: =G5*F5 -> 6000.1548 | I5: Pendiente | J5: Pendiente | K5: Boleta | M5: =G5/1.19 -> 5042.1469 | N5: =H5/1.19 -> 5042.1469 | O5: =H5-N5 -> 958.00791 | Q5: =YEAR(C5) -> 2025 | R5: =VLOOKUP(MONTH(C5),'Datos Maestros'!M$2:N$14,2,FALSE) -> 45536 | S5: =VLOOKUP(E5,Precios!B$2:W$941,3,FALSE) -> Queso Mantecoso | T5: =VLOOKUP(E5,Precios!B$2:N$941,4,FALSE)*F5 -> 500 | V5: =VLOOKUP(E5,Precios!B$2:N$941,13,FALSE)*F5 -> 1785.4242 | W5: =V5-X5 -> 1785.4242 | X5: =VLOOKUP(B5,'Datos Maestros'!$C$2:$D$7,2,FALSE)*V5 -> 0 | Y5: =C5-WEEKDAY(C5)+ IF(WEEKDAY(C5)=1,-5,2) -> 45915 | Z5: | | AA5: =VLOOKUP(D5,Clientes!$A$2:$J$486,9,FALSE) -> Frecuente | AB5: =VLOOKUP(D5,Clientes!$A$2:$K$486,11,FALSE) -> Persona Natural | AC5: =VLOOKUP(D5,Clientes!$A$2:$B$486,2,FALSE) -> Sector Colombia | AF5: Si | AG5: =R5 -> 45536 | AH5: Ventas | AI5: =A5 -> Quesos | AJ5: =VLOOKUP(E5,Precios!Z$2:AA$941,2,FALSE) -> Queso RUNCA Mantecoso | AK5: =VLOOKUP(E5,Precios!Z$2:BB$941,3,FALSE)*F5 -> -0.5
A6: Articulos de Aseo | B6: Fernando Figueroa | C6: 45917 | D6: Carolina Aros | E6: 5 Esponja Escalonada | F6: 1 | G6: =VLOOKUP(E6,Precios!B$2:N$941,12,FALSE) -> 1000 | H6: =G6*F6 -> 1000 | I6: Pendiente | J6: Pendiente | K6: Boleta | M6: =G6/1.19 -> 840.33613 | N6: =H6/1.19 -> 840.33613 | O6: =H6-N6 -> 159.66387 | Q6: =YEAR(C6) -> 2025 | R6: =VLOOKUP(MONTH(C6),'Datos Maestros'!M$2:N$14,2,FALSE) -> 45536 | S6: =VLOOKUP(E6,Precios!B$2:W$941,3,FALSE) -> Esponjas | T6: =VLOOKUP(E6,Precios!B$2:N$941,4,FALSE)*F6 -> 0 | V6: =VLOOKUP(E6,Precios!B$2:N$941,13,FALSE)*F6 -> 330.33613 | W6: =V6-X6 -> 330.33613 | X6: =VLOOKUP(B6,'Datos Maestros'!$C$2:$D$7,2,FALSE)*V6 -> 0 | Y6: =C6-WEEKDAY(C6)+ IF(WEEKDAY(C6)=1,-5,2) -> 45915 | Z6: | | AA6: =VLOOKUP(D6,Clientes!$A$2:$J$486,9,FALSE) -> Frecuente | AB6: =VLOOKUP(D6,Clientes!$A$2:$K$486,11,FALSE) -> Persona Natural | AC6: =VLOOKUP(D6,Clientes!$A$2:$B$486,2,FALSE) -> Sector Colombia | AF6: Si | AG6: =R6 -> 45536 | AH6: Ventas | AI6: =A6 -> Articulos de Aseo | AJ6: =VLOOKUP(E6,Precios!Z$2:AA$941,2,FALSE) -> Esponja Acanalada TEDDY | AK6: =VLOOKUP(E6,Precios!Z$2:BB$941,3,FALSE)*F6 -> -5
A7: Articulos de Aseo | B7: Fernando Figueroa | C7: 45917 | D7: Carolina Aros | E7: Pack 3 Jabon Ballerina - 750 ml | F7: 1 | G7: =VLOOKUP(E7,Precios!B$2:N$941,12,FALSE) -> 4500 | H7: =G7*F7 -> 4500 | I7: Pendiente | J7: Pendiente | K7: Boleta | M7: =G7/1.19 -> 3781.5126 | N7: =H7/1.19 -> 3781.5126 | O7: =H7-N7 -> 718.48739 | Q7: =YEAR(C7) -> 2025 | R7: =VLOOKUP(MONTH(C7),'Datos Maestros'!M$2:N$14,2,FALSE) -> 45536 | S7: =VLOOKUP(E7,Precios!B$2:W$941,3,FALSE) -> Jabon Liquido | T7: =VLOOKUP(E7,Precios!B$2:N$941,4,FALSE)*F7 -> 0 | V7: =VLOOKUP(E7,Precios!B$2:N$941,13,FALSE)*F7 -> 988.23529 | W7: =V7-X7 -> 988.23529 | X7: =VLOOKUP(B7,'Datos Maestros'!$C$2:$D$7,2,FALSE)*V7 -> 0 | Y7: =C7-WEEKDAY(C7)+ IF(WEEKDAY(C7)=1,-5,2) -> 45915 | Z7: | | AA7: =VLOOKUP(D7,Clientes!$A$2:$J$486,9,FALSE) -> Frecuente | AB7: =VLOOKUP(D7,Clientes!$A$2:$K$486,11,FALSE) -> Persona Natural | AC7: =VLOOKUP(D7,Clientes!$A$2:$B$486,2,FALSE) -> Sector Colombia | AF7: Si | AG7: =R7 -> 45536 | AH7: Ventas | AI7: =A7 -> Articulos de Aseo | AJ7: =VLOOKUP(E7,Precios!Z$2:AA$941,2,FALSE) -> Jabón Lìquido BALLERINA | AK7: =VLOOKUP(E7,Precios!Z$2:BB$941,3,FALSE)*F7 -> -3
A8: Licores | B8: Fernando Figueroa | C8: 45916 | D8: Fabiola Rojas | E8: Hielo 1 Kilo | F8: 2 | G8: =VLOOKUP(E8,Precios!B$2:N$941,12,FALSE) -> 1000 | H8: =G8*F8 -> 2000 | I8: Entregado | J8: Pendiente | K8: Boleta | M8: =G8/1.19 -> 840.33613 | N8: =H8/1.19 -> 1680.6723 | O8: =H8-N8 -> 319.32773 | Q8: =YEAR(C8) -> 2025 | R8: =VLOOKUP(MONTH(C8),'Datos Maestros'!M$2:N$14,2,FALSE) -> 45536 | S8: =VLOOKUP(E8,Precios!B$2:W$941,3,FALSE) -> Hielo 1 Kilo | T8: =VLOOKUP(E8,Precios!B$2:N$941,4,FALSE)*F8 -> 0 | V8: =VLOOKUP(E8,Precios!B$2:N$941,13,FALSE)*F8 -> 880.67227 | W8: =V8-X8 -> 880.67227 | X8: =VLOOKUP(B8,'Datos Maestros'!$C$2:$D$7,2,FALSE)*V8 -> 0 | Y8: =C8-WEEKDAY(C8)+ IF(WEEKDAY(C8)=1,-5,2) -> 45915 | Z8: | | AA8: =VLOOKUP(D8,Clientes!$A$2:$J$486,9,FALSE) -> Regular | AB8: =VLOOKUP(D8,Clientes!$A$2:$K$486,11,FALSE) -> Persona Natural | AC8: =VLOOKUP(D8,Clientes!$A$2:$B$486,2,FALSE) -> Jardin del Eden | AF8: Si | AG8: =R8 -> 45536 | AH8: Ventas | AI8: =A8 -> Licores | AJ8: =VLOOKUP(E8,Precios!Z$2:AA$941,2,FALSE) -> Hielo 1 Kilo | AK8: =VLOOKUP(E8,Precios!Z$2:BB$941,3,FALSE)*F8 -> -2
A9: Papeleria | B9: Fernando Figueroa | C9: 45916 | D9: Juan Carlos Perez | E9: OFERTA Papel Higiénico ELITE 32 rollos | F9: 1 | G9: =VLOOKUP(E9,Precios!B$2:N$941,12,FALSE) -> 20899.911 | H9: =G9*F9 -> 20899.911 | I9: Pendiente | J9: Pendiente | K9: Boleta | M9: =G9/1.19 -> 17562.951 | N9: =H9/1.19 -> 17562.951 | O9: =H9-N9 -> 3336.9606 | Q9: =YEAR(C9) -> 2025 | R9: =VLOOKUP(MONTH(C9),'Datos Maestros'!M$2:N$14,2,FALSE) -> 45536 | S9: =VLOOKUP(E9,Precios!B$2:W$941,3,FALSE) -> Papel Higiénico ELITE | T9: =VLOOKUP(E9,Precios!B$2:N$941,4,FALSE)*F9 -> 0 | V9: =VLOOKUP(E9,Precios!B$2:N$941,13,FALSE)*F9 -> 3117.9506 | W9: =V9-X9 -> 3117.9506 | X9: =VLOOKUP(B9,'Datos Maestros'!$C$2:$D$7,2,FALSE)*V9 -> 0 | Y9: =C9-WEEKDAY(C9)+ IF(WEEKDAY(C9)=1,-5,2) -> 45915 | Z9: | | AA9: =VLOOKUP(D9,Clientes!$A$2:$J$486,9,FALSE) -> Ocacional | AB9: =VLOOKUP(D9,Clientes!$A$2:$K$486,11,FALSE) -> Persona Natural | AC9: =VLOOKUP(D9,Clientes!$A$2:$B$486,2,FALSE) -> Sector Santa Delia | AF9: Si | AG9: =R9 -> 45536 | AH9: Ventas | AI9: =A9 -> Papeleria | AJ9: =VLOOKUP(E9,Precios!Z$2:AA$941,2,FALSE) -> Papel Higienico ELITE 50 metros | AK9: =VLOOKUP(E9,Precios!Z$2:BB$941,3,FALSE)*F9 -> -8
A10: Derivados | B10: Fernando Figueroa | C10: 45916 | D10: Juan Carlos Perez | E10: Provoleta Parrillera / 135 gramos) | F10: 1 | G10: =VLOOKUP(E10,Precios!B$2:N$941,12,FALSE) -> 2999.6253 | H10: =G10*F10 -> 2999.6253 | I10: Pendiente | J10: Pendiente | K10: Boleta | M10: =G10/1.19 -> 2520.6935 | N10: =H10/1.19 -> 2520.6935 | O10: =H10-N10 -> 478.93177 | Q10: =YEAR(C10) -> 2025 | R10: =VLOOKUP(MONTH(C10),'Datos Maestros'!M$2:N$14,2,FALSE) -> 45536 | S10: =VLOOKUP(E10,Precios!B$2:W$941,3,FALSE) -> Provoleta | T10: =VLOOKUP(E10,Precios!B$2:N$941,4,FALSE)*F10 -> 135 | V10: =VLOOKUP(E10,Precios!B$2:N$941,13,FALSE)*F10 -> 1040.6935 | W10: =V10-X10 -> 1040.6935 | X10: =VLOOKUP(B10,'Datos Maestros'!$C$2:$D$7,2,FALSE)*V10 -> 0 | Y10: =C10-WEEKDAY(C10)+ IF(WEEKDAY(C10)=1,-5,2) -> 45915 | Z10: | | AA10: =VLOOKUP(D10,Clientes!$A$2:$J$486,9,FALSE) -> Ocacional | AB10: =VLOOKUP(D10,Clientes!$A$2:$K$486,11,FALSE) -> Persona Natural | AC10: =VLOOKUP(D10,Clientes!$A$2:$B$486,2,FALSE) -> Sector Santa Delia | AF10: Si | AG10: =R10 -> 45536 | AH10: Ventas | AI10: =A10 -> Derivados | AJ10: =VLOOKUP(E10,Precios!Z$2:AA$941,2,FALSE) -> Provoleta Parrillera | AK10: =VLOOKUP(E10,Precios!Z$2:BB$941,3,FALSE)*F10 -> -1
A11: Quesos | B11: Fernando Figueroa | C11: 45916 | D11: Hector Sepulveda | E11: Queso Mantecoso / 1000 gramos | F11: 1 | G11: =VLOOKUP(E11,Precios!B$2:N$941,12,FALSE) -> 11000.014 | H11: =G11*F11 -> 11000.014 | I11: Pendiente | J11: Pendiente | K11: Boleta | M11: =G11/1.19 -> 9243.7095 | N11: =H11/1.19 -> 9243.7095 | O11: =H11-N11 -> 1756.3048 | Q11: =YEAR(C11) -> 2025 | R11: =VLOOKUP(MONTH(C11),'Datos Maestros'!M$2:N$14,2,FALSE) -> 45536 | S11: =VLOOKUP(E11,Precios!B$2:W$941,3,FALSE) -> Queso Mantecoso | T11: =VLOOKUP(E11,Precios!B$2:N$941,4,FALSE)*F11 -> 1000 | V11: =VLOOKUP(E11,Precios!B$2:N$941,13,FALSE)*F11 -> 2806.1129 | W11: =V11-X11 -> 2806.1129 | X11: =VLOOKUP(B11,'Datos Maestros'!$C$2:$D$7,2,FALSE)*V11 -> 0 | Y11: =C11-WEEKDAY(C11)+ IF(WEEKDAY(C11)=1,-5,2) -> 45915 | Z11: | | AA11: =VLOOKUP(D11,Clientes!$A$2:$J$486,9,FALSE) -> Regular | AB11: =VLOOKUP(D11,Clientes!$A$2:$K$486,11,FALSE) -> Persona Natural | AC11: =VLOOKUP(D11,Clientes!$A$2:$B$486,2,FALSE) -> Jardines de la Viña | AF11: Si | AG11: =R11 -> 45536 | AH11: Ventas | AI11: =A11 -> Quesos | AJ11: =VLOOKUP(E11,Precios!Z$2:AA$941,2,FALSE) -> Queso RUNCA Mantecoso | AK11: =VLOOKUP(E11,Precios!Z$2:BB$941,3,FALSE)*F11 -> -1
A12: Derivados | B12: Fernando Figueroa | C12: 45916 | D12: Judith Pons | E12: 2 x Queso Rueda Sabores / 200 gramos) | F12: 1 | G12: =VLOOKUP(E12,Precios!B$2:N$941,12,FALSE) -> 7000 | H12: =G12*F12 -> 7000 | I12: Entregado | J12: Pagado | K12: Boleta | M12: =G12/1.19 -> 5882.3529 | N12: =H12/1.19 -> 5882.3529 | O12: =H12-N12 -> 1117.6471 | Q12: =YEAR(C12) -> 2025 | R12: =VLOOKUP(MONTH(C12),'Datos Maestros'!M$2:N$14,2,FALSE) -> 45536 | S12: =VLOOKUP(E12,Precios!B$2:W$941,3,FALSE) -> Queso Rueda Sabores | T12: =VLOOKUP(E12,Precios!B$2:N$941,4,FALSE)*F12 -> 200 | V12: =VLOOKUP(E12,Precios!B$2:N$941,13,FALSE)*F12 -> 2080.6723 | W12: =V12-X12 -> 2080.6723 | X12: =VLOOKUP(B12,'Datos Maestros'!$C$2:$D$7,2,FALSE)*V12 -> 0 | Y12: =C12-WEEKDAY(C12)+ IF(WEEKDAY(C12)=1,-5,2) -> 45915 | Z12: | | AA12: =VLOOKUP(D12,Clientes!$A$2:$J$486,9,FALSE) -> Ocacional | AB12: =VLOOKUP(D12,Clientes!$A$2:$K$486,11,FALSE) -> Persona Natural | AC12: =VLOOKUP(D12,Clientes!$A$2:$B$486,2,FALSE) -> Sector Santa Delia | AF12: Si | AG12: =R12 -> 45536 | AH12: Ventas | AI12: =A12 -> Derivados | AJ12: =VLOOKUP(E12,Precios!Z$2:AA$941,2,FALSE) -> Queso Sabores | AK12: =VLOOKUP(E12,Precios!Z$2:BB$941,3,FALSE)*F12 -> -2
A13: Derivados | B13: Fernando Figueroa | C13: 45916 | D13: Judith Pons | E13: Queso Rueda Sabores / 200 gramos) | F13: 1 | G13: =VLOOKUP(E13,Precios!B$2:N$941,12,FALSE) -> 3700 | H13: =G13*F13 -> 3700 | I13: Entregado | J13: Pagado | K13: Boleta | M13: =G13/1.19 -> 3109.2437 | N13: =H13/1.19 -> 3109.2437 | O13: =H13-N13 -> 590.7563 | Q13: =YEAR(C13) -> 2025 | R13: =VLOOKUP(MONTH(C13),'Datos Maestros'!M$2:N$14,2,FALSE) -> 45536 | S13: =VLOOKUP(E13,Precios!B$2:W$941,3,FALSE) -> Queso Rueda Sabores | T13: =VLOOKUP(E13,Precios!B$2:N$941,4,FALSE)*F13 -> 200 | V13: =VLOOKUP(E13,Precios!B$2:N$941,13,FALSE)*F13 -> 1199.1597 | W13: =V13-X13 -> 1199.1597 | X13: =VLOOKUP(B13,'Datos Maestros'!$C$2:$D$7,2,FALSE)*V13 -> 0 | Y13: =C13-WEEKDAY(C13)+ IF(WEEKDAY(C13)=1,-5,2) -> 45915 | Z13: | | AA13: =VLOOKUP(D13,Clientes!$A$2:$J$486,9,FALSE) -> Ocacional | AB13: =VLOOKUP(D13,Clientes!$A$2:$K$486,11,FALSE) -> Persona Natural | AC13: =VLOOKUP(D13,Clientes!$A$2:$B$486,2,FALSE) -> Sector Santa Delia | AF13: Si | AG13: =R13 -> 45536 | AH13: Ventas | AI13: =A13 -> Derivados | AJ13: =VLOOKUP(E13,Precios!Z$2:AA$941,2,FALSE) -> Queso Sabores | AK13: =VLOOKUP(E13,Precios!Z$2:BB$941,3,FALSE)*F13 -> -1
... A33: Huevos | B33: Fernando Figueroa | C33: 45915 | D33: Carla Liebsch | E33: HUEVOS EXTRA 30 Huevos | F33: 3 | G33: =VLOOKUP(E33,Precios!B$2:N$941,12,FALSE) -> 8000.1832 | H33: =G33*F33 -> 24000.55 | I33: Entregado | J33: Pagado | K33: Boleta | M33: =G33/1.19 -> 6722.843 | N33: =H33/1.19 -> 20168.529 | O33: =H33-N33 -> 3832.0205 | Q33: =YEAR(C33) -> 2025 | R33: =VLOOKUP(MONTH(C33),'Datos Maestros'!M$2:N$14,2,FALSE) -> 45536 | S33: =VLOOKUP(E33,Precios!B$2:W$941,3,FALSE) -> Huevos EXTRA | T33: =VLOOKUP(E33,Precios!B$2:N$941,4,FALSE)*F33 -> 0 | V33: =VLOOKUP(E33,Precios!B$2:N$941,13,FALSE)*F33 -> 3454.869 | W33: =V33-X33 -> 3454.869 | X33: =VLOOKUP(B33,'Datos Maestros'!$C$2:$D$7,2,FALSE)*V33 -> 0 | Y33: =C33-WEEKDAY(C33)+ IF(WEEKDAY(C33)=1,-5,2) -> 45915 | Z33: | | AA33: =VLOOKUP(D33,Clientes!$A$2:$J$486,9,FALSE) -> Ocacional | AB33: =VLOOKUP(D33,Clientes!$A$2:$K$486,11,FALSE) -> Persona Natural | AC33: =VLOOKUP(D33,Clientes!$A$2:$B$486,2,FALSE) -> Vicuña Mackena | AF33: Si | AG33: =R33 -> 45536 | AH33: Ventas | AI33: =A33 -> Huevos | AJ33: =VLOOKUP(E33,Precios!Z$2:AA$941,2,FALSE) -> Bandeja Huevos EXTRA | AK33: =VLOOKUP(E33,Precios!Z$2:BB$941,3,FALSE)*F33 -> -3
A34: Articulos de Aseo | B34: Fernando Figueroa | C34: 45915 | D34: NIDO DEL CARPINTERIO SPA | E34: 6 x Bolsa Basura Teddy 45x55 c/asas | F34: 2 | G34: =VLOOKUP(E34,Precios!B$2:N$941,12,FALSE) -> 3000.2682 | H34: =G34*F34 -> 6000.5364 | I34: Entregado | J34: Pendiente | K34: Factura | L34: 111 | M34: =G34/1.19 -> 2521.2338 | N34: =H34/1.19 -> 5042.4676 | O34: =H34-N34 -> 958.06884 | Q34: =YEAR(C34) -> 2025 | R34: =VLOOKUP(MONTH(C34),'Datos Maestros'!M$2:N$14,2,FALSE) -> 45536 | S34: =VLOOKUP(E34,Precios!B$2:W$941,3,FALSE) -> Bolsa Basura | T34: =VLOOKUP(E34,Precios!B$2:N$941,4,FALSE)*F34 -> 0 | V34: =VLOOKUP(E34,Precios!B$2:N$941,13,FALSE)*F34 -> 1658.4676 | W34: =V34-X34 -> 1658.4676 | X34: =VLOOKUP(B34,'Datos Maestros'!$C$2:$D$7,2,FALSE)*V34 -> 0 | Y34: =C34-WEEKDAY(C34)+ IF(WEEKDAY(C34)=1,-5,2) -> 45915 | Z34: | | AA34: =VLOOKUP(D34,Clientes!$A$2:$J$486,9,FALSE) -> regular | AB34: =VLOOKUP(D34,Clientes!$A$2:$K$486,11,FALSE) -> Empresa | AC34: =VLOOKUP(D34,Clientes!$A$2:$B$486,2,FALSE) -> Araucania | AF34: Si | AG34: =R34 -> 45536 | AH34: Ventas | AI34: =A34 -> Articulos de Aseo | AJ34: =VLOOKUP(E34,Precios!Z$2:AA$941,2,FALSE) -> Bolsas Basura TEDDY 45x55 con Asas | AK34: =VLOOKUP(E34,Precios!Z$2:BB$941,3,FALSE)*F34 -> -12
A35: Quesos | B35: Fernando Figueroa | C35: 45915 | D35: Maria José Espinoza | E35: Queso Mantecoso / 1000 gramos | F35: 1 | G35: =VLOOKUP(E35,Precios!B$2:N$941,12,FALSE) -> 11000.014 | H35: =G35*F35 -> 11000.014 | I35: Entregado | J35: Pagado | K35: Boleta | M35: =G35/1.19 -> 9243.7095 | N35: =H35/1.19 -> 9243.7095 | O35: =H35-N35 -> 1756.3048 | Q35: =YEAR(C35) -> 2025 | R35: =VLOOKUP(MONTH(C35),'Datos Maestros'!M$2:N$14,2,FALSE) -> 45536 | S35: =VLOOKUP(E35,Precios!B$2:W$941,3,FALSE) -> Queso Mantecoso | T35: =VLOOKUP(E35,Precios!B$2:N$941,4,FALSE)*F35 -> 1000 | V35: =VLOOKUP(E35,Precios!B$2:N$941,13,FALSE)*F35 -> 2806.1129 | W35: =V35-X35 -> 2806.1129 | X35: =VLOOKUP(B35,'Datos Maestros'!$C$2:$D$7,2,FALSE)*V35 -> 0 | Y35: =C35-WEEKDAY(C35)+ IF(WEEKDAY(C35)=1,-5,2) -> 45915 | Z35: | | AA35: =VLOOKUP(D35,Clientes!$A$2:$J$486,9,FALSE) -> Frecuente | AB35: =VLOOKUP(D35,Clientes!$A$2:$K$486,11,FALSE) -> Persona Natural | AC35: =VLOOKUP(D35,Clientes!$A$2:$B$486,2,FALSE) -> Jardines de la viña | AF35: Si | AG35: =R35 -> 45536 | AH35: Ventas | AI35: =A35 -> Quesos | AJ35: =VLOOKUP(E35,Precios!Z$2:AA$941,2,FALSE) -> Queso RUNCA Mantecoso | AK35: =VLOOKUP(E35,Precios!Z$2:BB$941,3,FALSE)*F35 -> -1
A36: Papeleria | B36: Fernando Figueroa | C36: 45915 | D36: Maria José Espinoza | E36: Pack 2 Toalla NOVA 26 mts | F36: 2 | G36: =VLOOKUP(E36,Precios!B$2:N$941,12,FALSE) -> 1999.9551 | H36: =G36*F36 -> 3999.9102 | I36: Entregado | J36: Pagado | K36: Boleta | M36: =G36/1.19 -> 1680.6345 | N36: =H36/1.19 -> 3361.2691 | O36: =H36-N36 -> 638.64113 | Q36: =YEAR(C36) -> 2025 | R36: =VLOOKUP(MONTH(C36),'Datos Maestros'!M$2:N$14,2,FALSE) -> 45536 | S36: =VLOOKUP(E36,Precios!B$2:W$941,3,FALSE) -> Toalla Nova 26 mts | T36: =VLOOKUP(E36,Precios!B$2:N$941,4,FALSE)*F36 -> 0 | V36: =VLOOKUP(E36,Precios!B$2:N$941,13,FALSE)*F36 -> 1115.2691 | W36: =V36-X36 -> 1115.2691 | X36: =VLOOKUP(B36,'Datos Maestros'!$C$2:$D$7,2,FALSE)*V36 -> 0 | Y36: =C36-WEEKDAY(C36)+ IF(WEEKDAY(C36)=1,-5,2) -> 45915 | Z36: | | AA36: =VLOOKUP(D36,Clientes!$A$2:$J$486,9,FALSE) -> Frecuente | AB36: =VLOOKUP(D36,Clientes!$A$2:$K$486,11,FALSE) -> Persona Natural | AC36: =VLOOKUP(D36,Clientes!$A$2:$B$486,2,FALSE) -> Jardines de la viña | AF36: Si | AG36: =R36 -> 45536 | AH36: Ventas | AI36: =A36 -> Papeleria | AJ36: =VLOOKUP(E36,Precios!Z$2:AA$941,2,FALSE) -> Toalla Papel NOVA 26 metros | AK36: =VLOOKUP(E36,Precios!Z$2:BB$941,3,FALSE)*F36 -> -2
A37: Articulos de Aseo | B37: Fernando Figueroa | C37: 45915 | D37: Maria José Espinoza | E37: 5 Esponja Escalonada | F37: 2 | G37: =VLOOKUP(E37,Precios!B$2:N$941,12,FALSE) -> 1000 | H37: =G37*F37 -> 2000 | I37: Entregado | J37: Pagado | K37: Boleta | M37: =G37/1.19 -> 840.33613 | N37: =H37/1.19 -> 1680.6723 | O37: =H37-N37 -> 319.32773 | Q37: =YEAR(C37) -> 2025 | R37: =VLOOKUP(MONTH(C37),'Datos Maestros'!M$2:N$14,2,FALSE) -> 45536 | S37: =VLOOKUP(E37,Precios!B$2:W$941,3,FALSE) -> Esponjas | T37: =VLOOKUP(E37,Precios!B$2:N$941,4,FALSE)*F37 -> 0 | V37: =VLOOKUP(E37,Precios!B$2:N$941,13,FALSE)*F37 -> 660.67227 | W37: =V37-X37 -> 660.67227 | X37: =VLOOKUP(B37,'Datos Maestros'!$C$2:$D$7,2,FALSE)*V37 -> 0 | Y37: =C37-WEEKDAY(C37)+ IF(WEEKDAY(C37)=1,-5,2) -> 45915 | Z37: | | AA37: =VLOOKUP(D37,Clientes!$A$2:$J$486,9,FALSE) -> Frecuente | AB37: =VLOOKUP(D37,Clientes!$A$2:$K$486,11,FALSE) -> Persona Natural | AC37: =VLOOKUP(D37,Clientes!$A$2:$B$486,2,FALSE) -> Jardines de la viña | AF37: Si | AG37: =R37 -> 45536 | AH37: Ventas | AI37: =A37 -> Articulos de Aseo | AJ37: =VLOOKUP(E37,Precios!Z$2:AA$941,2,FALSE) -> Esponja Acanalada TEDDY | AK37: =VLOOKUP(E37,Precios!Z$2:BB$941,3,FALSE)*F37 -> -10
A38: Papeleria | B38: Fernando Figueroa | C38: 45915 | D38: Maria José Espinoza | E38: OFERTA Papel Higiénico ELITE 32 rollos | F38: 1 | G38: =VLOOKUP(E38,Precios!B$2:N$941,12,FALSE) -> 20899.911 | H38: =G38*F38 -> 20899.911 | I38: Entregado | J38: Pagado | K38: Boleta | M38: =G38/1.19 -> 17562.951 | N38: =H38/1.19 -> 17562.951 | O38: =H38-N38 -> 3336.9606 | Q38: =YEAR(C38) -> 2025 | R38: =VLOOKUP(MONTH(C38),'Datos Maestros'!M$2:N$14,2,FALSE) -> 45536 | S38: =VLOOKUP(E38,Precios!B$2:W$941,3,FALSE) -> Papel Higiénico ELITE | T38: =VLOOKUP(E38,Precios!B$2:N$941,4,FALSE)*F38 -> 0 | V38: =VLOOKUP(E38,Precios!B$2:N$941,13,FALSE)*F38 -> 3117.9506 | W38: =V38-X38 -> 3117.9506 | X38: =VLOOKUP(B38,'Datos Maestros'!$C$2:$D$7,2,FALSE)*V38 -> 0 | Y38: =C38-WEEKDAY(C38)+ IF(WEEKDAY(C38)=1,-5,2) -> 45915 | Z38: | | AA38: =VLOOKUP(D38,Clientes!$A$2:$J$486,9,FALSE) -> Frecuente | AB38: =VLOOKUP(D38,Clientes!$A$2:$K$486,11,FALSE) -> Persona Natural | AC38: =VLOOKUP(D38,Clientes!$A$2:$B$486,2,FALSE) -> Jardines de la viña | AF38: Si | AG38: =R38 -> 45536 | AH38: Ventas | AI38: =A38 -> Papeleria | AJ38: =VLOOKUP(E38,Precios!Z$2:AA$941,2,FALSE) -> Papel Higienico ELITE 50 metros | AK38: =VLOOKUP(E38,Precios!Z$2:BB$941,3,FALSE)*F38 -> -8
A39: Articulos de Aseo | B39: Fernando Figueroa | C39: 45915 | D39: Maria José Espinoza | E39: Pastillas Estanque WC (3 unidades) | F39: 1 | G39: =VLOOKUP(E39,Precios!B$2:N$941,12,FALSE) -> 1500.3974 | H39: =G39*F39 -> 1500.3974 | I39: Entregado | J39: Pagado | K39: Boleta | M39: =G39/1.19 -> 1260.8382 | N39: =H39/1.19 -> 1260.8382 | O39: =H39-N39 -> 239.55925 | Q39: =YEAR(C39) -> 2025 | R39: =VLOOKUP(MONTH(C39),'Datos Maestros'!M$2:N$14,2,FALSE) -> 45536 | S39: =VLOOKUP(E39,Precios!B$2:W$941,3,FALSE) -> WC | T39: =VLOOKUP(E39,Precios!B$2:N$941,4,FALSE)*F39 -> 0 | V39: =VLOOKUP(E39,Precios!B$2:N$941,13,FALSE)*F39 -> 562.83815 | W39: =V39-X39 -> 562.83815 | X39: =VLOOKUP(B39,'Datos Maestros'!$C$2:$D$7,2,FALSE)*V39 -> 0 | Y39: =C39-WEEKDAY(C39)+ IF(WEEKDAY(C39)=1,-5,2) -> 45915 | Z39: | | AA39: =VLOOKUP(D39,Clientes!$A$2:$J$486,9,FALSE) -> Frecuente | AB39: =VLOOKUP(D39,Clientes!$A$2:$K$486,11,FALSE) -> Persona Natural | AC39: =VLOOKUP(D39,Clientes!$A$2:$B$486,2,FALSE) -> Jardines de la viña | AF39: Si | AG39: =R39 -> 45536 | AH39: Ventas | AI39: =A39 -> Articulos de Aseo | AJ39: =VLOOKUP(E39,Precios!Z$2:AA$941,2,FALSE) -> Pastilla para estanque WC | AK39: =VLOOKUP(E39,Precios!Z$2:BB$941,3,FALSE)*F39 -> -1
A40: Articulos de Sanidad | B40: Fernando Figueroa | C40: 45915 | D40: Maria José Espinoza | E40: Caja 100 Guantes NITRILO Talla M | F40: 1 | G40: =VLOOKUP(E40,Precios!B$2:N$941,12,FALSE) -> 4199.902 | H40: =G40*F40 -> 4199.902 | I40: Entregado | J40: Pagado | K40: Boleta | M40: =G40/1.19 -> 3529.3294 | N40: =H40/1.19 -> 3529.3294 | O40: =H40-N40 -> 670.57259 | Q40: =YEAR(C40) -> 2025 | R40: =VLOOKUP(MONTH(C40),'Datos Maestros'!M$2:N$14,2,FALSE) -> 45536 | S40: =VLOOKUP(E40,Precios!B$2:W$941,3,FALSE) -> Guantes NITRILO | T40: =VLOOKUP(E40,Precios!B$2:N$941,4,FALSE)*F40 -> 0 | V40: =VLOOKUP(E40,Precios!B$2:N$941,13,FALSE)*F40 -> 1008.3294 | W40: =V40-X40 -> 1008.3294 | X40: =VLOOKUP(B40,'Datos Maestros'!$C$2:$D$7,2,FALSE)*V40 -> 0 | Y40: =C40-WEEKDAY(C40)+ IF(WEEKDAY(C40)=1,-5,2) -> 45915 | Z40: | | AA40: =VLOOKUP(D40,Clientes!$A$2:$J$486,9,FALSE) -> Frecuente | AB40: =VLOOKUP(D40,Clientes!$A$2:$K$486,11,FALSE) -> Persona Natural | AC40: =VLOOKUP(D40,Clientes!$A$2:$B$486,2,FALSE) -> Jardines de la viña | AF40: Si | AG40: =R40 -> 45536 | AH40: Ventas | AI40: =A40 -> Articulos de Sanidad | AJ40: =VLOOKUP(E40,Precios!Z$2:AA$941,2,FALSE) -> Guante NITRILO Talla M | AK40: =VLOOKUP(E40,Precios!Z$2:BB$941,3,FALSE)*F40 -> -1
A41: Articulos de Sanidad | B41: Fernando Figueroa | C41: 45915 | D41: Maria José Espinoza | E41: Cofias | F41: 1 | G41: =VLOOKUP(E41,Precios!B$2:N$941,12,FALSE) -> 2500 | H41: =G41*F41 -> 2500 | I41: Entregado | J41: Pagado | K41: Boleta | M41: =G41/1.19 -> 2100.8403 | N41: =H41/1.19 -> 2100.8403 | O41: =H41-N41 -> 399.15966 | Q41: =YEAR(C41) -> 2025 | R41: =VLOOKUP(MONTH(C41),'Datos Maestros'!M$2:N$14,2,FALSE) -> 45536 | S41: =VLOOKUP(E41,Precios!B$2:W$941,3,FALSE) -> Cofias | T41: =VLOOKUP(E41,Precios!B$2:N$941,4,FALSE)*F41 -> 0 | V41: =VLOOKUP(E41,Precios!B$2:N$941,13,FALSE)*F41 -> 1000 | W41: =V41-X41 -> 1000 | X41: =VLOOKUP(B41,'Datos Maestros'!$C$2:$D$7,2,FALSE)*V41 -> 0 | Y41: =C41-WEEKDAY(C41)+ IF(WEEKDAY(C41)=1,-5,2) -> 45915 | Z41: | | AA41: =VLOOKUP(D41,Clientes!$A$2:$J$486,9,FALSE) -> Frecuente | AB41: =VLOOKUP(D41,Clientes!$A$2:$K$486,11,FALSE) -> Persona Natural | AC41: =VLOOKUP(D41,Clientes!$A$2:$B$486,2,FALSE) -> Jardines de la viña | AF41: Si | AG41: =R41 -> 45536 | AH41: Ventas | AI41: =A41 -> Articulos de Sanidad | AJ41: =VLOOKUP(E41,Precios!Z$2:AA$941,2,FALSE) -> Cofias | AK41: =VLOOKUP(E41,Precios!Z$2:BB$941,3,FALSE)*F41 -> -1
A42: Articulos de Aseo | B42: Fernando Figueroa | C42: 45915 | D42: Maria José Espinoza | E42: 3 x Bolsa Basura Teddy 70x90 | F42: 1 | G42: =VLOOKUP(E42,Precios!B$2:N$941,12,FALSE) -> 3400.2971 | H42: =G42*F42 -> 3400.2971 | I42: Entregado | J42: Pagado | K42: Boleta | M42: =G42/1.19 -> 2857.3925 | N42: =H42/1.19 -> 2857.3925 | O42: =H42-N42 -> 542.90458 | Q42: =YEAR(C42) -> 2025 | R42: =VLOOKUP(MONTH(C42),'Datos Maestros'!M$2:N$14,2,FALSE) -> 45536 | S42: =VLOOKUP(E42,Precios!B$2:W$941,3,FALSE) -> Bolsa Basura | T42: =VLOOKUP(E42,Precios!B$2:N$941,4,FALSE)*F42 -> 0 | V42: =VLOOKUP(E42,Precios!B$2:N$941,13,FALSE)*F42 -> 1222.3925 | W42: =V42-X42 -> 1222.3925 | X42: =VLOOKUP(B42,'Datos Maestros'!$C$2:$D$7,2,FALSE)*V42 -> 0 | Y42: =C42-WEEKDAY(C42)+ IF(WEEKDAY(C42)=1,-5,2) -> 45915 | Z42: | | AA42: =VLOOKUP(D42,Clientes!$A$2:$J$486,9,FALSE) -> Frecuente | AB42: =VLOOKUP(D42,Clientes!$A$2:$K$486,11,FALSE) -> Persona Natural | AC42: =VLOOKUP(D42,Clientes!$A$2:$B$486,2,FALSE) -> Jardines de la viña | AF42: Si | AG42: =R42 -> 45536 | AH42: Ventas | AI42: =A42 -> Articulos de Aseo | AJ42: =VLOOKUP(E42,Precios!Z$2:AA$941,2,FALSE) -> Bolsas Basura TEDDY 70x90 | AK42: =VLOOKUP(E42,Precios!Z$2:BB$941,3,FALSE)*F42 -> -3
A43: Articulos de Aseo | B43: Fernando Figueroa | C43: 45915 | D43: Rodrigo Toloza | E43: 5 Esponja Escalonada | F43: 1 | G43: =VLOOKUP(E43,Precios!B$2:N$941,12,FALSE) -> 1000 | H43: =G43*F43 -> 1000 | I43: Entregado | J43: Pagado | K43: Boleta | M43: =G43/1.19 -> 840.33613 | N43: =H43/1.19 -> 840.33613 | O43: =H43-N43 -> 159.66387 | Q43: =YEAR(C43) -> 2025 | R43: =VLOOKUP(MONTH(C43),'Datos Maestros'!M$2:N$14,2,FALSE) -> 45536 | S43: =VLOOKUP(E43,Precios!B$2:W$941,3,FALSE) -> Esponjas | T43: =VLOOKUP(E43,Precios!B$2:N$941,4,FALSE)*F43 -> 0 | V43: =VLOOKUP(E43,Precios!B$2:N$941,13,FALSE)*F43 -> 330.33613 | W43: =V43-X43 -> 330.33613 | X43: =VLOOKUP(B43,'Datos Maestros'!$C$2:$D$7,2,FALSE)*V43 -> 0 | Y43: =C43-WEEKDAY(C43)+ IF(WEEKDAY(C43)=1,-5,2) -> 45915 | Z43: | | AA43: =VLOOKUP(D43,Clientes!$A$2:$J$486,9,FALSE) -> Ocacional | AB43: =VLOOKUP(D43,Clientes!$A$2:$K$486,11,FALSE) -> Persona Natural | AC43: =VLOOKUP(D43,Clientes!$A$2:$B$486,2,FALSE) -> Amigos Claudia Herrera | AF43: Si | AG43: =R43 -> 45536 | AH43: Ventas | AI43: =A43 -> Articulos de Aseo | AJ43: =VLOOKUP(E43,Precios!Z$2:AA$941,2,FALSE) -> Esponja Acanalada TEDDY | AK43: =VLOOKUP(E43,Precios!Z$2:BB$941,3,FALSE)*F43 -> -5
A44: Articulos de Aseo | B44: Fernando Figueroa | C44: 45915 | D44: Rodrigo Toloza | E44: Jabon Ballerina - 750 ml | F44: 1 | G44: =VLOOKUP(E44,Precios!B$2:N$941,12,FALSE) -> 1650.365 | H44: =G44*F44 -> 1650.365 | I44: Entregado | J44: Pagado | K44: Boleta | M44: =G44/1.19 -> 1386.8613 | N44: =H44/1.19 -> 1386.8613 | O44: =H44-N44 -> 263.50365 | Q44: =YEAR(C44) -> 2025 | R44: =VLOOKUP(MONTH(C44),'Datos Maestros'!M$2:N$14,2,FALSE) -> 45536 | S44: =VLOOKUP(E44,Precios!B$2:W$941,3,FALSE) -> Jabon Liquido | T44: =VLOOKUP(E44,Precios!B$2:N$941,4,FALSE)*F44 -> 0 | V44: =VLOOKUP(E44,Precios!B$2:N$941,13,FALSE)*F44 -> 436.86131 | W44: =V44-X44 -> 436.86131 | X44: =VLOOKUP(B44,'Datos Maestros'!$C$2:$D$7,2,FALSE)*V44 -> 0 | Y44: =C44-WEEKDAY(C44)+ IF(WEEKDAY(C44)=1,-5,2) -> 45915 | Z44: | | AA44: =VLOOKUP(D44,Clientes!$A$2:$J$486,9,FALSE) -> Ocacional | AB44: =VLOOKUP(D44,Clientes!$A$2:$K$486,11,FALSE) -> Persona Natural | AC44: =VLOOKUP(D44,Clientes!$A$2:$B$486,2,FALSE) -> Amigos Claudia Herrera | AF44: Si | AG44: =R44 -> 45536 | AH44: Ventas | AI44: =A44 -> Articulos de Aseo | AJ44: =VLOOKUP(E44,Precios!Z$2:AA$941,2,FALSE) -> Jabón Lìquido BALLERINA | AK44: =VLOOKUP(E44,Precios!Z$2:BB$941,3,FALSE)*F44 -> -3
A45: Articulos de Aseo | B45: Fernando Figueroa | C45: 45915 | D45: Rodrigo Toloza | E45: Pasta Diente Pepsodent 3x2 | F45: 1 | G45: =VLOOKUP(E45,Precios!B$2:N$941,12,FALSE) -> 3400 | H45: =G45*F45 -> 3400 | I45: Entregado | J45: Pagado | K45: Boleta | M45: =G45/1.19 -> 2857.1429 | N45: =H45/1.19 -> 2857.1429 | O45: =H45-N45 -> 542.85714 | Q45: =YEAR(C45) -> 2025 | R45: =VLOOKUP(MONTH(C45),'Datos Maestros'!M$2:N$14,2,FALSE) -> 45536 | S45: =VLOOKUP(E45,Precios!B$2:W$941,3,FALSE) -> Pasta de dientes | T45: =VLOOKUP(E45,Precios!B$2:N$941,4,FALSE)*F45 -> 0 | V45: =VLOOKUP(E45,Precios!B$2:N$941,13,FALSE)*F45 -> 571.42857 | W45: =V45-X45 -> 571.42857 | X45: =VLOOKUP(B45,'Datos Maestros'!$C$2:$D$7,2,FALSE)*V45 -> 0 | Y45: =C45-WEEKDAY(C45)+ IF(WEEKDAY(C45)=1,-5,2) -> 45915 | Z45: | | AA45: =VLOOKUP(D45,Clientes!$A$2:$J$486,9,FALSE) -> Ocacional | AB45: =VLOOKUP(D45,Clientes!$A$2:$K$486,11,FALSE) -> Persona Natural | AC45: =VLOOKUP(D45,Clientes!$A$2:$B$486,2,FALSE) -> Amigos Claudia Herrera | AF45: Si | AG45: =R45 -> 45536 | AH45: Ventas | AI45: =A45 -> Articulos de Aseo | AJ45: =VLOOKUP(E45,Precios!Z$2:AA$941,2,FALSE) -> Pasta de Dientes | AK45: =VLOOKUP(E45,Precios!Z$2:BB$941,3,FALSE)*F45 -> -1
A46: Papeleria | B46: Fernando Figueroa | C46: 45915 | D46: Amanda Pacheco | E46: OFERTA Papel Higiénico ELITE 24 rollos | F46: 1 | G46: =VLOOKUP(E46,Precios!B$2:N$941,12,FALSE) -> 16500.237 | H46: =G46*F46 -> 16500.237 | I46: Entregado | J46: Pendiente | K46: Boleta | M46: =G46/1.19 -> 13865.745 | N46: =H46/1.19 -> 13865.745 | O46: =H46-N46 -> 2634.4916 | Q46: =YEAR(C46) -> 2025 | R46: =VLOOKUP(MONTH(C46),'Datos Maestros'!M$2:N$14,2,FALSE) -> 45536 | S46: =VLOOKUP(E46,Precios!B$2:W$941,3,FALSE) -> Papel Higiénico ELITE | T46: =VLOOKUP(E46,Precios!B$2:N$941,4,FALSE)*F46 -> 0 | V46: =VLOOKUP(E46,Precios!B$2:N$941,13,FALSE)*F46 -> 3031.7452 | W46: =V46-X46 -> 3031.7452 | X46: =VLOOKUP(B46,'Datos Maestros'!$C$2:$D$7,2,FALSE)*V46 -> 0 | Y46: =C46-WEEKDAY(C46)+ IF(WEEKDAY(C46)=1,-5,2) -> 45915 | Z46: | | AA46: =VLOOKUP(D46,Clientes!$A$2:$J$486,9,FALSE) -> Ocacional | AB46: =VLOOKUP(D46,Clientes!$A$2:$K$486,11,FALSE) -> Persona Natural | AC46: =VLOOKUP(D46,Clientes!$A$2:$B$486,2,FALSE) -> Jardin del eden | AF46: Si | AG46: =R46 -> 45536 | AH46: Ventas | AI46: =A46 -> Papeleria | AJ46: =VLOOKUP(E46,Precios!Z$2:AA$941,2,FALSE) -> Papel Higienico ELITE 50 metros | AK46: =VLOOKUP(E46,Precios!Z$2:BB$941,3,FALSE)*F46 -> -6
... A147: Longanizas | B147: Fernando Figueroa | C147: 45909 | D147: Mabel Romero | E147: Longanizas VILLABLANCA / 1 Kilo | F147: 1 | G147: =VLOOKUP(E147,Precios!B$2:N$941,12,FALSE) -> 8200.2359 | H147: =G147*F147 -> 8200.2359 | I147: Entregado | J147: Pagado | K147: Boleta | M147: =G147/1.19 -> 6890.9545 | N147: =H147/1.19 -> 6890.9545 | O147: =H147-N147 -> 1309.2814 | Q147: =YEAR(C147) -> 2025 | R147: =VLOOKUP(MONTH(C147),'Datos Maestros'!M$2:N$14,2,FALSE) -> 45536 | S147: =VLOOKUP(E147,Precios!B$2:W$941,3,FALSE) -> Longanizas | T147: =VLOOKUP(E147,Precios!B$2:N$941,4,FALSE)*F147 -> 1 | V147: =VLOOKUP(E147,Precios!B$2:N$941,13,FALSE)*F147 -> 1632.4671 | W147: =V147-X147 -> 1632.4671 | X147: =VLOOKUP(B147,'Datos Maestros'!$C$2:$D$7,2,FALSE)*V147 -> 0 | Y147: =C147-WEEKDAY(C147)+ IF(WEEKDAY(C147)=1,-5,2) -> 45908 | Z147: | | AA147: =VLOOKUP(D147,Clientes!$A$2:$J$486,9,FALSE) -> Frecuente | AB147: =VLOOKUP(D147,Clientes!$A$2:$K$486,11,FALSE) -> Persona Natural | AC147: =VLOOKUP(D147,Clientes!$A$2:$B$486,2,FALSE) -> Curso Amalia | AF147: Si | AG147: =R147 -> 45536 | AH147: Ventas | AI147: =A147 -> Longanizas | AJ147: =VLOOKUP(E147,Precios!Z$2:AA$941,2,FALSE) -> Longanizas VILLABLANCA | AK147: =VLOOKUP(E147,Precios!Z$2:BB$941,3,FALSE)*F147 -> -1
A148: Film Plastico-Aluminio | B148: Fernando Figueroa | C148: 45909 | D148: Restaurante Los Naranjos | E148: Film Plástico 1.400 Metros | F148: 2 | G148: =VLOOKUP(E148,Precios!B$2:N$941,12,FALSE) -> 24000 | H148: =G148*F148 -> 48000 | I148: Entregado | J148: Pendiente | K148: Factura | L148: 110 | M148: =G148/1.19 -> 20168.067 | N148: =H148/1.19 -> 40336.134 | O148: =H148-N148 -> 7663.8655 | Q148: =YEAR(C148) -> 2025 | R148: =VLOOKUP(MONTH(C148),'Datos Maestros'!M$2:N$14,2,FALSE) -> 45536 | S148: =VLOOKUP(E148,Precios!B$2:W$941,3,FALSE) -> Film Plastico | T148: =VLOOKUP(E148,Precios!B$2:N$941,4,FALSE)*F148 -> 0 | V148: =VLOOKUP(E148,Precios!B$2:N$941,13,FALSE)*F148 -> 13722.689 | W148: =V148-X148 -> 13722.689 | X148: =VLOOKUP(B148,'Datos Maestros'!$C$2:$D$7,2,FALSE)*V148 -> 0 | Y148: =C148-WEEKDAY(C148)+ IF(WEEKDAY(C148)=1,-5,2) -> 45908 | Z148: | | AA148: =VLOOKUP(D148,Clientes!$A$2:$J$486,9,FALSE) -> Frecuente | AB148: =VLOOKUP(D148,Clientes!$A$2:$K$486,11,FALSE) -> Empresa | AC148: =VLOOKUP(D148,Clientes!$A$2:$B$486,2,FALSE) -> Departamental | AF148: Si | AG148: =R148 -> 45536 | AH148: Ventas | AI148: =A148 -> Film Plastico-Aluminio | AJ148: =VLOOKUP(E148,Precios!Z$2:AA$941,2,FALSE) -> Film Plástico 1400 metros | AK148: =VLOOKUP(E148,Precios!Z$2:BB$941,3,FALSE)*F148 -> -2
A149: Film Plastico-Aluminio | B149: Fernando Figueroa | C149: 45909 | D149: Restaurante Los Naranjos | E149: Descuentos | F149: 1 | G149: -1000 | H149: =G149*F149 -> -1000 | I149: Entregado | J149: Pendiente | K149: Factura | L149: 110 | M149: =G149/1.19 -> -840.33613 | N149: =H149/1.19 -> -840.33613 | O149: =H149-N149 -> -159.66387 | Q149: =YEAR(C149) -> 2025 | R149: =VLOOKUP(MONTH(C149),'Datos Maestros'!M$2:N$14,2,FALSE) -> 45536 | S149: =VLOOKUP(E149,Precios!B$2:W$941,3,FALSE) -> Descuentos | T149: =VLOOKUP(E149,Precios!B$2:N$941,4,FALSE)*F149 -> 1000 | V149: -1000 | W149: =V149-X149 -> -1000 | X149: =VLOOKUP(B149,'Datos Maestros'!$C$2:$D$7,2,FALSE)*V149 -> 0 | Y149: =C149-WEEKDAY(C149)+ IF(WEEKDAY(C149)=1,-5,2) -> 45908 | Z149: | | AA149: =VLOOKUP(D149,Clientes!$A$2:$J$486,9,FALSE) -> Frecuente | AB149: =VLOOKUP(D149,Clientes!$A$2:$K$486,11,FALSE) -> Empresa | AC149: =VLOOKUP(D149,Clientes!$A$2:$B$486,2,FALSE) -> Departamental | AF149: Si | AG149: =R149 -> 45536 | AH149: Ventas | AI149: =A149 -> Film Plastico-Aluminio | AJ149: =VLOOKUP(E149,Precios!Z$2:AA$941,2,FALSE) -> Descuentos | AK149: =VLOOKUP(E149,Precios!Z$2:BB$941,3,FALSE)*F149 -> -1
A150: Articulos de Sanidad | B150: Fernando Figueroa | C150: 45909 | D150: Restaurante Los Naranjos | E150: Caja 100 Guantes NITRILO Talla L | F150: 2 | G150: =VLOOKUP(E150,Precios!B$2:N$941,12,FALSE) -> 4199.902 | H150: =G150*F150 -> 8399.804 | I150: Entregado | J150: Pendiente | K150: Factura | L150: 110 | M150: =G150/1.19 -> 3529.3294 | N150: =H150/1.19 -> 7058.6588 | O150: =H150-N150 -> 1341.1452 | Q150: =YEAR(C150) -> 2025 | R150: =VLOOKUP(MONTH(C150),'Datos Maestros'!M$2:N$14,2,FALSE) -> 45536 | S150: =VLOOKUP(E150,Precios!B$2:W$941,3,FALSE) -> Guantes NITRILO | T150: =VLOOKUP(E150,Precios!B$2:N$941,4,FALSE)*F150 -> 0 | V150: =VLOOKUP(E150,Precios!B$2:N$941,13,FALSE)*F150 -> 2016.6588 | W150: =V150-X150 -> 2016.6588 | X150: =VLOOKUP(B150,'Datos Maestros'!$C$2:$D$7,2,FALSE)*V150 -> 0 | Y150: =C150-WEEKDAY(C150)+ IF(WEEKDAY(C150)=1,-5,2) -> 45908 | Z150: | | AA150: =VLOOKUP(D150,Clientes!$A$2:$J$486,9,FALSE) -> Frecuente | AB150: =VLOOKUP(D150,Clientes!$A$2:$K$486,11,FALSE) -> Empresa | AC150: =VLOOKUP(D150,Clientes!$A$2:$B$486,2,FALSE) -> Departamental | AF150: Si | AG150: =R150 -> 45536 | AH150: Ventas | AI150: =A150 -> Articulos de Sanidad | AJ150: =VLOOKUP(E150,Precios!Z$2:AA$941,2,FALSE) -> Guante NITRILO Talla L | AK150: =VLOOKUP(E150,Precios!Z$2:BB$941,3,FALSE)*F150 -> -2
A151: Papeleria | B151: Fernando Figueroa | C151: 45909 | D151: Restaurante Los Naranjos | E151: Toalla Papel Jumbo 250 mts (Pack 2) | F151: 3 | G151: =VLOOKUP(E151,Precios!B$2:N$941,12,FALSE) -> 9500.0304 | H151: =G151*F151 -> 28500.091 | I151: Entregado | J151: Pendiente | K151: Factura | L151: 110 | M151: =G151/1.19 -> 7983.2188 | N151: =H151/1.19 -> 23949.656 | O151: =H151-N151 -> 4550.4347 | Q151: =YEAR(C151) -> 2025 | R151: =VLOOKUP(MONTH(C151),'Datos Maestros'!M$2:N$14,2,FALSE) -> 45536 | S151: =VLOOKUP(E151,Precios!B$2:W$941,3,FALSE) -> Toalla Papel Soft Quality | T151: =VLOOKUP(E151,Precios!B$2:N$941,4,FALSE)*F151 -> 0 | V151: =VLOOKUP(E151,Precios!B$2:N$941,13,FALSE)*F151 -> 8193.6565 | W151: =V151-X151 -> 8193.6565 | X151: =VLOOKUP(B151,'Datos Maestros'!$C$2:$D$7,2,FALSE)*V151 -> 0 | Y151: =C151-WEEKDAY(C151)+ IF(WEEKDAY(C151)=1,-5,2) -> 45908 | Z151: | | AA151: =VLOOKUP(D151,Clientes!$A$2:$J$486,9,FALSE) -> Frecuente | AB151: =VLOOKUP(D151,Clientes!$A$2:$K$486,11,FALSE) -> Empresa | AC151: =VLOOKUP(D151,Clientes!$A$2:$B$486,2,FALSE) -> Departamental | AF151: Si | AG151: =R151 -> 45536 | AH151: Ventas | AI151: =A151 -> Papeleria | AJ151: =VLOOKUP(E151,Precios!Z$2:AA$941,2,FALSE) -> Toalla Papel 250 metros dipensador | AK151: =VLOOKUP(E151,Precios!Z$2:BB$941,3,FALSE)*F151 -> -3
A152: Papeleria | B152: Fernando Figueroa | C152: 45909 | D152: Restaurante Los Naranjos | E152: OFERTA Papel Higiénico SWAN 50 mts d/h 32 rollos | F152: 1 | G152: =VLOOKUP(E152,Precios!B$2:N$941,12,FALSE) -> 19900.217 | H152: =G152*F152 -> 19900.217 | I152: Entregado | J152: Pendiente | K152: Factura | L152: 110 | M152: =G152/1.19 -> 16722.872 | N152: =H152/1.19 -> 16722.872 | O152: =H152-N152 -> 3177.3456 | Q152: =YEAR(C152) -> 2025 | R152: =VLOOKUP(MONTH(C152),'Datos Maestros'!M$2:N$14,2,FALSE) -> 45536 | S152: =VLOOKUP(E152,Precios!B$2:W$941,3,FALSE) -> Papel Higiénico SWAN | T152: =VLOOKUP(E152,Precios!B$2:N$941,4,FALSE)*F152 -> 0 | V152: =VLOOKUP(E152,Precios!B$2:N$941,13,FALSE)*F152 -> 4253.9641 | W152: =V152-X152 -> 4253.9641 | X152: =VLOOKUP(B152,'Datos Maestros'!$C$2:$D$7,2,FALSE)*V152 -> 0 | Y152: =C152-WEEKDAY(C152)+ IF(WEEKDAY(C152)=1,-5,2) -> 45908 | Z152: | | AA152: =VLOOKUP(D152,Clientes!$A$2:$J$486,9,FALSE) -> Frecuente | AB152: =VLOOKUP(D152,Clientes!$A$2:$K$486,11,FALSE) -> Empresa | AC152: =VLOOKUP(D152,Clientes!$A$2:$B$486,2,FALSE) -> Departamental | AF152: Si | AG152: =R152 -> 45536 | AH152: Ventas | AI152: =A152 -> Papeleria | AJ152: =VLOOKUP(E152,Precios!Z$2:AA$941,2,FALSE) -> Papel Higienico SWAN 50 metros | AK152: =VLOOKUP(E152,Precios!Z$2:BB$941,3,FALSE)*F152 -> -8
A153: Articulos de Aseo | B153: Fernando Figueroa | C153: 45909 | D153: Sandra Arriagada | E153: Pack 3 Jabon Ballerina - 750 ml | F153: 1 | G153: =VLOOKUP(E153,Precios!B$2:N$941,12,FALSE) -> 4500 | H153: =G153*F153 -> 4500 | I153: Entregado | J153: Pagado | K153: Boleta | M153: =G153/1.19 -> 3781.5126 | N153: =H153/1.19 -> 3781.5126 | O153: =H153-N153 -> 718.48739 | Q153: =YEAR(C153) -> 2025 | R153: =VLOOKUP(MONTH(C153),'Datos Maestros'!M$2:N$14,2,FALSE) -> 45536 | S153: =VLOOKUP(E153,Precios!B$2:W$941,3,FALSE) -> Jabon Liquido | T153: =VLOOKUP(E153,Precios!B$2:N$941,4,FALSE)*F153 -> 0 | V153: =VLOOKUP(E153,Precios!B$2:N$941,13,FALSE)*F153 -> 988.23529 | W153: =V153-X153 -> 988.23529 | X153: =VLOOKUP(B153,'Datos Maestros'!$C$2:$D$7,2,FALSE)*V153 -> 0 | Y153: =C153-WEEKDAY(C153)+ IF(WEEKDAY(C153)=1,-5,2) -> 45908 | Z153: | | AA153: =VLOOKUP(D153,Clientes!$A$2:$J$486,9,FALSE) -> Ocacional | AB153: =VLOOKUP(D153,Clientes!$A$2:$K$486,11,FALSE) -> Persona Natural | AC153: =VLOOKUP(D153,Clientes!$A$2:$B$486,2,FALSE) -> Santa Amalia | AF153: Si | AG153: =R153 -> 45536 | AH153: Ventas | AI153: =A153 -> Articulos de Aseo | AJ153: =VLOOKUP(E153,Precios!Z$2:AA$941,2,FALSE) -> Jabón Lìquido BALLERINA | AK153: =VLOOKUP(E153,Precios!Z$2:BB$941,3,FALSE)*F153 -> -3
A154: Articulos de Aseo | B154: Fernando Figueroa | C154: 45909 | D154: Sandra Arriagada | E154: Jabon Popeye- 170 g | F154: 1 | G154: =VLOOKUP(E154,Precios!B$2:N$941,12,FALSE) -> 1200.1376 | H154: =G154*F154 -> 1200.1376 | I154: Entregado | J154: Pagado | K154: Boleta | M154: =G154/1.19 -> 1008.519 | N154: =H154/1.19 -> 1008.519 | O154: =H154-N154 -> 191.6186 | Q154: =YEAR(C154) -> 2025 | R154: =VLOOKUP(MONTH(C154),'Datos Maestros'!M$2:N$14,2,FALSE) -> 45536 | S154: =VLOOKUP(E154,Precios!B$2:W$941,3,FALSE) -> Jabon POPEYE | T154: =VLOOKUP(E154,Precios!B$2:N$941,4,FALSE)*F154 -> 0 | V154: =VLOOKUP(E154,Precios!B$2:N$941,13,FALSE)*F154 -> 275.32567 | W154: =V154-X154 -> 275.32567 | X154: =VLOOKUP(B154,'Datos Maestros'!$C$2:$D$7,2,FALSE)*V154 -> 0 | Y154: =C154-WEEKDAY(C154)+ IF(WEEKDAY(C154)=1,-5,2) -> 45908 | Z154: | | AA154: =VLOOKUP(D154,Clientes!$A$2:$J$486,9,FALSE) -> Ocacional | AB154: =VLOOKUP(D154,Clientes!$A$2:$K$486,11,FALSE) -> Persona Natural | AC154: =VLOOKUP(D154,Clientes!$A$2:$B$486,2,FALSE) -> Santa Amalia | AF154: Si | AG154: =R154 -> 45536 | AH154: Ventas | AI154: =A154 -> Articulos de Aseo | AJ154: =VLOOKUP(E154,Precios!Z$2:AA$941,2,FALSE) -> Jabón Lìquido BALLERINA | AK154: =VLOOKUP(E154,Precios!Z$2:BB$941,3,FALSE)*F154 -> -1
A155: Detergentes | B155: Fernando Figueroa | C155: 45909 | D155: Sandra Arriagada | E155: Cloro Gel / 5 Litros | F155: 1 | G155: =VLOOKUP(E155,Precios!B$2:N$941,12,FALSE) -> 3500 | H155: =G155*F155 -> 3500 | I155: Entregado | J155: Pagado | K155: Boleta | M155: =G155/1.19 -> 2941.1765 | N155: =H155/1.19 -> 2941.1765 | O155: =H155-N155 -> 558.82353 | Q155: =YEAR(C155) -> 2025 | R155: =VLOOKUP(MONTH(C155),'Datos Maestros'!M$2:N$14,2,FALSE) -> 45536 | S155: =VLOOKUP(E155,Precios!B$2:W$941,3,FALSE) -> Cloro Gel | T155: =VLOOKUP(E155,Precios!B$2:N$941,4,FALSE)*F155 -> 5 | V155: =VLOOKUP(E155,Precios!B$2:N$941,13,FALSE)*F155 -> 1016.8067 | W155: =V155-X155 -> 1016.8067 | X155: =VLOOKUP(B155,'Datos Maestros'!$C$2:$D$7,2,FALSE)*V155 -> 0 | Y155: =C155-WEEKDAY(C155)+ IF(WEEKDAY(C155)=1,-5,2) -> 45908 | Z155: | | AA155: =VLOOKUP(D155,Clientes!$A$2:$J$486,9,FALSE) -> Ocacional | AB155: =VLOOKUP(D155,Clientes!$A$2:$K$486,11,FALSE) -> Persona Natural | AC155: =VLOOKUP(D155,Clientes!$A$2:$B$486,2,FALSE) -> Santa Amalia | AF155: Si | AG155: =R155 -> 45536 | AH155: Ventas | AI155: =A155 -> Detergentes | AJ155: =VLOOKUP(E155,Precios!Z$2:AA$941,2,FALSE) -> Cloro GEL SPUM 5 Litros | AK155: =VLOOKUP(E155,Precios!Z$2:BB$941,3,FALSE)*F155 -> -1
A156: Detergentes | B156: Fernando Figueroa | C156: 45909 | D156: Sandra Arriagada | E156: Cloro / 5 Litros | F156: 1 | G156: =VLOOKUP(E156,Precios!B$2:N$941,12,FALSE) -> 2000 | H156: =G156*F156 -> 2000 | I156: Entregado | J156: Pagado | K156: Boleta | M156: =G156/1.19 -> 1680.6723 | N156: =H156/1.19 -> 1680.6723 | O156: =H156-N156 -> 319.32773 | Q156: =YEAR(C156) -> 2025 | R156: =VLOOKUP(MONTH(C156),'Datos Maestros'!M$2:N$14,2,FALSE) -> 45536 | S156: =VLOOKUP(E156,Precios!B$2:W$941,3,FALSE) -> Cloro | T156: =VLOOKUP(E156,Precios!B$2:N$941,4,FALSE)*F156 -> 5 | V156: =VLOOKUP(E156,Precios!B$2:N$941,13,FALSE)*F156 -> 756.30252 | W156: =V156-X156 -> 756.30252 | X156: =VLOOKUP(B156,'Datos Maestros'!$C$2:$D$7,2,FALSE)*V156 -> 0 | Y156: =C156-WEEKDAY(C156)+ IF(WEEKDAY(C156)=1,-5,2) -> 45908 | Z156: | | AA156: =VLOOKUP(D156,Clientes!$A$2:$J$486,9,FALSE) -> Ocacional | AB156: =VLOOKUP(D156,Clientes!$A$2:$K$486,11,FALSE) -> Persona Natural | AC156: =VLOOKUP(D156,Clientes!$A$2:$B$486,2,FALSE) -> Santa Amalia | AF156: Si | AG156: =R156 -> 45536 | AH156: Ventas | AI156: =A156 -> Detergentes | AJ156: =VLOOKUP(E156,Precios!Z$2:AA$941,2,FALSE) -> Cloro SPUM 5 Litros | AK156: =VLOOKUP(E156,Precios!Z$2:BB$941,3,FALSE)*F156 -> -1
A157: Detergentes | B157: Fernando Figueroa | C157: 45909 | D157: Sandra Arriagada | E157: Detergente Premium / 5 Litros | F157: 1 | G157: =VLOOKUP(E157,Precios!B$2:N$941,12,FALSE) -> 3500 | H157: =G157*F157 -> 3500 | I157: Entregado | J157: Pagado | K157: Boleta | M157: =G157/1.19 -> 2941.1765 | N157: =H157/1.19 -> 2941.1765 | O157: =H157-N157 -> 558.82353 | Q157: =YEAR(C157) -> 2025 | R157: =VLOOKUP(MONTH(C157),'Datos Maestros'!M$2:N$14,2,FALSE) -> 45536 | S157: =VLOOKUP(E157,Precios!B$2:W$941,3,FALSE) -> Detergente Premium | T157: =VLOOKUP(E157,Precios!B$2:N$941,4,FALSE)*F157 -> 5 | V157: =VLOOKUP(E157,Precios!B$2:N$941,13,FALSE)*F157 -> 764.70588 | W157: =V157-X157 -> 764.70588 | X157: =VLOOKUP(B157,'Datos Maestros'!$C$2:$D$7,2,FALSE)*V157 -> 0 | Y157: =C157-WEEKDAY(C157)+ IF(WEEKDAY(C157)=1,-5,2) -> 45908 | Z157: | | AA157: =VLOOKUP(D157,Clientes!$A$2:$J$486,9,FALSE) -> Ocacional | AB157: =VLOOKUP(D157,Clientes!$A$2:$K$486,11,FALSE) -> Persona Natural | AC157: =VLOOKUP(D157,Clientes!$A$2:$B$486,2,FALSE) -> Santa Amalia | AF157: Si | AG157: =R157 -> 45536 | AH157: Ventas | AI157: =A157 -> Detergentes | AJ157: =VLOOKUP(E157,Precios!Z$2:AA$941,2,FALSE) -> Detergente SPUM 5 Litros (Verde) | AK157: =VLOOKUP(E157,Precios!Z$2:BB$941,3,FALSE)*F157 -> -1
A158: Papeleria | B158: Fernando Figueroa | C158: 45909 | D158: Sandra Arriagada | E158: Pack 3 Toalla Jumbo SWAN D/H / 100 metros | F158: 1 | G158: =VLOOKUP(E158,Precios!B$2:N$941,12,FALSE) -> 9499.8792 | H158: =G158*F158 -> 9499.8792 | I158: Entregado | J158: Pagado | K158: Boleta | M158: =G158/1.19 -> 7983.0918 | N158: =H158/1.19 -> 7983.0918 | O158: =H158-N158 -> 1516.7874 | Q158: =YEAR(C158) -> 2025 | R158: =VLOOKUP(MONTH(C158),'Datos Maestros'!M$2:N$14,2,FALSE) -> 45536 | S158: =VLOOKUP(E158,Precios!B$2:W$941,3,FALSE) -> Toalla Papel SWAN | T158: =VLOOKUP(E158,Precios!B$2:N$941,4,FALSE)*F158 -> 100 | V158: =VLOOKUP(E158,Precios!B$2:N$941,13,FALSE)*F158 -> 2695.0918 | W158: =V158-X158 -> 2695.0918 | X158: =VLOOKUP(B158,'Datos Maestros'!$C$2:$D$7,2,FALSE)*V158 -> 0 | Y158: =C158-WEEKDAY(C158)+ IF(WEEKDAY(C158)=1,-5,2) -> 45908 | Z158: | | AA158: =VLOOKUP(D158,Clientes!$A$2:$J$486,9,FALSE) -> Ocacional | AB158: =VLOOKUP(D158,Clientes!$A$2:$K$486,11,FALSE) -> Persona Natural | AC158: =VLOOKUP(D158,Clientes!$A$2:$B$486,2,FALSE) -> Santa Amalia | AF158: Si | AG158: =R158 -> 45536 | AH158: Ventas | AI158: =A158 -> Papeleria | AJ158: =VLOOKUP(E158,Precios!Z$2:AA$941,2,FALSE) -> Toalla Papel SWAN D/H NARANJA 100 metros | AK158: =VLOOKUP(E158,Precios!Z$2:BB$941,3,FALSE)*F158 -> -3
A159: Papeleria | B159: Fernando Figueroa | C159: 45909 | D159: Sandra Arriagada | E159: Pack 2 Toalla NOVA 26 mts | F159: 3 | G159: =VLOOKUP(E159,Precios!B$2:N$941,12,FALSE) -> 1999.9551 | H159: =G159*F159 -> 5999.8653 | I159: Entregado | J159: Pagado | K159: Boleta | M159: =G159/1.19 -> 1680.6345 | N159: =H159/1.19 -> 5041.9036 | O159: =H159-N159 -> 957.96169 | Q159: =YEAR(C159) -> 2025 | R159: =VLOOKUP(MONTH(C159),'Datos Maestros'!M$2:N$14,2,FALSE) -> 45536 | S159: =VLOOKUP(E159,Precios!B$2:W$941,3,FALSE) -> Toalla Nova 26 mts | T159: =VLOOKUP(E159,Precios!B$2:N$941,4,FALSE)*F159 -> 0 | V159: =VLOOKUP(E159,Precios!B$2:N$941,13,FALSE)*F159 -> 1672.9036 | W159: =V159-X159 -> 1672.9036 | X159: =VLOOKUP(B159,'Datos Maestros'!$C$2:$D$7,2,FALSE)*V159 -> 0 | Y159: =C159-WEEKDAY(C159)+ IF(WEEKDAY(C159)=1,-5,2) -> 45908 | Z159: | | AA159: =VLOOKUP(D159,Clientes!$A$2:$J$486,9,FALSE) -> Ocacional | AB159: =VLOOKUP(D159,Clientes!$A$2:$K$486,11,FALSE) -> Persona Natural | AC159: =VLOOKUP(D159,Clientes!$A$2:$B$486,2,FALSE) -> Santa Amalia | AF159: Si | AG159: =R159 -> 45536 | AH159: Ventas | AI159: =A159 -> Papeleria | AJ159: =VLOOKUP(E159,Precios!Z$2:AA$941,2,FALSE) -> Toalla Papel NOVA 26 metros | AK159: =VLOOKUP(E159,Precios!Z$2:BB$941,3,FALSE)*F159 -> -3
A160: Papeleria | B160: Fernando Figueroa | C160: 45909 | D160: Loreto Zambrano | E160: OFERTA Papel Higiénico ELITE 32 rollos | F160: 1 | G160: =VLOOKUP(E160,Precios!B$2:N$941,12,FALSE) -> 20899.911 | H160: =G160*F160 -> 20899.911 | I160: Entregado | J160: Pagado | K160: Boleta | M160: =G160/1.19 -> 17562.951 | N160: =H160/1.19 -> 17562.951 | O160: =H160-N160 -> 3336.9606 | Q160: =YEAR(C160) -> 2025 | R160: =VLOOKUP(MONTH(C160),'Datos Maestros'!M$2:N$14,2,FALSE) -> 45536 | S160: =VLOOKUP(E160,Precios!B$2:W$941,3,FALSE) -> Papel Higiénico ELITE | T160: =VLOOKUP(E160,Precios!B$2:N$941,4,FALSE)*F160 -> 0 | V160: =VLOOKUP(E160,Precios!B$2:N$941,13,FALSE)*F160 -> 3117.9506 | W160: =V160-X160 -> 3117.9506 | X160: =VLOOKUP(B160,'Datos Maestros'!$C$2:$D$7,2,FALSE)*V160 -> 0 | Y160: =C160-WEEKDAY(C160)+ IF(WEEKDAY(C160)=1,-5,2) -> 45908 | Z160: | | AA160: =VLOOKUP(D160,Clientes!$A$2:$J$486,9,FALSE) -> Frecuente | AB160: =VLOOKUP(D160,Clientes!$A$2:$K$486,11,FALSE) -> Persona Natural | AC160: =VLOOKUP(D160,Clientes!$A$2:$B$486,2,FALSE) -> Jardin del Eden | AF160: Si | AG160: =R160 -> 45536 | AH160: Ventas | AI160: =A160 -> Papeleria | AJ160: =VLOOKUP(E160,Precios!Z$2:AA$941,2,FALSE) -> Papel Higienico ELITE 50 metros | AK160: =VLOOKUP(E160,Precios!Z$2:BB$941,3,FALSE)*F160 -> -8
A161: Papeleria | B161: Fernando Figueroa | C161: 45909 | D161: Loreto Zambrano | E161: Pack 4 Toalla NOVA 70 mts | F161: 1 | G161: =VLOOKUP(E161,Precios!B$2:N$941,12,FALSE) -> 11499.715 | H161: =G161*F161 -> 11499.715 | I161: Entregado | J161: Pagado | K161: Boleta | M161: =G161/1.19 -> 9663.626 | N161: =H161/1.19 -> 9663.626 | O161: =H161-N161 -> 1836.0889 | Q161: =YEAR(C161) -> 2025 | R161: =VLOOKUP(MONTH(C161),'Datos Maestros'!M$2:N$14,2,FALSE) -> 45536 | S161: =VLOOKUP(E161,Precios!B$2:W$941,3,FALSE) -> Toalla Nova 70 mts | T161: =VLOOKUP(E161,Precios!B$2:N$941,4,FALSE)*F161 -> 0 | V161: =VLOOKUP(E161,Precios!B$2:N$941,13,FALSE)*F161 -> 2883.626 | W161: =V161-X161 -> 2883.626 | X161: =VLOOKUP(B161,'Datos Maestros'!$C$2:$D$7,2,FALSE)*V161 -> 0 | Y161: =C161-WEEKDAY(C161)+ IF(WEEKDAY(C161)=1,-5,2) -> 45908 | Z161: | | AA161: =VLOOKUP(D161,Clientes!$A$2:$J$486,9,FALSE) -> Frecuente | AB161: =VLOOKUP(D161,Clientes!$A$2:$K$486,11,FALSE) -> Persona Natural | AC161: =VLOOKUP(D161,Clientes!$A$2:$B$486,2,FALSE) -> Jardin del Eden | AF161: Si | AG161: =R161 -> 45536 | AH161: Ventas | AI161: =A161 -> Papeleria | AJ161: =VLOOKUP(E161,Precios!Z$2:AA$941,2,FALSE) -> Toalla Papel NOVA 70 metros | AK161: =VLOOKUP(E161,Precios!Z$2:BB$941,3,FALSE)*F161 -> -4
A162: Articulos de Aseo | B162: Fernando Figueroa | C162: 45909 | D162: Loreto Zambrano | E162: Toalla desinfectantes 50 Unidades | F162: 4 | G162: =VLOOKUP(E162,Precios!B$2:N$941,12,FALSE) -> 2700.0077 | H162: =G162*F162 -> 10800.031 | I162: Entregado | J162: Pagado | K162: Boleta | M162: =G162/1.19 -> 2268.914 | N162: =H162/1.19 -> 9075.656 | O162: =H162-N162 -> 1724.3746 | Q162: =YEAR(C162) -> 2025 | R162: =VLOOKUP(MONTH(C162),'Datos Maestros'!M$2:N$14,2,FALSE) -> 45536 | S162: =VLOOKUP(E162,Precios!B$2:W$941,3,FALSE) -> Toalla desinfectantes | T162: =VLOOKUP(E162,Precios!B$2:N$941,4,FALSE)*F162 -> 0 | V162: =VLOOKUP(E162,Precios!B$2:N$941,13,FALSE)*F162 -> 3159.6896 | W162: =V162-X162 -> 3159.6896 | X162: =VLOOKUP(B162,'Datos Maestros'!$C$2:$D$7,2,FALSE)*V162 -> 0 | Y162: =C162-WEEKDAY(C162)+ IF(WEEKDAY(C162)=1,-5,2) -> 45908 | Z162: | | AA162: =VLOOKUP(D162,Clientes!$A$2:$J$486,9,FALSE) -> Frecuente | AB162: =VLOOKUP(D162,Clientes!$A$2:$K$486,11,FALSE) -> Persona Natural | AC162: =VLOOKUP(D162,Clientes!$A$2:$B$486,2,FALSE) -> Jardin del Eden | AF162: Si | AG162: =R162 -> 45536 | AH162: Ventas | AI162: =A162 -> Articulos de Aseo | AJ162: =VLOOKUP(E162,Precios!Z$2:AA$941,2,FALSE) -> Toalla desinfectante IGENIX 50 unidades | AK162: =VLOOKUP(E162,Precios!Z$2:BB$941,3,FALSE)*F162 -> -4
A163: Papeleria | B163: Fernando Figueroa | C163: 45909 | D163: Loreto Zambrano | E163: Pack 3 Servilleta / 300 unidades c/u | F163: 1 | G163: =VLOOKUP(E163,Precios!B$2:N$941,12,FALSE) -> 5000.3257 | H163: =G163*F163 -> 5000.3257 | I163: Entregado | J163: Pagado | K163: Boleta | M163: =G163/1.19 -> 4201.9544 | N163: =H163/1.19 -> 4201.9544 | O163: =H163-N163 -> 798.37134 | Q163: =YEAR(C163) -> 2025 | R163: =VLOOKUP(MONTH(C163),'Datos Maestros'!M$2:N$14,2,FALSE) -> 45536 | S163: =VLOOKUP(E163,Precios!B$2:W$941,3,FALSE) -> Servilletas | T163: =VLOOKUP(E163,Precios!B$2:N$941,4,FALSE)*F163 -> 300 | V163: =VLOOKUP(E163,Precios!B$2:N$941,13,FALSE)*F163 -> 2008.9544 | W163: =V163-X163 -> 2008.9544 | X163: =VLOOKUP(B163,'Datos Maestros'!$C$2:$D$7,2,FALSE)*V163 -> 0 | Y163: =C163-WEEKDAY(C163)+ IF(WEEKDAY(C163)=1,-5,2) -> 45908 | Z163: | | AA163: =VLOOKUP(D163,Clientes!$A$2:$J$486,9,FALSE) -> Frecuente | AB163: =VLOOKUP(D163,Clientes!$A$2:$K$486,11,FALSE) -> Persona Natural | AC163: =VLOOKUP(D163,Clientes!$A$2:$B$486,2,FALSE) -> Jardin del Eden | AF163: Si | AG163: =R163 -> 45536 | AH163: Ventas | AI163: =A163 -> Papeleria | AJ163: =VLOOKUP(E163,Precios!Z$2:AA$941,2,FALSE) -> Servilletas SOFTQUALITY 300 unidades | AK163: =VLOOKUP(E163,Precios!Z$2:BB$941,3,FALSE)*F163 -> -3
A164: Articulos de Aseo | B164: Fernando Figueroa | C164: 45909 | D164: Loreto Zambrano | E164: 3 x Bolsa Basura Teddy 45x55 c/asas | F164: 1 | G164: =VLOOKUP(E164,Precios!B$2:N$941,12,FALSE) -> 1650.3934 | H164: =G164*F164 -> 1650.3934 | I164: Entregado | J164: Pagado | K164: Boleta | M164: =G164/1.19 -> 1386.8852 | N164: =H164/1.19 -> 1386.8852 | O164: =H164-N164 -> 263.5082 | Q164: =YEAR(C164) -> 2025 | R164: =VLOOKUP(MONTH(C164),'Datos Maestros'!M$2:N$14,2,FALSE) -> 45536 | S164: =VLOOKUP(E164,Precios!B$2:W$941,3,FALSE) -> Bolsa Basura | T164: =VLOOKUP(E164,Precios!B$2:N$941,4,FALSE)*F164 -> 0 | V164: =VLOOKUP(E164,Precios!B$2:N$941,13,FALSE)*F164 -> 540.88525 | W164: =V164-X164 -> 540.88525 | X164: =VLOOKUP(B164,'Datos Maestros'!$C$2:$D$7,2,FALSE)*V164 -> 0 | Y164: =C164-WEEKDAY(C164)+ IF(WEEKDAY(C164)=1,-5,2) -> 45908 | Z164: | | AA164: =VLOOKUP(D164,Clientes!$A$2:$J$486,9,FALSE) -> Frecuente | AB164: =VLOOKUP(D164,Clientes!$A$2:$K$486,11,FALSE) -> Persona Natural | AC164: =VLOOKUP(D164,Clientes!$A$2:$B$486,2,FALSE) -> Jardin del Eden | AF164: Si | AG164: =R164 -> 45536 | AH164: Ventas | AI164: =A164 -> Articulos de Aseo | AJ164: =VLOOKUP(E164,Precios!Z$2:AA$941,2,FALSE) -> Bolsas Basura TEDDY 45x55 con Asas | AK164: =VLOOKUP(E164,Precios!Z$2:BB$941,3,FALSE)*F164 -> -3
... A176: Quesos | B176: Fernando Figueroa | C176: 45908 | D176: Geraldine Espinoza | E176: Queso Mantecoso / 1000 gramos | F176: 1 | G176: =VLOOKUP(E176,Precios!B$2:N$941,12,FALSE) -> 11000.014 | H176: =G176*F176 -> 11000.014 | I176: Entregado | J176: Pagado | K176: Boleta | M176: =G176/1.19 -> 9243.7095 | N176: =H176/1.19 -> 9243.7095 | O176: =H176-N176 -> 1756.3048 | Q176: =YEAR(C176) -> 2025 | R176: =VLOOKUP(MONTH(C176),'Datos Maestros'!M$2:N$14,2,FALSE) -> 45536 | S176: =VLOOKUP(E176,Precios!B$2:W$941,3,FALSE) -> Queso Mantecoso | T176: =VLOOKUP(E176,Precios!B$2:N$941,4,FALSE)*F176 -> 1000 | V176: =VLOOKUP(E176,Precios!B$2:N$941,13,FALSE)*F176 -> 2806.1129 | W176: =V176-X176 -> 2806.1129 | X176: =VLOOKUP(B176,'Datos Maestros'!$C$2:$D$7,2,FALSE)*V176 -> 0 | Y176: =C176-WEEKDAY(C176)+ IF(WEEKDAY(C176)=1,-5,2) -> 45908 | Z176: | | AA176: =VLOOKUP(D176,Clientes!$A$2:$J$486,9,FALSE) -> Ocacional | AB176: =VLOOKUP(D176,Clientes!$A$2:$K$486,11,FALSE) -> Persona Natural | AC176: =VLOOKUP(D176,Clientes!$A$2:$B$486,2,FALSE) -> Jardines de la viña | AF176: Si | AG176: =R176 -> 45536 | AH176: Ventas | AI176: =A176 -> Quesos | AJ176: =VLOOKUP(E176,Precios!Z$2:AA$941,2,FALSE) -> Queso RUNCA Mantecoso | AK176: =VLOOKUP(E176,Precios!Z$2:BB$941,3,FALSE)*F176 -> -1
A177: Huevos | B177: Fernando Figueroa | C177: 45907 | D177: Maria Angelica Vera | E177: HUEVOS EXTRA 30 Huevos | F177: 1 | G177: =VLOOKUP(E177,Precios!B$2:N$941,12,FALSE) -> 8000.1832 | H177: =G177*F177 -> 8000.1832 | I177: Entregado | J177: Pagado | K177: Boleta | L177: 182 | M177: =G177/1.19 -> 6722.843 | N177: =H177/1.19 -> 6722.843 | O177: =H177-N177 -> 1277.3402 | Q177: =YEAR(C177) -> 2025 | R177: =VLOOKUP(MONTH(C177),'Datos Maestros'!M$2:N$14,2,FALSE) -> 45536 | S177: =VLOOKUP(E177,Precios!B$2:W$941,3,FALSE) -> Huevos EXTRA | T177: =VLOOKUP(E177,Precios!B$2:N$941,4,FALSE)*F177 -> 0 | V177: =VLOOKUP(E177,Precios!B$2:N$941,13,FALSE)*F177 -> 1151.623 | W177: =V177-X177 -> 1151.623 | X177: =VLOOKUP(B177,'Datos Maestros'!$C$2:$D$7,2,FALSE)*V177 -> 0 | Y177: =C177-WEEKDAY(C177)+ IF(WEEKDAY(C177)=1,-5,2) -> 45901 | Z177: | | AA177: =VLOOKUP(D177,Clientes!$A$2:$J$486,9,FALSE) -> Frecuente | AB177: =VLOOKUP(D177,Clientes!$A$2:$K$486,11,FALSE) -> Persona Natural | AC177: =VLOOKUP(D177,Clientes!$A$2:$B$486,2,FALSE) -> Jardines de la Viña | AF177: Si | AG177: =R177 -> 45536 | AH177: Ventas | AI177: =A177 -> Huevos | AJ177: =VLOOKUP(E177,Precios!Z$2:AA$941,2,FALSE) -> Bandeja Huevos EXTRA | AK177: =VLOOKUP(E177,Precios!Z$2:BB$941,3,FALSE)*F177 -> -1
A178: Articulos de Aseo | B178: Fernando Figueroa | C178: 45907 | D178: INAM TOUR EIRL | E178: Trapero Húmedo VIRGINIA | F178: 1 | G178: =VLOOKUP(E178,Precios!B$2:N$941,12,FALSE) -> 2750 | H178: =G178*F178 -> 2750 | I178: Entregado | J178: Pendiente | K178: Factura | M178: =G178/1.19 -> 2310.9244 | N178: =H178/1.19 -> 2310.9244 | O178: =H178-N178 -> 439.07563 | Q178: =YEAR(C178) -> 2025 | R178: =VLOOKUP(MONTH(C178),'Datos Maestros'!M$2:N$14,2,FALSE) -> 45536 | S178: =VLOOKUP(E178,Precios!B$2:W$941,3,FALSE) -> Trapero Húmedo | T178: =VLOOKUP(E178,Precios!B$2:N$941,4,FALSE)*F178 -> 0 | V178: =VLOOKUP(E178,Precios!B$2:N$941,13,FALSE)*F178 -> 663.86555 | W178: =V178-X178 -> 663.86555 | X178: =VLOOKUP(B178,'Datos Maestros'!$C$2:$D$7,2,FALSE)*V178 -> 0 | Y178: =C178-WEEKDAY(C178)+ IF(WEEKDAY(C178)=1,-5,2) -> 45901 | Z178: | | AA178: =VLOOKUP(D178,Clientes!$A$2:$J$486,9,FALSE) -> Frecuente | AB178: =VLOOKUP(D178,Clientes!$A$2:$K$486,11,FALSE) -> Empresa | AC178: =VLOOKUP(D178,Clientes!$A$2:$B$486,2,FALSE) -> Jardines de la viña | AF178: Si | AG178: =R178 -> 45536 | AH178: Ventas | AI178: =A178 -> Articulos de Aseo | AJ178: =VLOOKUP(E178,Precios!Z$2:AA$941,2,FALSE) -> Traperos Humedos VIRGINIA | AK178: =VLOOKUP(E178,Precios!Z$2:BB$941,3,FALSE)*F178 -> -1
A179: Articulos de Aseo | B179: Fernando Figueroa | C179: 45907 | D179: INAM TOUR EIRL | E179: Toalla desinfectantes 50 Unidades | F179: 1 | G179: =VLOOKUP(E179,Precios!B$2:N$941,12,FALSE) -> 2700.0077 | H179: =G179*F179 -> 2700.0077 | I179: Entregado | J179: Pendiente | K179: Factura | M179: =G179/1.19 -> 2268.914 | N179: =H179/1.19 -> 2268.914 | O179: =H179-N179 -> 431.09366 | Q179: =YEAR(C179) -> 2025 | R179: =VLOOKUP(MONTH(C179),'Datos Maestros'!M$2:N$14,2,FALSE) -> 45536 | S179: =VLOOKUP(E179,Precios!B$2:W$941,3,FALSE) -> Toalla desinfectantes | T179: =VLOOKUP(E179,Precios!B$2:N$941,4,FALSE)*F179 -> 0 | V179: =VLOOKUP(E179,Precios!B$2:N$941,13,FALSE)*F179 -> 789.92241 | W179: =V179-X179 -> 789.92241 | X179: =VLOOKUP(B179,'Datos Maestros'!$C$2:$D$7,2,FALSE)*V179 -> 0 | Y179: =C179-WEEKDAY(C179)+ IF(WEEKDAY(C179)=1,-5,2) -> 45901 | Z179: | | AA179: =VLOOKUP(D179,Clientes!$A$2:$J$486,9,FALSE) -> Frecuente | AB179: =VLOOKUP(D179,Clientes!$A$2:$K$486,11,FALSE) -> Empresa | AC179: =VLOOKUP(D179,Clientes!$A$2:$B$486,2,FALSE) -> Jardines de la viña | AF179: Si | AG179: =R179 -> 45536 | AH179: Ventas | AI179: =A179 -> Articulos de Aseo | AJ179: =VLOOKUP(E179,Precios!Z$2:AA$941,2,FALSE) -> Toalla desinfectante IGENIX 50 unidades | AK179: =VLOOKUP(E179,Precios!Z$2:BB$941,3,FALSE)*F179 -> -1
A180: Articulos de Aseo | B180: Fernando Figueroa | C180: 45907 | D180: INAM TOUR EIRL | E180: 3 x Bolsa Basura Teddy 50x70 | F180: 1 | G180: =VLOOKUP(E180,Precios!B$2:N$941,12,FALSE) -> 1800.17 | H180: =G180*F180 -> 1800.17 | I180: Entregado | J180: Pendiente | K180: Factura | M180: =G180/1.19 -> 1512.7479 | N180: =H180/1.19 -> 1512.7479 | O180: =H180-N180 -> 287.4221 | Q180: =YEAR(C180) -> 2025 | R180: =VLOOKUP(MONTH(C180),'Datos Maestros'!M$2:N$14,2,FALSE) -> 45536 | S180: =VLOOKUP(E180,Precios!B$2:W$941,3,FALSE) -> Bolsa Basura | T180: =VLOOKUP(E180,Precios!B$2:N$941,4,FALSE)*F180 -> 0 | V180: =VLOOKUP(E180,Precios!B$2:N$941,13,FALSE)*F180 -> 711.74788 | W180: =V180-X180 -> 711.74788 | X180: =VLOOKUP(B180,'Datos Maestros'!$C$2:$D$7,2,FALSE)*V180 -> 0 | Y180: =C180-WEEKDAY(C180)+ IF(WEEKDAY(C180)=1,-5,2) -> 45901 | Z180: | | AA180: =VLOOKUP(D180,Clientes!$A$2:$J$486,9,FALSE) -> Frecuente | AB180: =VLOOKUP(D180,Clientes!$A$2:$K$486,11,FALSE) -> Empresa | AC180: =VLOOKUP(D180,Clientes!$A$2:$B$486,2,FALSE) -> Jardines de la viña | AF180: Si | AG180: =R180 -> 45536 | AH180: Ventas | AI180: =A180 -> Articulos de Aseo | AJ180: =VLOOKUP(E180,Precios!Z$2:AA$941,2,FALSE) -> Bolsas Basura TEDDY 50x70 | AK180: =VLOOKUP(E180,Precios!Z$2:BB$941,3,FALSE)*F180 -> -3
A181: Detergentes | B181: Fernando Figueroa | C181: 45907 | D181: INAM TOUR EIRL | E181: Detergente Premium / 5 Litros | F181: 1 | G181: =VLOOKUP(E181,Precios!B$2:N$941,12,FALSE) -> 3500 | H181: =G181*F181 -> 3500 | I181: Entregado | J181: Pendiente | K181: Factura | M181: =G181/1.19 -> 2941.1765 | N181: =H181/1.19 -> 2941.1765 | O181: =H181-N181 -> 558.82353 | Q181: =YEAR(C181) -> 2025 | R181: =VLOOKUP(MONTH(C181),'Datos Maestros'!M$2:N$14,2,FALSE) -> 45536 | S181: =VLOOKUP(E181,Precios!B$2:W$941,3,FALSE) -> Detergente Premium | T181: =VLOOKUP(E181,Precios!B$2:N$941,4,FALSE)*F181 -> 5 | V181: =VLOOKUP(E181,Precios!B$2:N$941,13,FALSE)*F181 -> 764.70588 | W181: =V181-X181 -> 764.70588 | X181: =VLOOKUP(B181,'Datos Maestros'!$C$2:$D$7,2,FALSE)*V181 -> 0 | Y181: =C181-WEEKDAY(C181)+ IF(WEEKDAY(C181)=1,-5,2) -> 45901 | Z181: | | AA181: =VLOOKUP(D181,Clientes!$A$2:$J$486,9,FALSE) -> Frecuente | AB181: =VLOOKUP(D181,Clientes!$A$2:$K$486,11,FALSE) -> Empresa | AC181: =VLOOKUP(D181,Clientes!$A$2:$B$486,2,FALSE) -> Jardines de la viña | AF181: Si | AG181: =R181 -> 45536 | AH181: Ventas | AI181: =A181 -> Detergentes | AJ181: =VLOOKUP(E181,Precios!Z$2:AA$941,2,FALSE) -> Detergente SPUM 5 Litros (Verde) | AK181: =VLOOKUP(E181,Precios!Z$2:BB$941,3,FALSE)*F181 -> -1
A182: Huevos | B182: Fernando Figueroa | C182: 45907 | D182: Rene Rodriguez | E182: HUEVOS EXTRA 30 Huevos | F182: 1 | G182: =VLOOKUP(E182,Precios!B$2:N$941,12,FALSE) -> 8000.1832 | H182: =G182*F182 -> 8000.1832 | I182: Entregado | J182: Pagado | K182: Boleta | L182: 182 | M182: =G182/1.19 -> 6722.843 | N182: =H182/1.19 -> 6722.843 | O182: =H182-N182 -> 1277.3402 | Q182: =YEAR(C182) -> 2025 | R182: =VLOOKUP(MONTH(C182),'Datos Maestros'!M$2:N$14,2,FALSE) -> 45536 | S182: =VLOOKUP(E182,Precios!B$2:W$941,3,FALSE) -> Huevos EXTRA | T182: =VLOOKUP(E182,Precios!B$2:N$941,4,FALSE)*F182 -> 0 | V182: =VLOOKUP(E182,Precios!B$2:N$941,13,FALSE)*F182 -> 1151.623 | W182: =V182-X182 -> 1151.623 | X182: =VLOOKUP(B182,'Datos Maestros'!$C$2:$D$7,2,FALSE)*V182 -> 0 | Y182: =C182-WEEKDAY(C182)+ IF(WEEKDAY(C182)=1,-5,2) -> 45901 | Z182: | | AA182: =VLOOKUP(D182,Clientes!$A$2:$J$486,9,FALSE) -> Ocacional | AB182: =VLOOKUP(D182,Clientes!$A$2:$K$486,11,FALSE) -> Persona Natural | AC182: =VLOOKUP(D182,Clientes!$A$2:$B$486,2,FALSE) -> Jardin del eden | AF182: Si | AG182: =R182 -> 45536 | AH182: Ventas | AI182: =A182 -> Huevos | AJ182: =VLOOKUP(E182,Precios!Z$2:AA$941,2,FALSE) -> Bandeja Huevos EXTRA | AK182: =VLOOKUP(E182,Precios!Z$2:BB$941,3,FALSE)*F182 -> -1
A183: Longanizas | B183: Fernando Figueroa | C183: 45907 | D183: Johaniss Cocteleria | E183: Longanizas VILLABLANCA / 1 Kilo | F183: 1 | G183: =VLOOKUP(E183,Precios!B$2:N$941,12,FALSE) -> 8200.2359 | H183: =G183*F183 -> 8200.2359 | I183: Entregado | J183: Pagado | K183: Boleta | L183: 182 | M183: =G183/1.19 -> 6890.9545 | N183: =H183/1.19 -> 6890.9545 | O183: =H183-N183 -> 1309.2814 | Q183: =YEAR(C183) -> 2025 | R183: =VLOOKUP(MONTH(C183),'Datos Maestros'!M$2:N$14,2,FALSE) -> 45536 | S183: =VLOOKUP(E183,Precios!B$2:W$941,3,FALSE) -> Longanizas | T183: =VLOOKUP(E183,Precios!B$2:N$941,4,FALSE)*F183 -> 1 | V183: =VLOOKUP(E183,Precios!B$2:N$941,13,FALSE)*F183 -> 1632.4671 | W183: =V183-X183 -> 1632.4671 | X183: =VLOOKUP(B183,'Datos Maestros'!$C$2:$D$7,2,FALSE)*V183 -> 0 | Y183: =C183-WEEKDAY(C183)+ IF(WEEKDAY(C183)=1,-5,2) -> 45901 | Z183: | | AA183: =VLOOKUP(D183,Clientes!$A$2:$J$486,9,FALSE) -> Frecuente | AB183: =VLOOKUP(D183,Clientes!$A$2:$K$486,11,FALSE) -> Persona Natural | AC183: =VLOOKUP(D183,Clientes!$A$2:$B$486,2,FALSE) -> Araucania | AF183: Si | AG183: =R183 -> 45536 | AH183: Ventas | AI183: =A183 -> Longanizas | AJ183: =VLOOKUP(E183,Precios!Z$2:AA$941,2,FALSE) -> Longanizas VILLABLANCA | AK183: =VLOOKUP(E183,Precios!Z$2:BB$941,3,FALSE)*F183 -> -1
A184: Longanizas | B184: Fernando Figueroa | C184: 45907 | D184: Patricia Friz | E184: Longanizas VILLABLANCA / 1 Kilo | F184: 2 | G184: =VLOOKUP(E184,Precios!B$2:N$941,12,FALSE) -> 8200.2359 | H184: =G184*F184 -> 16400.472 | I184: Entregado | J184: Pagado | K184: Boleta | L184: 182 | M184: =G184/1.19 -> 6890.9545 | N184: =H184/1.19 -> 13781.909 | O184: =H184-N184 -> 2618.5627 | Q184: =YEAR(C184) -> 2025 | R184: =VLOOKUP(MONTH(C184),'Datos Maestros'!M$2:N$14,2,FALSE) -> 45536 | S184: =VLOOKUP(E184,Precios!B$2:W$941,3,FALSE) -> Longanizas | T184: =VLOOKUP(E184,Precios!B$2:N$941,4,FALSE)*F184 -> 2 | V184: =VLOOKUP(E184,Precios!B$2:N$941,13,FALSE)*F184 -> 3264.9343 | W184: =V184-X184 -> 3264.9343 | X184: =VLOOKUP(B184,'Datos Maestros'!$C$2:$D$7,2,FALSE)*V184 -> 0 | Y184: =C184-WEEKDAY(C184)+ IF(WEEKDAY(C184)=1,-5,2) -> 45901 | Z184: | | AA184: =VLOOKUP(D184,Clientes!$A$2:$J$486,9,FALSE) -> Ocacional | AB184: =VLOOKUP(D184,Clientes!$A$2:$K$486,11,FALSE) -> Persona Natural | AC184: =VLOOKUP(D184,Clientes!$A$2:$B$486,2,FALSE) -> Alicachue | AF184: Si | AG184: =R184 -> 45536 | AH184: Ventas | AI184: =A184 -> Longanizas | AJ184: =VLOOKUP(E184,Precios!Z$2:AA$941,2,FALSE) -> Longanizas VILLABLANCA | AK184: =VLOOKUP(E184,Precios!Z$2:BB$941,3,FALSE)*F184 -> -2
A185: Quesos | B185: Fernando Figueroa | C185: 45906 | D185: Cecilia Gomez | E185: Queso Mantecoso / 500 gramos | F185: 1 | G185: =VLOOKUP(E185,Precios!B$2:N$941,12,FALSE) -> 6000.1548 | H185: =G185*F185 -> 6000.1548 | I185: Entregado | J185: Pendiente | K185: Boleta | L185: 182 | M185: =G185/1.19 -> 5042.1469 | N185: =H185/1.19 -> 5042.1469 | O185: =H185-N185 -> 958.00791 | Q185: =YEAR(C185) -> 2025 | R185: =VLOOKUP(MONTH(C185),'Datos Maestros'!M$2:N$14,2,FALSE) -> 45536 | S185: =VLOOKUP(E185,Precios!B$2:W$941,3,FALSE) -> Queso Mantecoso | T185: =VLOOKUP(E185,Precios!B$2:N$941,4,FALSE)*F185 -> 500 | V185: =VLOOKUP(E185,Precios!B$2:N$941,13,FALSE)*F185 -> 1785.4242 | W185: =V185-X185 -> 1785.4242 | X185: =VLOOKUP(B185,'Datos Maestros'!$C$2:$D$7,2,FALSE)*V185 -> 0 | Y185: =C185-WEEKDAY(C185)+ IF(WEEKDAY(C185)=1,-5,2) -> 45901 | Z185: | | AA185: =VLOOKUP(D185,Clientes!$A$2:$J$486,9,FALSE) -> Ocacional | AB185: =VLOOKUP(D185,Clientes!$A$2:$K$486,11,FALSE) -> Persona Natural | AC185: =VLOOKUP(D185,Clientes!$A$2:$B$486,2,FALSE) -> Walker Martinez | AF185: Si | AG185: =R185 -> 45536 | AH185: Ventas | AI185: =A185 -> Quesos | AJ185: =VLOOKUP(E185,Precios!Z$2:AA$941,2,FALSE) -> Queso RUNCA Mantecoso | AK185: =VLOOKUP(E185,Precios!Z$2:BB$941,3,FALSE)*F185 -> -0.5
A186: Articulos de Aseo | B186: Fernando Figueroa | C186: 45906 | D186: Patricia Saavedra | E186: 3 x Bolsa Basura Teddy 70x90 | F186: 1 | G186: =VLOOKUP(E186,Precios!B$2:N$941,12,FALSE) -> 3400.2971 | H186: =G186*F186 -> 3400.2971 | I186: Entregado | J186: Pendiente | K186: Boleta | L186: 182 | M186: =G186/1.19 -> 2857.3925 | N186: =H186/1.19 -> 2857.3925 | O186: =H186-N186 -> 542.90458 | Q186: =YEAR(C186) -> 2025 | R186: =VLOOKUP(MONTH(C186),'Datos Maestros'!M$2:N$14,2,FALSE) -> 45536 | S186: =VLOOKUP(E186,Precios!B$2:W$941,3,FALSE) -> Bolsa Basura | T186: =VLOOKUP(E186,Precios!B$2:N$941,4,FALSE)*F186 -> 0 | V186: =VLOOKUP(E186,Precios!B$2:N$941,13,FALSE)*F186 -> 1222.3925 | W186: =V186-X186 -> 1222.3925 | X186: =VLOOKUP(B186,'Datos Maestros'!$C$2:$D$7,2,FALSE)*V186 -> 0 | Y186: =C186-WEEKDAY(C186)+ IF(WEEKDAY(C186)=1,-5,2) -> 45901 | Z186: | | AA186: =VLOOKUP(D186,Clientes!$A$2:$J$486,9,FALSE) -> Familiar | AB186: =VLOOKUP(D186,Clientes!$A$2:$K$486,11,FALSE) -> Persona Natural | AC186: =VLOOKUP(D186,Clientes!$A$2:$B$486,2,FALSE) -> Familiar | AF186: Si | AG186: =R186 -> 45536 | AH186: Ventas | AI186: =A186 -> Articulos de Aseo | AJ186: =VLOOKUP(E186,Precios!Z$2:AA$941,2,FALSE) -> Bolsas Basura TEDDY 70x90 | AK186: =VLOOKUP(E186,Precios!Z$2:BB$941,3,FALSE)*F186 -> -3
A187: Licores | B187: Fernando Figueroa | C187: 45906 | D187: Patricia Saavedra | E187: Hielo 1 Kilo | F187: 2 | G187: =VLOOKUP(E187,Precios!B$2:N$941,12,FALSE) -> 1000 | H187: =G187*F187 -> 2000 | I187: Entregado | J187: Pendiente | K187: Boleta | L187: 182 | M187: =G187/1.19 -> 840.33613 | N187: =H187/1.19 -> 1680.6723 | O187: =H187-N187 -> 319.32773 | Q187: =YEAR(C187) -> 2025 | R187: =VLOOKUP(MONTH(C187),'Datos Maestros'!M$2:N$14,2,FALSE) -> 45536 | S187: =VLOOKUP(E187,Precios!B$2:W$941,3,FALSE) -> Hielo 1 Kilo | T187: =VLOOKUP(E187,Precios!B$2:N$941,4,FALSE)*F187 -> 0 | V187: =VLOOKUP(E187,Precios!B$2:N$941,13,FALSE)*F187 -> 880.67227 | W187: =V187-X187 -> 880.67227 | X187: =VLOOKUP(B187,'Datos Maestros'!$C$2:$D$7,2,FALSE)*V187 -> 0 | Y187: =C187-WEEKDAY(C187)+ IF(WEEKDAY(C187)=1,-5,2) -> 45901 | Z187: | | AA187: =VLOOKUP(D187,Clientes!$A$2:$J$486,9,FALSE) -> Familiar | AB187: =VLOOKUP(D187,Clientes!$A$2:$K$486,11,FALSE) -> Persona Natural | AC187: =VLOOKUP(D187,Clientes!$A$2:$B$486,2,FALSE) -> Familiar | AF187: Si | AG187: =R187 -> 45536 | AH187: Ventas | AI187: =A187 -> Licores | AJ187: =VLOOKUP(E187,Precios!Z$2:AA$941,2,FALSE) -> Hielo 1 Kilo | AK187: =VLOOKUP(E187,Precios!Z$2:BB$941,3,FALSE)*F187 -> -2
A188: Articulos de Aseo | B188: Fernando Figueroa | C188: 45906 | D188: Patricia Saavedra | E188: Pack 2 Ambiental cono Lavanda | F188: 1 | G188: =VLOOKUP(E188,Precios!B$2:N$941,12,FALSE) -> 2999.8784 | H188: =G188*F188 -> 2999.8784 | I188: Entregado | J188: Pendiente | K188: Boleta | L188: 182 | M188: =G188/1.19 -> 2520.9062 | N188: =H188/1.19 -> 2520.9062 | O188: =H188-N188 -> 478.97218 | Q188: =YEAR(C188) -> 2025 | R188: =VLOOKUP(MONTH(C188),'Datos Maestros'!M$2:N$14,2,FALSE) -> 45536 | S188: =VLOOKUP(E188,Precios!B$2:W$941,3,FALSE) -> Ambiental | T188: =VLOOKUP(E188,Precios!B$2:N$941,4,FALSE)*F188 -> 0 | V188: =VLOOKUP(E188,Precios!B$2:N$941,13,FALSE)*F188 -> 862.90619 | W188: =V188-X188 -> 862.90619 | X188: =VLOOKUP(B188,'Datos Maestros'!$C$2:$D$7,2,FALSE)*V188 -> 0 | Y188: =C188-WEEKDAY(C188)+ IF(WEEKDAY(C188)=1,-5,2) -> 45901 | Z188: | | AA188: =VLOOKUP(D188,Clientes!$A$2:$J$486,9,FALSE) -> Familiar | AB188: =VLOOKUP(D188,Clientes!$A$2:$K$486,11,FALSE) -> Persona Natural | AC188: =VLOOKUP(D188,Clientes!$A$2:$B$486,2,FALSE) -> Familiar | AF188: Si | AG188: =R188 -> 45536 | AH188: Ventas | AI188: =A188 -> Articulos de Aseo | AJ188: =VLOOKUP(E188,Precios!Z$2:AA$941,2,FALSE) -> Aromatizante Cono TEDDY Gel LAVANDA | AK188: =VLOOKUP(E188,Precios!Z$2:BB$941,3,FALSE)*F188 -> -2
A189: Articulos de Aseo | B189: Fernando Figueroa | C189: 45906 | D189: Patricia Saavedra | E189: Ambiental cono Lavanda | F189: 1 | G189: =VLOOKUP(E189,Precios!B$2:N$941,12,FALSE) -> 1599.9189 | H189: =G189*F189 -> 1599.9189 | I189: Entregado | J189: Pendiente | K189: Boleta | L189: 182 | M189: =G189/1.19 -> 1344.4697 | N189: =H189/1.19 -> 1344.4697 | O189: =H189-N189 -> 255.44924 | Q189: =YEAR(C189) -> 2025 | R189: =VLOOKUP(MONTH(C189),'Datos Maestros'!M$2:N$14,2,FALSE) -> 45536 | S189: =VLOOKUP(E189,Precios!B$2:W$941,3,FALSE) -> Ambiental | T189: =VLOOKUP(E189,Precios!B$2:N$941,4,FALSE)*F189 -> 0 | V189: =VLOOKUP(E189,Precios!B$2:N$941,13,FALSE)*F189 -> 515.46967 | W189: =V189-X189 -> 515.46967 | X189: =VLOOKUP(B189,'Datos Maestros'!$C$2:$D$7,2,FALSE)*V189 -> 0 | Y189: =C189-WEEKDAY(C189)+ IF(WEEKDAY(C189)=1,-5,2) -> 45901 | Z189: | | AA189: =VLOOKUP(D189,Clientes!$A$2:$J$486,9,FALSE) -> Familiar | AB189: =VLOOKUP(D189,Clientes!$A$2:$K$486,11,FALSE) -> Persona Natural | AC189: =VLOOKUP(D189,Clientes!$A$2:$B$486,2,FALSE) -> Familiar | AF189: Si | AG189: =R189 -> 45536 | AH189: Ventas | AI189: =A189 -> Articulos de Aseo | AJ189: =VLOOKUP(E189,Precios!Z$2:AA$941,2,FALSE) -> Aromatizante Cono TEDDY Gel LAVANDA | AK189: =VLOOKUP(E189,Precios!Z$2:BB$941,3,FALSE)*F189 -> -1
A190: Frutos Secos | B190: Fernando Figueroa | C190: 45906 | D190: Patricia Saavedra | E190: CranBerry / 500 gramos | F190: 1 | G190: =VLOOKUP(E190,Precios!B$2:N$941,12,FALSE) -> 4500 | H190: =G190*F190 -> 4500 | I190: Entregado | J190: Pendiente | K190: Boleta | L190: 182 | M190: =G190/1.19 -> 3781.5126 | N190: =H190/1.19 -> 3781.5126 | O190: =H190-N190 -> 718.48739 | Q190: =YEAR(C190) -> 2025 | R190: =VLOOKUP(MONTH(C190),'Datos Maestros'!M$2:N$14,2,FALSE) -> 45536 | S190: =VLOOKUP(E190,Precios!B$2:W$941,3,FALSE) -> CranBerry | T190: =VLOOKUP(E190,Precios!B$2:N$941,4,FALSE)*F190 -> 500 | V190: =VLOOKUP(E190,Precios!B$2:N$941,13,FALSE)*F190 -> 1039.4958 | W190: =V190-X190 -> 1039.4958 | X190: =VLOOKUP(B190,'Datos Maestros'!$C$2:$D$7,2,FALSE)*V190 -> 0 | Y190: =C190-WEEKDAY(C190)+ IF(WEEKDAY(C190)=1,-5,2) -> 45901 | Z190: | | AA190: =VLOOKUP(D190,Clientes!$A$2:$J$486,9,FALSE) -> Familiar | AB190: =VLOOKUP(D190,Clientes!$A$2:$K$486,11,FALSE) -> Persona Natural | AC190: =VLOOKUP(D190,Clientes!$A$2:$B$486,2,FALSE) -> Familiar | AF190: Si | AG190: =R190 -> 45536 | AH190: Ventas | AI190: =A190 -> Frutos Secos | AJ190: =VLOOKUP(E190,Precios!Z$2:AA$941,2,FALSE) -> 0 | AK190: =VLOOKUP(E190,Precios!Z$2:BB$941,3,FALSE)*F190 -> 0
A191: Longanizas | B191: Fernando Figueroa | C191: 45906 | D191: Pilar Ortiz | E191: Longanizas VILLABLANCA / 1 Kilo | F191: 1 | G191: =VLOOKUP(E191,Precios!B$2:N$941,12,FALSE) -> 8200.2359 | H191: =G191*F191 -> 8200.2359 | I191: Entregado | J191: Pagado | K191: Boleta | L191: 182 | M191: =G191/1.19 -> 6890.9545 | N191: =H191/1.19 -> 6890.9545 | O191: =H191-N191 -> 1309.2814 | Q191: =YEAR(C191) -> 2025 | R191: =VLOOKUP(MONTH(C191),'Datos Maestros'!M$2:N$14,2,FALSE) -> 45536 | S191: =VLOOKUP(E191,Precios!B$2:W$941,3,FALSE) -> Longanizas | T191: =VLOOKUP(E191,Precios!B$2:N$941,4,FALSE)*F191 -> 1 | V191: =VLOOKUP(E191,Precios!B$2:N$941,13,FALSE)*F191 -> 1632.4671 | W191: =V191-X191 -> 1632.4671 | X191: =VLOOKUP(B191,'Datos Maestros'!$C$2:$D$7,2,FALSE)*V191 -> 0 | Y191: =C191-WEEKDAY(C191)+ IF(WEEKDAY(C191)=1,-5,2) -> 45901 | Z191: | | AA191: =VLOOKUP(D191,Clientes!$A$2:$J$486,9,FALSE) -> Ocacional | AB191: =VLOOKUP(D191,Clientes!$A$2:$K$486,11,FALSE) -> Persona Natural | AC191: =VLOOKUP(D191,Clientes!$A$2:$B$486,2,FALSE) -> Geronimo Alderete | AF191: Si | AG191: =R191 -> 45536 | AH191: Ventas | AI191: =A191 -> Longanizas | AJ191: =VLOOKUP(E191,Precios!Z$2:AA$941,2,FALSE) -> Longanizas VILLABLANCA | AK191: =VLOOKUP(E191,Precios!Z$2:BB$941,3,FALSE)*F191 -> -1
A192: Detergentes | B192: Fernando Figueroa | C192: 45906 | D192: Claudia Zuleta | E192: Detergente Piel Sensible / 5 Litros | F192: 3 | G192: =VLOOKUP(E192,Precios!B$2:N$941,12,FALSE) -> 3500 | H192: =G192*F192 -> 10500 | I192: Entregado | J192: Pagado | K192: Boleta | L192: 182 | M192: =G192/1.19 -> 2941.1765 | N192: =H192/1.19 -> 8823.5294 | O192: =H192-N192 -> 1676.4706 | Q192: =YEAR(C192) -> 2025 | R192: =VLOOKUP(MONTH(C192),'Datos Maestros'!M$2:N$14,2,FALSE) -> 45536 | S192: =VLOOKUP(E192,Precios!B$2:W$941,3,FALSE) -> Detergente Piel Sensible | T192: =VLOOKUP(E192,Precios!B$2:N$941,4,FALSE)*F192 -> 15 | V192: =VLOOKUP(E192,Precios!B$2:N$941,13,FALSE)*F192 -> 2546.2185 | W192: =V192-X192 -> 2546.2185 | X192: =VLOOKUP(B192,'Datos Maestros'!$C$2:$D$7,2,FALSE)*V192 -> 0 | Y192: =C192-WEEKDAY(C192)+ IF(WEEKDAY(C192)=1,-5,2) -> 45901 | Z192: | | AA192: =VLOOKUP(D192,Clientes!$A$2:$J$486,9,FALSE) -> Frecuente | AB192: =VLOOKUP(D192,Clientes!$A$2:$K$486,11,FALSE) -> Persona Natural | AC192: =VLOOKUP(D192,Clientes!$A$2:$B$486,2,FALSE) -> Jardin del Eden | AF192: Si | AG192: =R192 -> 45536 | AH192: Ventas | AI192: =A192 -> Detergentes | AJ192: =VLOOKUP(E192,Precios!Z$2:AA$941,2,FALSE) -> Detergente SPUM 5 Litros (Blanco) | AK192: =VLOOKUP(E192,Precios!Z$2:BB$941,3,FALSE)*F192 -> -3
A193: Detergentes | B193: Fernando Figueroa | C193: 45906 | D193: Claudia Zuleta | E193: Cloro Gel / 5 Litros | F193: 1 | G193: =VLOOKUP(E193,Precios!B$2:N$941,12,FALSE) -> 3500 | H193: =G193*F193 -> 3500 | I193: Entregado | J193: Pagado | K193: Boleta | L193: 182 | M193: =G193/1.19 -> 2941.1765 | N193: =H193/1.19 -> 2941.1765 | O193: =H193-N193 -> 558.82353 | Q193: =YEAR(C193) -> 2025 | R193: =VLOOKUP(MONTH(C193),'Datos Maestros'!M$2:N$14,2,FALSE) -> 45536 | S193: =VLOOKUP(E193,Precios!B$2:W$941,3,FALSE) -> Cloro Gel | T193: =VLOOKUP(E193,Precios!B$2:N$941,4,FALSE)*F193 -> 5 | V193: =VLOOKUP(E193,Precios!B$2:N$941,13,FALSE)*F193 -> 1016.8067 | W193: =V193-X193 -> 1016.8067 | X193: =VLOOKUP(B193,'Datos Maestros'!$C$2:$D$7,2,FALSE)*V193 -> 0 | Y193: =C193-WEEKDAY(C193)+ IF(WEEKDAY(C193)=1,-5,2) -> 45901 | Z193: | | AA193: =VLOOKUP(D193,Clientes!$A$2:$J$486,9,FALSE) -> Frecuente | AB193: =VLOOKUP(D193,Clientes!$A$2:$K$486,11,FALSE) -> Persona Natural | AC193: =VLOOKUP(D193,Clientes!$A$2:$B$486,2,FALSE) -> Jardin del Eden | AF193: Si | AG193: =R193 -> 45536 | AH193: Ventas | AI193: =A193 -> Detergentes | AJ193: =VLOOKUP(E193,Precios!Z$2:AA$941,2,FALSE) -> Cloro GEL SPUM 5 Litros | AK193: =VLOOKUP(E193,Precios!Z$2:BB$941,3,FALSE)*F193 -> -1
... A238: Abarrotes | B238: Fernando Figueroa | C238: 45905 | D238: TRAVEL ABROAD EXPERIENCE S.P.A | E238: Recarga Nescafé 130grs | F238: 1 | G238: =VLOOKUP(E238,Precios!B$2:N$941,12,FALSE) -> 5000 | H238: =G238*F238 -> 5000 | I238: Entregado | J238: Pendiente | K238: Factura | L238: 109 | M238: =G238/1.19 -> 4201.6807 | N238: =H238/1.19 -> 4201.6807 | O238: =H238-N238 -> 798.31933 | Q238: =YEAR(C238) -> 2025 | R238: =VLOOKUP(MONTH(C238),'Datos Maestros'!M$2:N$14,2,FALSE) -> 45536 | S238: =VLOOKUP(E238,Precios!B$2:W$941,3,FALSE) -> Cafe | T238: =VLOOKUP(E238,Precios!B$2:N$941,4,FALSE)*F238 -> 0 | V238: =VLOOKUP(E238,Precios!B$2:N$941,13,FALSE)*F238 -> 0 | W238: =V238-X238 -> 0 | X238: =VLOOKUP(B238,'Datos Maestros'!$C$2:$D$7,2,FALSE)*V238 -> 0 | Y238: =C238-WEEKDAY(C238)+ IF(WEEKDAY(C238)=1,-5,2) -> 45901 | Z238: | | AA238: =VLOOKUP(D238,Clientes!$A$2:$J$486,9,FALSE) -> Ocacional | AB238: =VLOOKUP(D238,Clientes!$A$2:$K$486,11,FALSE) -> Empresa | AC238: =VLOOKUP(D238,Clientes!$A$2:$B$486,2,FALSE) -> Las Condes | AF238: Si | AG238: =R238 -> 45536 | AH238: Ventas | AI238: =A238 -> Abarrotes | AJ238: =VLOOKUP(E238,Precios!Z$2:AA$941,2,FALSE) -> 0 | AK238: =VLOOKUP(E238,Precios!Z$2:BB$941,3,FALSE)*F238 -> -2
A239: Articulos de Aseo | B239: Fernando Figueroa | C239: 45905 | D239: TRAVEL ABROAD EXPERIENCE S.P.A | E239: Transporte | F239: 1 | G239: 1500 | H239: =G239*F239 -> 1500 | I239: Entregado | J239: Pendiente | K239: Factura | L239: 109 | M239: =G239/1.19 -> 1260.5042 | N239: =H239/1.19 -> 1260.5042 | O239: =H239-N239 -> 239.4958 | Q239: =YEAR(C239) -> 2025 | R239: =VLOOKUP(MONTH(C239),'Datos Maestros'!M$2:N$14,2,FALSE) -> 45536 | S239: =VLOOKUP(E239,Precios!B$2:W$941,3,FALSE) -> Transporte | T239: =VLOOKUP(E239,Precios!B$2:N$941,4,FALSE)*F239 -> 0 | V239: 1500 | W239: =V239-X239 -> 1500 | X239: =VLOOKUP(B239,'Datos Maestros'!$C$2:$D$7,2,FALSE)*V239 -> 0 | Y239: =C239-WEEKDAY(C239)+ IF(WEEKDAY(C239)=1,-5,2) -> 45901 | Z239: | | AA239: =VLOOKUP(D239,Clientes!$A$2:$J$486,9,FALSE) -> Ocacional | AB239: =VLOOKUP(D239,Clientes!$A$2:$K$486,11,FALSE) -> Empresa | AC239: =VLOOKUP(D239,Clientes!$A$2:$B$486,2,FALSE) -> Las Condes | AF239: Si | AG239: =R239 -> 45536 | AH239: Ventas | AI239: =A239 -> Articulos de Aseo | AJ239: =VLOOKUP(E239,Precios!Z$2:AA$941,2,FALSE) -> Transporte | AK239: =VLOOKUP(E239,Precios!Z$2:BB$941,3,FALSE)*F239 -> -1
A240: Articulos de Aseo | B240: Fernando Figueroa | C240: 45905 | D240: TRAVEL ABROAD EXPERIENCE S.P.A | E240: Transporte | F240: 1 | G240: -1600 | H240: =G240*F240 -> -1600 | I240: Entregado | J240: Pagado | K240: Boleta | L240: 181 | M240: =G240/1.19 -> -1344.5378 | N240: =H240/1.19 -> -1344.5378 | O240: =H240-N240 -> -255.46218 | Q240: =YEAR(C240) -> 2025 | R240: =VLOOKUP(MONTH(C240),'Datos Maestros'!M$2:N$14,2,FALSE) -> 45536 | S240: =VLOOKUP(E240,Precios!B$2:W$941,3,FALSE) -> Transporte | T240: =VLOOKUP(E240,Precios!B$2:N$941,4,FALSE)*F240 -> 0 | V240: -1600 | W240: =V240-X240 -> -1600 | X240: =VLOOKUP(B240,'Datos Maestros'!$C$2:$D$7,2,FALSE)*V240 -> 0 | Y240: =C240-WEEKDAY(C240)+ IF(WEEKDAY(C240)=1,-5,2) -> 45901 | Z240: | | AA240: =VLOOKUP(D240,Clientes!$A$2:$J$486,9,FALSE) -> Ocacional | AB240: =VLOOKUP(D240,Clientes!$A$2:$K$486,11,FALSE) -> Empresa | AC240: =VLOOKUP(D240,Clientes!$A$2:$B$486,2,FALSE) -> Las Condes | AF240: Si | AG240: =R240 -> 45536 | AH240: Ventas | AI240: =A240 -> Articulos de Aseo | AJ240: =VLOOKUP(E240,Precios!Z$2:AA$941,2,FALSE) -> Transporte | AK240: =VLOOKUP(E240,Precios!Z$2:BB$941,3,FALSE)*F240 -> -1
A241: Longanizas | B241: Fernando Figueroa | C241: 45905 | D241: Angela Neira Fritz | E241: OFERTA 3 Longanizas VILLABLANCA / 3 Kilos | F241: 1 | G241: =VLOOKUP(E241,Precios!B$2:N$941,12,FALSE) -> 23999.59 | H241: =G241*F241 -> 23999.59 | I241: Entregado | J241: Pendiente | K241: Boleta | L241: 181 | M241: =G241/1.19 -> 20167.723 | N241: =H241/1.19 -> 20167.723 | O241: =H241-N241 -> 3831.8673 | Q241: =YEAR(C241) -> 2025 | R241: =VLOOKUP(MONTH(C241),'Datos Maestros'!M$2:N$14,2,FALSE) -> 45536 | S241: =VLOOKUP(E241,Precios!B$2:W$941,3,FALSE) -> Longanizas | T241: =VLOOKUP(E241,Precios!B$2:N$941,4,FALSE)*F241 -> 3 | V241: =VLOOKUP(E241,Precios!B$2:N$941,13,FALSE)*F241 -> 4429.2352 | W241: =V241-X241 -> 4429.2352 | X241: =VLOOKUP(B241,'Datos Maestros'!$C$2:$D$7,2,FALSE)*V241 -> 0 | Y241: =C241-WEEKDAY(C241)+ IF(WEEKDAY(C241)=1,-5,2) -> 45901 | Z241: | | AA241: =VLOOKUP(D241,Clientes!$A$2:$J$486,9,FALSE) -> Frecuente | AB241: =VLOOKUP(D241,Clientes!$A$2:$K$486,11,FALSE) -> Persona Natural | AC241: =VLOOKUP(D241,Clientes!$A$2:$B$486,2,FALSE) -> Jardin del Eden | AF241: Si | AG241: =R241 -> 45536 | AH241: Ventas | AI241: =A241 -> Longanizas | AJ241: =VLOOKUP(E241,Precios!Z$2:AA$941,2,FALSE) -> Longanizas VILLABLANCA | AK241: =VLOOKUP(E241,Precios!Z$2:BB$941,3,FALSE)*F241 -> -3
A242: Derivados | B242: Fernando Figueroa | C242: 45905 | D242: Angela Neira Fritz | E242: Provoleta Parrillera / 135 gramos) | F242: 1 | G242: =VLOOKUP(E242,Precios!B$2:N$941,12,FALSE) -> 2999.6253 | H242: =G242*F242 -> 2999.6253 | I242: Entregado | J242: Pendiente | K242: Boleta | L242: 181 | M242: =G242/1.19 -> 2520.6935 | N242: =H242/1.19 -> 2520.6935 | O242: =H242-N242 -> 478.93177 | Q242: =YEAR(C242) -> 2025 | R242: =VLOOKUP(MONTH(C242),'Datos Maestros'!M$2:N$14,2,FALSE) -> 45536 | S242: =VLOOKUP(E242,Precios!B$2:W$941,3,FALSE) -> Provoleta | T242: =VLOOKUP(E242,Precios!B$2:N$941,4,FALSE)*F242 -> 135 | V242: =VLOOKUP(E242,Precios!B$2:N$941,13,FALSE)*F242 -> 1040.6935 | W242: =V242-X242 -> 1040.6935 | X242: =VLOOKUP(B242,'Datos Maestros'!$C$2:$D$7,2,FALSE)*V242 -> 0 | Y242: =C242-WEEKDAY(C242)+ IF(WEEKDAY(C242)=1,-5,2) -> 45901 | Z242: | | AA242: =VLOOKUP(D242,Clientes!$A$2:$J$486,9,FALSE) -> Frecuente | AB242: =VLOOKUP(D242,Clientes!$A$2:$K$486,11,FALSE) -> Persona Natural | AC242: =VLOOKUP(D242,Clientes!$A$2:$B$486,2,FALSE) -> Jardin del Eden | AF242: Si | AG242: =R242 -> 45536 | AH242: Ventas | AI242: =A242 -> Derivados | AJ242: =VLOOKUP(E242,Precios!Z$2:AA$941,2,FALSE) -> Provoleta Parrillera | AK242: =VLOOKUP(E242,Precios!Z$2:BB$941,3,FALSE)*F242 -> -1
A243: Detergentes | B243: Fernando Figueroa | C243: 45905 | D243: Angela Neira Fritz | E243: Detergente Piel Sensible / 5 Litros | F243: 4 | G243: =VLOOKUP(E243,Precios!B$2:N$941,12,FALSE) -> 3500 | H243: =G243*F243 -> 14000 | I243: Entregado | J243: Pendiente | K243: Boleta | L243: 181 | M243: =G243/1.19 -> 2941.1765 | N243: =H243/1.19 -> 11764.706 | O243: =H243-N243 -> 2235.2941 | Q243: =YEAR(C243) -> 2025 | R243: =VLOOKUP(MONTH(C243),'Datos Maestros'!M$2:N$14,2,FALSE) -> 45536 | S243: =VLOOKUP(E243,Precios!B$2:W$941,3,FALSE) -> Detergente Piel Sensible | T243: =VLOOKUP(E243,Precios!B$2:N$941,4,FALSE)*F243 -> 20 | V243: =VLOOKUP(E243,Precios!B$2:N$941,13,FALSE)*F243 -> 3394.958 | W243: =V243-X243 -> 3394.958 | X243: =VLOOKUP(B243,'Datos Maestros'!$C$2:$D$7,2,FALSE)*V243 -> 0 | Y243: =C243-WEEKDAY(C243)+ IF(WEEKDAY(C243)=1,-5,2) -> 45901 | Z243: | | AA243: =VLOOKUP(D243,Clientes!$A$2:$J$486,9,FALSE) -> Frecuente | AB243: =VLOOKUP(D243,Clientes!$A$2:$K$486,11,FALSE) -> Persona Natural | AC243: =VLOOKUP(D243,Clientes!$A$2:$B$486,2,FALSE) -> Jardin del Eden | AF243: Si | AG243: =R243 -> 45536 | AH243: Ventas | AI243: =A243 -> Detergentes | AJ243: =VLOOKUP(E243,Precios!Z$2:AA$941,2,FALSE) -> Detergente SPUM 5 Litros (Blanco) | AK243: =VLOOKUP(E243,Precios!Z$2:BB$941,3,FALSE)*F243 -> -4
A244: Detergentes | B244: Fernando Figueroa | C244: 45905 | D244: Angela Neira Fritz | E244: Suavizante / 5 Litros | F244: 1 | G244: =VLOOKUP(E244,Precios!B$2:N$941,12,FALSE) -> 3000 | H244: =G244*F244 -> 3000 | I244: Entregado | J244: Pendiente | K244: Boleta | L244: 181 | M244: =G244/1.19 -> 2521.0084 | N244: =H244/1.19 -> 2521.0084 | O244: =H244-N244 -> 478.9916 | Q244: =YEAR(C244) -> 2025 | R244: =VLOOKUP(MONTH(C244),'Datos Maestros'!M$2:N$14,2,FALSE) -> 45536 | S244: =VLOOKUP(E244,Precios!B$2:W$941,3,FALSE) -> Suavizante | T244: =VLOOKUP(E244,Precios!B$2:N$941,4,FALSE)*F244 -> 5 | V244: =VLOOKUP(E244,Precios!B$2:N$941,13,FALSE)*F244 -> 764.70588 | W244: =V244-X244 -> 764.70588 | X244: =VLOOKUP(B244,'Datos Maestros'!$C$2:$D$7,2,FALSE)*V244 -> 0 | Y244: =C244-WEEKDAY(C244)+ IF(WEEKDAY(C244)=1,-5,2) -> 45901 | Z244: | | AA244: =VLOOKUP(D244,Clientes!$A$2:$J$486,9,FALSE) -> Frecuente | AB244: =VLOOKUP(D244,Clientes!$A$2:$K$486,11,FALSE) -> Persona Natural | AC244: =VLOOKUP(D244,Clientes!$A$2:$B$486,2,FALSE) -> Jardin del Eden | AF244: Si | AG244: =R244 -> 45536 | AH244: Ventas | AI244: =A244 -> Detergentes | AJ244: =VLOOKUP(E244,Precios!Z$2:AA$941,2,FALSE) -> Suavizante SPUM 5 Litros | AK244: =VLOOKUP(E244,Precios!Z$2:BB$941,3,FALSE)*F244 -> -1
A245: Detergentes | B245: Fernando Figueroa | C245: 45905 | D245: Angela Neira Fritz | E245: Cloro / 5 Litros | F245: 1 | G245: =VLOOKUP(E245,Precios!B$2:N$941,12,FALSE) -> 2000 | H245: =G245*F245 -> 2000 | I245: Entregado | J245: Pendiente | K245: Boleta | L245: 181 | M245: =G245/1.19 -> 1680.6723 | N245: =H245/1.19 -> 1680.6723 | O245: =H245-N245 -> 319.32773 | Q245: =YEAR(C245) -> 2025 | R245: =VLOOKUP(MONTH(C245),'Datos Maestros'!M$2:N$14,2,FALSE) -> 45536 | S245: =VLOOKUP(E245,Precios!B$2:W$941,3,FALSE) -> Cloro | T245: =VLOOKUP(E245,Precios!B$2:N$941,4,FALSE)*F245 -> 5 | V245: =VLOOKUP(E245,Precios!B$2:N$941,13,FALSE)*F245 -> 756.30252 | W245: =V245-X245 -> 756.30252 | X245: =VLOOKUP(B245,'Datos Maestros'!$C$2:$D$7,2,FALSE)*V245 -> 0 | Y245: =C245-WEEKDAY(C245)+ IF(WEEKDAY(C245)=1,-5,2) -> 45901 | Z245: | | AA245: =VLOOKUP(D245,Clientes!$A$2:$J$486,9,FALSE) -> Frecuente | AB245: =VLOOKUP(D245,Clientes!$A$2:$K$486,11,FALSE) -> Persona Natural | AC245: =VLOOKUP(D245,Clientes!$A$2:$B$486,2,FALSE) -> Jardin del Eden | AF245: Si | AG245: =R245 -> 45536 | AH245: Ventas | AI245: =A245 -> Detergentes | AJ245: =VLOOKUP(E245,Precios!Z$2:AA$941,2,FALSE) -> Cloro SPUM 5 Litros | AK245: =VLOOKUP(E245,Precios!Z$2:BB$941,3,FALSE)*F245 -> -1
A246: Detergentes | B246: Fernando Figueroa | C246: 45905 | D246: Angela Neira Fritz | E246: Cloro Gel / 5 Litros | F246: 1 | G246: =VLOOKUP(E246,Precios!B$2:N$941,12,FALSE) -> 3500 | H246: =G246*F246 -> 3500 | I246: Entregado | J246: Pendiente | K246: Boleta | L246: 181 | M246: =G246/1.19 -> 2941.1765 | N246: =H246/1.19 -> 2941.1765 | O246: =H246-N246 -> 558.82353 | Q246: =YEAR(C246) -> 2025 | R246: =VLOOKUP(MONTH(C246),'Datos Maestros'!M$2:N$14,2,FALSE) -> 45536 | S246: =VLOOKUP(E246,Precios!B$2:W$941,3,FALSE) -> Cloro Gel | T246: =VLOOKUP(E246,Precios!B$2:N$941,4,FALSE)*F246 -> 5 | V246: =VLOOKUP(E246,Precios!B$2:N$941,13,FALSE)*F246 -> 1016.8067 | W246: =V246-X246 -> 1016.8067 | X246: =VLOOKUP(B246,'Datos Maestros'!$C$2:$D$7,2,FALSE)*V246 -> 0 | Y246: =C246-WEEKDAY(C246)+ IF(WEEKDAY(C246)=1,-5,2) -> 45901 | Z246: | | AA246: =VLOOKUP(D246,Clientes!$A$2:$J$486,9,FALSE) -> Frecuente | AB246: =VLOOKUP(D246,Clientes!$A$2:$K$486,11,FALSE) -> Persona Natural | AC246: =VLOOKUP(D246,Clientes!$A$2:$B$486,2,FALSE) -> Jardin del Eden | AF246: Si | AG246: =R246 -> 45536 | AH246: Ventas | AI246: =A246 -> Detergentes | AJ246: =VLOOKUP(E246,Precios!Z$2:AA$941,2,FALSE) -> Cloro GEL SPUM 5 Litros | AK246: =VLOOKUP(E246,Precios!Z$2:BB$941,3,FALSE)*F246 -> -1
A247: Detergentes | B247: Fernando Figueroa | C247: 45905 | D247: Angela Neira Fritz | E247: Wyn 1.5 lt | F247: 1 | G247: =VLOOKUP(E247,Precios!B$2:N$941,12,FALSE) -> 2699.928 | H247: =G247*F247 -> 2699.928 | I247: Entregado | J247: Pendiente | K247: Boleta | L247: 181 | M247: =G247/1.19 -> 2268.8471 | N247: =H247/1.19 -> 2268.8471 | O247: =H247-N247 -> 431.08094 | Q247: =YEAR(C247) -> 2025 | R247: =VLOOKUP(MONTH(C247),'Datos Maestros'!M$2:N$14,2,FALSE) -> 45536 | S247: =VLOOKUP(E247,Precios!B$2:W$941,3,FALSE) -> Lavaloza | T247: =VLOOKUP(E247,Precios!B$2:N$941,4,FALSE)*F247 -> 0 | V247: =VLOOKUP(E247,Precios!B$2:N$941,13,FALSE)*F247 -> 798.1804 | W247: =V247-X247 -> 798.1804 | X247: =VLOOKUP(B247,'Datos Maestros'!$C$2:$D$7,2,FALSE)*V247 -> 0 | Y247: =C247-WEEKDAY(C247)+ IF(WEEKDAY(C247)=1,-5,2) -> 45901 | Z247: | | AA247: =VLOOKUP(D247,Clientes!$A$2:$J$486,9,FALSE) -> Frecuente | AB247: =VLOOKUP(D247,Clientes!$A$2:$K$486,11,FALSE) -> Persona Natural | AC247: =VLOOKUP(D247,Clientes!$A$2:$B$486,2,FALSE) -> Jardin del Eden | AF247: Si | AG247: =R247 -> 45536 | AH247: Ventas | AI247: =A247 -> Detergentes | AJ247: =VLOOKUP(E247,Precios!Z$2:AA$941,2,FALSE) -> Lavaloza WYN 1.5 Litros (recarga) | AK247: =VLOOKUP(E247,Precios!Z$2:BB$941,3,FALSE)*F247 -> -1
A248: Papeleria | B248: Fernando Figueroa | C248: 45905 | D248: Angela Neira Fritz | E248: OFERTA Papel Higiénico ELITE 24 rollos | F248: 1 | G248: =VLOOKUP(E248,Precios!B$2:N$941,12,FALSE) -> 16500.237 | H248: =G248*F248 -> 16500.237 | I248: Entregado | J248: Pendiente | K248: Boleta | L248: 181 | M248: =G248/1.19 -> 13865.745 | N248: =H248/1.19 -> 13865.745 | O248: =H248-N248 -> 2634.4916 | Q248: =YEAR(C248) -> 2025 | R248: =VLOOKUP(MONTH(C248),'Datos Maestros'!M$2:N$14,2,FALSE) -> 45536 | S248: =VLOOKUP(E248,Precios!B$2:W$941,3,FALSE) -> Papel Higiénico ELITE | T248: =VLOOKUP(E248,Precios!B$2:N$941,4,FALSE)*F248 -> 0 | V248: =VLOOKUP(E248,Precios!B$2:N$941,13,FALSE)*F248 -> 3031.7452 | W248: =V248-X248 -> 3031.7452 | X248: =VLOOKUP(B248,'Datos Maestros'!$C$2:$D$7,2,FALSE)*V248 -> 0 | Y248: =C248-WEEKDAY(C248)+ IF(WEEKDAY(C248)=1,-5,2) -> 45901 | Z248: | | AA248: =VLOOKUP(D248,Clientes!$A$2:$J$486,9,FALSE) -> Frecuente | AB248: =VLOOKUP(D248,Clientes!$A$2:$K$486,11,FALSE) -> Persona Natural | AC248: =VLOOKUP(D248,Clientes!$A$2:$B$486,2,FALSE) -> Jardin del Eden | AF248: Si | AG248: =R248 -> 45536 | AH248: Ventas | AI248: =A248 -> Papeleria | AJ248: =VLOOKUP(E248,Precios!Z$2:AA$941,2,FALSE) -> Papel Higienico ELITE 50 metros | AK248: =VLOOKUP(E248,Precios!Z$2:BB$941,3,FALSE)*F248 -> -6
A249: Detergentes | B249: Fernando Figueroa | C249: 45905 | D249: Angela Neira Fritz | E249: Cif 750 cc | F249: 1 | G249: =VLOOKUP(E249,Precios!B$2:N$941,12,FALSE) -> 2400 | H249: =G249*F249 -> 2400 | I249: Entregado | J249: Pendiente | K249: Boleta | L249: 181 | M249: =G249/1.19 -> 2016.8067 | N249: =H249/1.19 -> 2016.8067 | O249: =H249-N249 -> 383.19328 | Q249: =YEAR(C249) -> 2025 | R249: =VLOOKUP(MONTH(C249),'Datos Maestros'!M$2:N$14,2,FALSE) -> 45536 | S249: =VLOOKUP(E249,Precios!B$2:W$941,3,FALSE) -> Cif | T249: =VLOOKUP(E249,Precios!B$2:N$941,4,FALSE)*F249 -> 0 | V249: =VLOOKUP(E249,Precios!B$2:N$941,13,FALSE)*F249 -> 959.66387 | W249: =V249-X249 -> 959.66387 | X249: =VLOOKUP(B249,'Datos Maestros'!$C$2:$D$7,2,FALSE)*V249 -> 0 | Y249: =C249-WEEKDAY(C249)+ IF(WEEKDAY(C249)=1,-5,2) -> 45901 | Z249: | | AA249: =VLOOKUP(D249,Clientes!$A$2:$J$486,9,FALSE) -> Frecuente | AB249: =VLOOKUP(D249,Clientes!$A$2:$K$486,11,FALSE) -> Persona Natural | AC249: =VLOOKUP(D249,Clientes!$A$2:$B$486,2,FALSE) -> Jardin del Eden | AF249: Si | AG249: =R249 -> 45536 | AH249: Ventas | AI249: =A249 -> Detergentes | AJ249: =VLOOKUP(E249,Precios!Z$2:AA$941,2,FALSE) -> CIF 750 cc | AK249: =VLOOKUP(E249,Precios!Z$2:BB$941,3,FALSE)*F249 -> -1
A250: Quesos | B250: Fernando Figueroa | C250: 45905 | D250: Angela Neira Fritz | E250: Queso Mantecoso / 1000 gramos | F250: 1 | G250: =VLOOKUP(E250,Precios!B$2:N$941,12,FALSE) -> 11000.014 | H250: =G250*F250 -> 11000.014 | I250: Entregado | J250: Pendiente | K250: Boleta | L250: 181 | M250: =G250/1.19 -> 9243.7095 | N250: =H250/1.19 -> 9243.7095 | O250: =H250-N250 -> 1756.3048 | Q250: =YEAR(C250) -> 2025 | R250: =VLOOKUP(MONTH(C250),'Datos Maestros'!M$2:N$14,2,FALSE) -> 45536 | S250: =VLOOKUP(E250,Precios!B$2:W$941,3,FALSE) -> Queso Mantecoso | T250: =VLOOKUP(E250,Precios!B$2:N$941,4,FALSE)*F250 -> 1000 | V250: =VLOOKUP(E250,Precios!B$2:N$941,13,FALSE)*F250 -> 2806.1129 | W250: =V250-X250 -> 2806.1129 | X250: =VLOOKUP(B250,'Datos Maestros'!$C$2:$D$7,2,FALSE)*V250 -> 0 | Y250: =C250-WEEKDAY(C250)+ IF(WEEKDAY(C250)=1,-5,2) -> 45901 | Z250: | | AA250: =VLOOKUP(D250,Clientes!$A$2:$J$486,9,FALSE) -> Frecuente | AB250: =VLOOKUP(D250,Clientes!$A$2:$K$486,11,FALSE) -> Persona Natural | AC250: =VLOOKUP(D250,Clientes!$A$2:$B$486,2,FALSE) -> Jardin del Eden | AF250: Si | AG250: =R250 -> 45536 | AH250: Ventas | AI250: =A250 -> Quesos | AJ250: =VLOOKUP(E250,Precios!Z$2:AA$941,2,FALSE) -> Queso RUNCA Mantecoso | AK250: =VLOOKUP(E250,Precios!Z$2:BB$941,3,FALSE)*F250 -> -1
A251: Huevos | B251: Fernando Figueroa | C251: 45905 | D251: Angela Neira Fritz | E251: HUEVOS EXTRA 30 Huevos | F251: 1 | G251: =VLOOKUP(E251,Precios!B$2:N$941,12,FALSE) -> 8000.1832 | H251: =G251*F251 -> 8000.1832 | I251: Entregado | J251: Pendiente | K251: Boleta | L251: 181 | M251: =G251/1.19 -> 6722.843 | N251: =H251/1.19 -> 6722.843 | O251: =H251-N251 -> 1277.3402 | Q251: =YEAR(C251) -> 2025 | R251: =VLOOKUP(MONTH(C251),'Datos Maestros'!M$2:N$14,2,FALSE) -> 45536 | S251: =VLOOKUP(E251,Precios!B$2:W$941,3,FALSE) -> Huevos EXTRA | T251: =VLOOKUP(E251,Precios!B$2:N$941,4,FALSE)*F251 -> 0 | V251: =VLOOKUP(E251,Precios!B$2:N$941,13,FALSE)*F251 -> 1151.623 | W251: =V251-X251 -> 1151.623 | X251: =VLOOKUP(B251,'Datos Maestros'!$C$2:$D$7,2,FALSE)*V251 -> 0 | Y251: =C251-WEEKDAY(C251)+ IF(WEEKDAY(C251)=1,-5,2) -> 45901 | Z251: | | AA251: =VLOOKUP(D251,Clientes!$A$2:$J$486,9,FALSE) -> Frecuente | AB251: =VLOOKUP(D251,Clientes!$A$2:$K$486,11,FALSE) -> Persona Natural | AC251: =VLOOKUP(D251,Clientes!$A$2:$B$486,2,FALSE) -> Jardin del Eden | AF251: Si | AG251: =R251 -> 45536 | AH251: Ventas | AI251: =A251 -> Huevos | AJ251: =VLOOKUP(E251,Precios!Z$2:AA$941,2,FALSE) -> Bandeja Huevos EXTRA | AK251: =VLOOKUP(E251,Precios!Z$2:BB$941,3,FALSE)*F251 -> -1
A252: Quesos | B252: Fernando Figueroa | C252: 45904 | D252: Pamela Rojas | E252: Queso Mantecoso / 1000 gramos | F252: 1 | G252: =VLOOKUP(E252,Precios!B$2:N$941,12,FALSE) -> 11000.014 | H252: =G252*F252 -> 11000.014 | I252: Entregado | J252: Pagado | K252: Boleta | L252: 181 | M252: =G252/1.19 -> 9243.7095 | N252: =H252/1.19 -> 9243.7095 | O252: =H252-N252 -> 1756.3048 | Q252: =YEAR(C252) -> 2025 | R252: =VLOOKUP(MONTH(C252),'Datos Maestros'!M$2:N$14,2,FALSE) -> 45536 | S252: =VLOOKUP(E252,Precios!B$2:W$941,3,FALSE) -> Queso Mantecoso | T252: =VLOOKUP(E252,Precios!B$2:N$941,4,FALSE)*F252 -> 1000 | V252: =VLOOKUP(E252,Precios!B$2:N$941,13,FALSE)*F252 -> 2806.1129 | W252: =V252-X252 -> 2806.1129 | X252: =VLOOKUP(B252,'Datos Maestros'!$C$2:$D$7,2,FALSE)*V252 -> 0 | Y252: =C252-WEEKDAY(C252)+ IF(WEEKDAY(C252)=1,-5,2) -> 45901 | Z252: | | AA252: =VLOOKUP(D252,Clientes!$A$2:$J$486,9,FALSE) -> Frecuente | AB252: =VLOOKUP(D252,Clientes!$A$2:$K$486,11,FALSE) -> Persona Natural | AC252: =VLOOKUP(D252,Clientes!$A$2:$B$486,2,FALSE) -> Jardines de la Viña | AF252: Si | AG252: =R252 -> 45536 | AH252: Ventas | AI252: =A252 -> Quesos | AJ252: =VLOOKUP(E252,Precios!Z$2:AA$941,2,FALSE) -> Queso RUNCA Mantecoso | AK252: =VLOOKUP(E252,Precios!Z$2:BB$941,3,FALSE)*F252 -> -1
... A485: Film Plastico-Aluminio | B485: Fernando Figueroa | C485: 45887 | D485: Restaurante Los Naranjos | E485: Film Plástico 1.400 Metros | F485: 1 | G485: =VLOOKUP(E485,Precios!B$2:N$941,12,FALSE) -> 24000 | H485: =G485*F485 -> 24000 | I485: Entregado | J485: Pagado | K485: Factura | L485: 106 | M485: =G485/1.19 -> 20168.067 | N485: =H485/1.19 -> 20168.067 | O485: =H485-N485 -> 3831.9328 | Q485: =YEAR(C485) -> 2025 | R485: =VLOOKUP(MONTH(C485),'Datos Maestros'!M$2:N$14,2,FALSE) -> 45505 | S485: =VLOOKUP(E485,Precios!B$2:W$941,3,FALSE) -> Film Plastico | T485: =VLOOKUP(E485,Precios!B$2:N$941,4,FALSE)*F485 -> 0 | V485: =VLOOKUP(E485,Precios!B$2:N$941,13,FALSE)*F485 -> 6861.3445 | W485: =V485-X485 -> 6861.3445 | X485: =VLOOKUP(B485,'Datos Maestros'!$C$2:$D$7,2,FALSE)*V485 -> 0 | Y485: =C485-WEEKDAY(C485)+ IF(WEEKDAY(C485)=1,-5,2) -> 45887 | Z485: | | AA485: =VLOOKUP(D485,Clientes!$A$2:$J$486,9,FALSE) -> Frecuente | AB485: =VLOOKUP(D485,Clientes!$A$2:$K$486,11,FALSE) -> Empresa | AC485: =VLOOKUP(D485,Clientes!$A$2:$B$486,2,FALSE) -> Departamental | AF485: Si | AG485: =R485 -> 45505 | AH485: Ventas | AI485: =A485 -> Film Plastico-Aluminio | AJ485: =VLOOKUP(E485,Precios!Z$2:AA$941,2,FALSE) -> Film Plástico 1400 metros | AK485: =VLOOKUP(E485,Precios!Z$2:BB$941,3,FALSE)*F485 -> -1
A486: Film Plastico-Aluminio | B486: Fernando Figueroa | C486: 45887 | D486: Restaurante Los Naranjos | E486: Descuentos | F486: 1 | G486: -500 | H486: =G486*F486 -> -500 | I486: Entregado | J486: Pagado | K486: Factura | L486: 106 | M486: =G486/1.19 -> -420.16807 | N486: =H486/1.19 -> -420.16807 | O486: =H486-N486 -> -79.831933 | Q486: =YEAR(C486) -> 2025 | R486: =VLOOKUP(MONTH(C486),'Datos Maestros'!M$2:N$14,2,FALSE) -> 45505 | S486: =VLOOKUP(E486,Precios!B$2:W$941,3,FALSE) -> Descuentos | T486: =VLOOKUP(E486,Precios!B$2:N$941,4,FALSE)*F486 -> 1000 | V486: -500 | W486: =V486-X486 -> -500 | X486: =VLOOKUP(B486,'Datos Maestros'!$C$2:$D$7,2,FALSE)*V486 -> 0 | Y486: =C486-WEEKDAY(C486)+ IF(WEEKDAY(C486)=1,-5,2) -> 45887 | Z486: | | AA486: =VLOOKUP(D486,Clientes!$A$2:$J$486,9,FALSE) -> Frecuente | AB486: =VLOOKUP(D486,Clientes!$A$2:$K$486,11,FALSE) -> Empresa | AC486: =VLOOKUP(D486,Clientes!$A$2:$B$486,2,FALSE) -> Departamental | AF486: Si | AG486: =R486 -> 45505 | AH486: Ventas | AI486: =A486 -> Film Plastico-Aluminio | AJ486: =VLOOKUP(E486,Precios!Z$2:AA$941,2,FALSE) -> Descuentos | AK486: =VLOOKUP(E486,Precios!Z$2:BB$941,3,FALSE)*F486 -> -1
A487: Articulos de Sanidad | B487: Fernando Figueroa | C487: 45887 | D487: Restaurante Los Naranjos | E487: Caja 100 Guantes NITRILO Talla L | F487: 3 | G487: =VLOOKUP(E487,Precios!B$2:N$941,12,FALSE) -> 4199.902 | H487: =G487*F487 -> 12599.706 | I487: Entregado | J487: Pagado | K487: Factura | L487: 106 | M487: =G487/1.19 -> 3529.3294 | N487: =H487/1.19 -> 10587.988 | O487: =H487-N487 -> 2011.7178 | Q487: =YEAR(C487) -> 2025 | R487: =VLOOKUP(MONTH(C487),'Datos Maestros'!M$2:N$14,2,FALSE) -> 45505 | S487: =VLOOKUP(E487,Precios!B$2:W$941,3,FALSE) -> Guantes NITRILO | T487: =VLOOKUP(E487,Precios!B$2:N$941,4,FALSE)*F487 -> 0 | V487: =VLOOKUP(E487,Precios!B$2:N$941,13,FALSE)*F487 -> 3024.9882 | W487: =V487-X487 -> 3024.9882 | X487: =VLOOKUP(B487,'Datos Maestros'!$C$2:$D$7,2,FALSE)*V487 -> 0 | Y487: =C487-WEEKDAY(C487)+ IF(WEEKDAY(C487)=1,-5,2) -> 45887 | Z487: | | AA487: =VLOOKUP(D487,Clientes!$A$2:$J$486,9,FALSE) -> Frecuente | AB487: =VLOOKUP(D487,Clientes!$A$2:$K$486,11,FALSE) -> Empresa | AC487: =VLOOKUP(D487,Clientes!$A$2:$B$486,2,FALSE) -> Departamental | AF487: Si | AG487: =R487 -> 45505 | AH487: Ventas | AI487: =A487 -> Articulos de Sanidad | AJ487: =VLOOKUP(E487,Precios!Z$2:AA$941,2,FALSE) -> Guante NITRILO Talla L | AK487: =VLOOKUP(E487,Precios!Z$2:BB$941,3,FALSE)*F487 -> -3
A488: Papeleria | B488: Fernando Figueroa | C488: 45887 | D488: Restaurante Los Naranjos | E488: Toalla Papel Jumbo 250 mts (Pack 2) | F488: 3 | G488: =VLOOKUP(E488,Precios!B$2:N$941,12,FALSE) -> 9500.0304 | H488: =G488*F488 -> 28500.091 | I488: Entregado | J488: Pagado | K488: Factura | L488: 106 | M488: =G488/1.19 -> 7983.2188 | N488: =H488/1.19 -> 23949.656 | O488: =H488-N488 -> 4550.4347 | Q488: =YEAR(C488) -> 2025 | R488: =VLOOKUP(MONTH(C488),'Datos Maestros'!M$2:N$14,2,FALSE) -> 45505 | S488: =VLOOKUP(E488,Precios!B$2:W$941,3,FALSE) -> Toalla Papel Soft Quality | T488: =VLOOKUP(E488,Precios!B$2:N$941,4,FALSE)*F488 -> 0 | V488: =VLOOKUP(E488,Precios!B$2:N$941,13,FALSE)*F488 -> 8193.6565 | W488: =V488-X488 -> 8193.6565 | X488: =VLOOKUP(B488,'Datos Maestros'!$C$2:$D$7,2,FALSE)*V488 -> 0 | Y488: =C488-WEEKDAY(C488)+ IF(WEEKDAY(C488)=1,-5,2) -> 45887 | Z488: | | AA488: =VLOOKUP(D488,Clientes!$A$2:$J$486,9,FALSE) -> Frecuente | AB488: =VLOOKUP(D488,Clientes!$A$2:$K$486,11,FALSE) -> Empresa | AC488: =VLOOKUP(D488,Clientes!$A$2:$B$486,2,FALSE) -> Departamental | AF488: Si | AG488: =R488 -> 45505 | AH488: Ventas | AI488: =A488 -> Papeleria | AJ488: =VLOOKUP(E488,Precios!Z$2:AA$941,2,FALSE) -> Toalla Papel 250 metros dipensador | AK488: =VLOOKUP(E488,Precios!Z$2:BB$941,3,FALSE)*F488 -> -3
A489: Quesos | B489: Fernando Figueroa | C489: 45887 | D489: Marcela Neira | E489: Queso Mantecoso / 1000 gramos | F489: 2 | G489: =VLOOKUP(E489,Precios!B$2:N$941,12,FALSE) -> 11000.014 | H489: =G489*F489 -> 22000.029 | I489: Entregado | J489: Pagado | K489: Boleta | L489: 172 | M489: =G489/1.19 -> 9243.7095 | N489: =H489/1.19 -> 18487.419 | O489: =H489-N489 -> 3512.6096 | Q489: =YEAR(C489) -> 2025 | R489: =VLOOKUP(MONTH(C489),'Datos Maestros'!M$2:N$14,2,FALSE) -> 45505 | S489: =VLOOKUP(E489,Precios!B$2:W$941,3,FALSE) -> Queso Mantecoso | T489: =VLOOKUP(E489,Precios!B$2:N$941,4,FALSE)*F489 -> 2000 | V489: =VLOOKUP(E489,Precios!B$2:N$941,13,FALSE)*F489 -> 5612.2258 | W489: =V489-X489 -> 5612.2258 | X489: =VLOOKUP(B489,'Datos Maestros'!$C$2:$D$7,2,FALSE)*V489 -> 0 | Y489: =C489-WEEKDAY(C489)+ IF(WEEKDAY(C489)=1,-5,2) -> 45887 | Z489: | | AA489: =VLOOKUP(D489,Clientes!$A$2:$J$486,9,FALSE) -> Frecuente | AB489: =VLOOKUP(D489,Clientes!$A$2:$K$486,11,FALSE) -> Persona Natural | AC489: =VLOOKUP(D489,Clientes!$A$2:$B$486,2,FALSE) -> Curso Amalia | AF489: Si | AG489: =R489 -> 45505 | AH489: Ventas | AI489: =A489 -> Quesos | AJ489: =VLOOKUP(E489,Precios!Z$2:AA$941,2,FALSE) -> Queso RUNCA Mantecoso | AK489: =VLOOKUP(E489,Precios!Z$2:BB$941,3,FALSE)*F489 -> -2
A490: Huevos | B490: Fernando Figueroa | C490: 45887 | D490: Marcela Neira | E490: HUEVOS EXTRA 30 Huevos | F490: 1 | G490: =VLOOKUP(E490,Precios!B$2:N$941,12,FALSE) -> 8000.1832 | H490: =G490*F490 -> 8000.1832 | I490: Entregado | J490: Pagado | K490: Boleta | L490: 172 | M490: =G490/1.19 -> 6722.843 | N490: =H490/1.19 -> 6722.843 | O490: =H490-N490 -> 1277.3402 | Q490: =YEAR(C490) -> 2025 | R490: =VLOOKUP(MONTH(C490),'Datos Maestros'!M$2:N$14,2,FALSE) -> 45505 | S490: =VLOOKUP(E490,Precios!B$2:W$941,3,FALSE) -> Huevos EXTRA | T490: =VLOOKUP(E490,Precios!B$2:N$941,4,FALSE)*F490 -> 0 | V490: =VLOOKUP(E490,Precios!B$2:N$941,13,FALSE)*F490 -> 1151.623 | W490: =V490-X490 -> 1151.623 | X490: =VLOOKUP(B490,'Datos Maestros'!$C$2:$D$7,2,FALSE)*V490 -> 0 | Y490: =C490-WEEKDAY(C490)+ IF(WEEKDAY(C490)=1,-5,2) -> 45887 | Z490: | | AA490: =VLOOKUP(D490,Clientes!$A$2:$J$486,9,FALSE) -> Frecuente | AB490: =VLOOKUP(D490,Clientes!$A$2:$K$486,11,FALSE) -> Persona Natural | AC490: =VLOOKUP(D490,Clientes!$A$2:$B$486,2,FALSE) -> Curso Amalia | AF490: Si | AG490: =R490 -> 45505 | AH490: Ventas | AI490: =A490 -> Huevos | AJ490: =VLOOKUP(E490,Precios!Z$2:AA$941,2,FALSE) -> Bandeja Huevos EXTRA | AK490: =VLOOKUP(E490,Precios!Z$2:BB$941,3,FALSE)*F490 -> -1
A491: Huevos | B491: Fernando Figueroa | C491: 45887 | D491: Tamara Pino | E491: HUEVOS EXTRA 30 Huevos | F491: 1 | G491: =VLOOKUP(E491,Precios!B$2:N$941,12,FALSE) -> 8000.1832 | H491: =G491*F491 -> 8000.1832 | I491: Entregado | J491: Pagado | K491: Boleta | L491: 172 | M491: =G491/1.19 -> 6722.843 | N491: =H491/1.19 -> 6722.843 | O491: =H491-N491 -> 1277.3402 | Q491: =YEAR(C491) -> 2025 | R491: =VLOOKUP(MONTH(C491),'Datos Maestros'!M$2:N$14,2,FALSE) -> 45505 | S491: =VLOOKUP(E491,Precios!B$2:W$941,3,FALSE) -> Huevos EXTRA | T491: =VLOOKUP(E491,Precios!B$2:N$941,4,FALSE)*F491 -> 0 | V491: =VLOOKUP(E491,Precios!B$2:N$941,13,FALSE)*F491 -> 1151.623 | W491: =V491-X491 -> 1151.623 | X491: =VLOOKUP(B491,'Datos Maestros'!$C$2:$D$7,2,FALSE)*V491 -> 0 | Y491: =C491-WEEKDAY(C491)+ IF(WEEKDAY(C491)=1,-5,2) -> 45887 | Z491: | | AA491: =VLOOKUP(D491,Clientes!$A$2:$J$486,9,FALSE) -> Ocacional | AB491: =VLOOKUP(D491,Clientes!$A$2:$K$486,11,FALSE) -> Persona Natural | AC491: =VLOOKUP(D491,Clientes!$A$2:$B$486,2,FALSE) -> Jardines de la viña | AF491: Si | AG491: =R491 -> 45505 | AH491: Ventas | AI491: =A491 -> Huevos | AJ491: =VLOOKUP(E491,Precios!Z$2:AA$941,2,FALSE) -> Bandeja Huevos EXTRA | AK491: =VLOOKUP(E491,Precios!Z$2:BB$941,3,FALSE)*F491 -> -1
A492: Papeleria | B492: Fernando Figueroa | C492: 45887 | D492: Katty Letelier | E492: OFERTA Papel Higiénico ELITE 24 rollos | F492: 1 | G492: =VLOOKUP(E492,Precios!B$2:N$941,12,FALSE) -> 16500.237 | H492: =G492*F492 -> 16500.237 | I492: Entregado | J492: Pagado | K492: Boleta | L492: 172 | M492: =G492/1.19 -> 13865.745 | N492: =H492/1.19 -> 13865.745 | O492: =H492-N492 -> 2634.4916 | Q492: =YEAR(C492) -> 2025 | R492: =VLOOKUP(MONTH(C492),'Datos Maestros'!M$2:N$14,2,FALSE) -> 45505 | S492: =VLOOKUP(E492,Precios!B$2:W$941,3,FALSE) -> Papel Higiénico ELITE | T492: =VLOOKUP(E492,Precios!B$2:N$941,4,FALSE)*F492 -> 0 | V492: =VLOOKUP(E492,Precios!B$2:N$941,13,FALSE)*F492 -> 3031.7452 | W492: =V492-X492 -> 3031.7452 | X492: =VLOOKUP(B492,'Datos Maestros'!$C$2:$D$7,2,FALSE)*V492 -> 0 | Y492: =C492-WEEKDAY(C492)+ IF(WEEKDAY(C492)=1,-5,2) -> 45887 | Z492: | | AA492: =VLOOKUP(D492,Clientes!$A$2:$J$486,9,FALSE) -> Frecuente | AB492: =VLOOKUP(D492,Clientes!$A$2:$K$486,11,FALSE) -> Persona Natural | AC492: =VLOOKUP(D492,Clientes!$A$2:$B$486,2,FALSE) -> Ex 4to Antilhue | AF492: Si | AG492: =R492 -> 45505 | AH492: Ventas | AI492: =A492 -> Papeleria | AJ492: =VLOOKUP(E492,Precios!Z$2:AA$941,2,FALSE) -> Papel Higienico ELITE 50 metros | AK492: =VLOOKUP(E492,Precios!Z$2:BB$941,3,FALSE)*F492 -> -6
A493: Detergentes | B493: Fernando Figueroa | C493: 45887 | D493: Katty Letelier | E493: Limpiapiso / 5 Litros | F493: 1 | G493: =VLOOKUP(E493,Precios!B$2:N$941,12,FALSE) -> 2000 | H493: =G493*F493 -> 2000 | I493: Entregado | J493: Pagado | K493: Boleta | L493: 172 | M493: =G493/1.19 -> 1680.6723 | N493: =H493/1.19 -> 1680.6723 | O493: =H493-N493 -> 319.32773 | Q493: =YEAR(C493) -> 2025 | R493: =VLOOKUP(MONTH(C493),'Datos Maestros'!M$2:N$14,2,FALSE) -> 45505 | S493: =VLOOKUP(E493,Precios!B$2:W$941,3,FALSE) -> Limpiapiso | T493: =VLOOKUP(E493,Precios!B$2:N$941,4,FALSE)*F493 -> 5 | V493: =VLOOKUP(E493,Precios!B$2:N$941,13,FALSE)*F493 -> 680.67227 | W493: =V493-X493 -> 680.67227 | X493: =VLOOKUP(B493,'Datos Maestros'!$C$2:$D$7,2,FALSE)*V493 -> 0 | Y493: =C493-WEEKDAY(C493)+ IF(WEEKDAY(C493)=1,-5,2) -> 45887 | Z493: | | AA493: =VLOOKUP(D493,Clientes!$A$2:$J$486,9,FALSE) -> Frecuente | AB493: =VLOOKUP(D493,Clientes!$A$2:$K$486,11,FALSE) -> Persona Natural | AC493: =VLOOKUP(D493,Clientes!$A$2:$B$486,2,FALSE) -> Ex 4to Antilhue | AF493: Si | AG493: =R493 -> 45505 | AH493: Ventas | AI493: =A493 -> Detergentes | AJ493: =VLOOKUP(E493,Precios!Z$2:AA$941,2,FALSE) -> Limpiapiso SPUM 5 Litros | AK493: =VLOOKUP(E493,Precios!Z$2:BB$941,3,FALSE)*F493 -> -1
A494: Detergentes | B494: Fernando Figueroa | C494: 45887 | D494: Katty Letelier | E494: Detergente Piel Sensible / 5 Litros | F494: 1 | G494: =VLOOKUP(E494,Precios!B$2:N$941,12,FALSE) -> 3500 | H494: =G494*F494 -> 3500 | I494: Entregado | J494: Pagado | K494: Boleta | L494: 172 | M494: =G494/1.19 -> 2941.1765 | N494: =H494/1.19 -> 2941.1765 | O494: =H494-N494 -> 558.82353 | Q494: =YEAR(C494) -> 2025 | R494: =VLOOKUP(MONTH(C494),'Datos Maestros'!M$2:N$14,2,FALSE) -> 45505 | S494: =VLOOKUP(E494,Precios!B$2:W$941,3,FALSE) -> Detergente Piel Sensible | T494: =VLOOKUP(E494,Precios!B$2:N$941,4,FALSE)*F494 -> 5 | V494: =VLOOKUP(E494,Precios!B$2:N$941,13,FALSE)*F494 -> 848.7395 | W494: =V494-X494 -> 848.7395 | X494: =VLOOKUP(B494,'Datos Maestros'!$C$2:$D$7,2,FALSE)*V494 -> 0 | Y494: =C494-WEEKDAY(C494)+ IF(WEEKDAY(C494)=1,-5,2) -> 45887 | Z494: | | AA494: =VLOOKUP(D494,Clientes!$A$2:$J$486,9,FALSE) -> Frecuente | AB494: =VLOOKUP(D494,Clientes!$A$2:$K$486,11,FALSE) -> Persona Natural | AC494: =VLOOKUP(D494,Clientes!$A$2:$B$486,2,FALSE) -> Ex 4to Antilhue | AF494: Si | AG494: =R494 -> 45505 | AH494: Ventas | AI494: =A494 -> Detergentes | AJ494: =VLOOKUP(E494,Precios!Z$2:AA$941,2,FALSE) -> Detergente SPUM 5 Litros (Blanco) | AK494: =VLOOKUP(E494,Precios!Z$2:BB$941,3,FALSE)*F494 -> -1
A495: Detergentes | B495: Fernando Figueroa | C495: 45886 | D495: Clemira Riffo | E495: Detergente Premium / 5 Litros | F495: 1 | G495: =VLOOKUP(E495,Precios!B$2:N$941,12,FALSE) -> 3500 | H495: =G495*F495 -> 3500 | I495: Entregado | J495: Pagado | K495: Boleta | L495: 171 | M495: =G495/1.19 -> 2941.1765 | N495: =H495/1.19 -> 2941.1765 | O495: =H495-N495 -> 558.82353 | Q495: =YEAR(C495) -> 2025 | R495: =VLOOKUP(MONTH(C495),'Datos Maestros'!M$2:N$14,2,FALSE) -> 45505 | S495: =VLOOKUP(E495,Precios!B$2:W$941,3,FALSE) -> Detergente Premium | T495: =VLOOKUP(E495,Precios!B$2:N$941,4,FALSE)*F495 -> 5 | V495: =VLOOKUP(E495,Precios!B$2:N$941,13,FALSE)*F495 -> 764.70588 | W495: =V495-X495 -> 764.70588 | X495: =VLOOKUP(B495,'Datos Maestros'!$C$2:$D$7,2,FALSE)*V495 -> 0 | Y495: =C495-WEEKDAY(C495)+ IF(WEEKDAY(C495)=1,-5,2) -> 45880 | Z495: | | AA495: =VLOOKUP(D495,Clientes!$A$2:$J$486,9,FALSE) -> Familiar | AB495: =VLOOKUP(D495,Clientes!$A$2:$K$486,11,FALSE) -> Persona Natural | AC495: =VLOOKUP(D495,Clientes!$A$2:$B$486,2,FALSE) -> Familiar | AF495: Si | AG495: =R495 -> 45505 | AH495: Ventas | AI495: =A495 -> Detergentes | AJ495: =VLOOKUP(E495,Precios!Z$2:AA$941,2,FALSE) -> Detergente SPUM 5 Litros (Verde) | AK495: =VLOOKUP(E495,Precios!Z$2:BB$941,3,FALSE)*F495 -> -1
A496: Huevos | B496: Fernando Figueroa | C496: 45886 | D496: Andrea - Azahares 8470 | E496: HUEVOS EXTRA 30 Huevos | F496: 1 | G496: =VLOOKUP(E496,Precios!B$2:N$941,12,FALSE) -> 8000.1832 | H496: =G496*F496 -> 8000.1832 | I496: Entregado | J496: Pagado | K496: Boleta | L496: 171 | M496: =G496/1.19 -> 6722.843 | N496: =H496/1.19 -> 6722.843 | O496: =H496-N496 -> 1277.3402 | Q496: =YEAR(C496) -> 2025 | R496: =VLOOKUP(MONTH(C496),'Datos Maestros'!M$2:N$14,2,FALSE) -> 45505 | S496: =VLOOKUP(E496,Precios!B$2:W$941,3,FALSE) -> Huevos EXTRA | T496: =VLOOKUP(E496,Precios!B$2:N$941,4,FALSE)*F496 -> 0 | V496: =VLOOKUP(E496,Precios!B$2:N$941,13,FALSE)*F496 -> 1151.623 | W496: =V496-X496 -> 1151.623 | X496: =VLOOKUP(B496,'Datos Maestros'!$C$2:$D$7,2,FALSE)*V496 -> 0 | Y496: =C496-WEEKDAY(C496)+ IF(WEEKDAY(C496)=1,-5,2) -> 45880 | Z496: | | AA496: =VLOOKUP(D496,Clientes!$A$2:$J$486,9,FALSE) -> Ocacional | AB496: =VLOOKUP(D496,Clientes!$A$2:$K$486,11,FALSE) -> Persona Natural | AC496: =VLOOKUP(D496,Clientes!$A$2:$B$486,2,FALSE) -> Jardin del eden | AF496: Si | AG496: =R496 -> 45505 | AH496: Ventas | AI496: =A496 -> Huevos | AJ496: =VLOOKUP(E496,Precios!Z$2:AA$941,2,FALSE) -> Bandeja Huevos EXTRA | AK496: =VLOOKUP(E496,Precios!Z$2:BB$941,3,FALSE)*F496 -> -1
A497: Articulos de Aseo | B497: Fernando Figueroa | C497: 45886 | D497: Lorena Herrera | E497: Pack 3 Paños Cocina Fibra (30x50 cm) | F497: 1 | G497: =VLOOKUP(E497,Precios!B$2:N$941,12,FALSE) -> 2499.9842 | H497: =G497*F497 -> 2499.9842 | I497: Entregado | J497: Pagado | K497: Boleta | L497: 171 | M497: =G497/1.19 -> 2100.8271 | N497: =H497/1.19 -> 2100.8271 | O497: =H497-N497 -> 399.15714 | Q497: =YEAR(C497) -> 2025 | R497: =VLOOKUP(MONTH(C497),'Datos Maestros'!M$2:N$14,2,FALSE) -> 45505 | S497: =VLOOKUP(E497,Precios!B$2:W$941,3,FALSE) -> Paños Cocina | T497: =VLOOKUP(E497,Precios!B$2:N$941,4,FALSE)*F497 -> 0 | V497: =VLOOKUP(E497,Precios!B$2:N$941,13,FALSE)*F497 -> 1430.2431 | W497: =V497-X497 -> 1430.2431 | X497: =VLOOKUP(B497,'Datos Maestros'!$C$2:$D$7,2,FALSE)*V497 -> 0 | Y497: =C497-WEEKDAY(C497)+ IF(WEEKDAY(C497)=1,-5,2) -> 45880 | Z497: | | AA497: =VLOOKUP(D497,Clientes!$A$2:$J$486,9,FALSE) -> Familiar | AB497: =VLOOKUP(D497,Clientes!$A$2:$K$486,11,FALSE) -> Persona Natural | AC497: =VLOOKUP(D497,Clientes!$A$2:$B$486,2,FALSE) -> Familiar | AF497: Si | AG497: =R497 -> 45505 | AH497: Ventas | AI497: =A497 -> Articulos de Aseo | AJ497: =VLOOKUP(E497,Precios!Z$2:AA$941,2,FALSE) -> Paños Cocina Teddy | AK497: =VLOOKUP(E497,Precios!Z$2:BB$941,3,FALSE)*F497 -> -3
A498: Detergentes | B498: Fernando Figueroa | C498: 45886 | D498: Lorena Herrera | E498: Wyn 1.5 lt | F498: 1 | G498: =VLOOKUP(E498,Precios!B$2:N$941,12,FALSE) -> 2699.928 | H498: =G498*F498 -> 2699.928 | I498: Entregado | J498: Pagado | K498: Boleta | L498: 171 | M498: =G498/1.19 -> 2268.8471 | N498: =H498/1.19 -> 2268.8471 | O498: =H498-N498 -> 431.08094 | Q498: =YEAR(C498) -> 2025 | R498: =VLOOKUP(MONTH(C498),'Datos Maestros'!M$2:N$14,2,FALSE) -> 45505 | S498: =VLOOKUP(E498,Precios!B$2:W$941,3,FALSE) -> Lavaloza | T498: =VLOOKUP(E498,Precios!B$2:N$941,4,FALSE)*F498 -> 0 | V498: =VLOOKUP(E498,Precios!B$2:N$941,13,FALSE)*F498 -> 798.1804 | W498: =V498-X498 -> 798.1804 | X498: =VLOOKUP(B498,'Datos Maestros'!$C$2:$D$7,2,FALSE)*V498 -> 0 | Y498: =C498-WEEKDAY(C498)+ IF(WEEKDAY(C498)=1,-5,2) -> 45880 | Z498: | | AA498: =VLOOKUP(D498,Clientes!$A$2:$J$486,9,FALSE) -> Familiar | AB498: =VLOOKUP(D498,Clientes!$A$2:$K$486,11,FALSE) -> Persona Natural | AC498: =VLOOKUP(D498,Clientes!$A$2:$B$486,2,FALSE) -> Familiar | AF498: Si | AG498: =R498 -> 45505 | AH498: Ventas | AI498: =A498 -> Detergentes | AJ498: =VLOOKUP(E498,Precios!Z$2:AA$941,2,FALSE) -> Lavaloza WYN 1.5 Litros (recarga) | AK498: =VLOOKUP(E498,Precios!Z$2:BB$941,3,FALSE)*F498 -> -1
... A601: Derivados | B601: Fernando Figueroa | C601: 45881 | D601: Michael Evans | E601: Trapero Algodón TEDDY (con Ojal) | F601: 1 | G601: =VLOOKUP(E601,Precios!B$2:N$941,12,FALSE) -> 1199.9358 | H601: =G601*F601 -> 1199.9358 | I601: Entregado | J601: Pagado | K601: Boleta | L601: 169 | M601: =G601/1.19 -> 1008.3494 | N601: =H601/1.19 -> 1008.3494 | O601: =H601-N601 -> 191.58638 | Q601: =YEAR(C601) -> 2025 | R601: =VLOOKUP(MONTH(C601),'Datos Maestros'!M$2:N$14,2,FALSE) -> 45505 | S601: =VLOOKUP(E601,Precios!B$2:W$941,3,FALSE) -> Trapero Algodon | T601: =VLOOKUP(E601,Precios!B$2:N$941,4,FALSE)*F601 -> 0 | V601: =VLOOKUP(E601,Precios!B$2:N$941,13,FALSE)*F601 -> 537.34939 | W601: =V601-X601 -> 537.34939 | X601: =VLOOKUP(B601,'Datos Maestros'!$C$2:$D$7,2,FALSE)*V601 -> 0 | Y601: =C601-WEEKDAY(C601)+ IF(WEEKDAY(C601)=1,-5,2) -> 45880 | Z601: | | AA601: =VLOOKUP(D601,Clientes!$A$2:$J$486,9,FALSE) -> Ocacional | AB601: =VLOOKUP(D601,Clientes!$A$2:$K$486,11,FALSE) -> Persona Natural | AC601: =VLOOKUP(D601,Clientes!$A$2:$B$486,2,FALSE) -> Diego Portales | AF601: Si | AG601: =R601 -> 45505 | AH601: Ventas | AI601: =A601 -> Derivados | AJ601: =VLOOKUP(E601,Precios!Z$2:AA$941,2,FALSE) -> Trapero Algodón TEDDY | AK601: =VLOOKUP(E601,Precios!Z$2:BB$941,3,FALSE)*F601 -> -1
A602: Derivados | B602: Fernando Figueroa | C602: 45881 | D602: Michael Evans | E602: Transporte | F602: 1 | G602: -1600 | H602: =G602*F602 -> -1600 | I602: Entregado | J602: Pagado | K602: Boleta | L602: 169 | M602: =G602/1.19 -> -1344.5378 | N602: =H602/1.19 -> -1344.5378 | O602: =H602-N602 -> -255.46218 | Q602: =YEAR(C602) -> 2025 | R602: =VLOOKUP(MONTH(C602),'Datos Maestros'!M$2:N$14,2,FALSE) -> 45505 | S602: =VLOOKUP(E602,Precios!B$2:W$941,3,FALSE) -> Transporte | T602: =VLOOKUP(E602,Precios!B$2:N$941,4,FALSE)*F602 -> 0 | V602: -1600 | W602: =V602-X602 -> -1600 | X602: =VLOOKUP(B602,'Datos Maestros'!$C$2:$D$7,2,FALSE)*V602 -> 0 | Y602: =C602-WEEKDAY(C602)+ IF(WEEKDAY(C602)=1,-5,2) -> 45880 | Z602: | | AA602: =VLOOKUP(D602,Clientes!$A$2:$J$486,9,FALSE) -> Ocacional | AB602: =VLOOKUP(D602,Clientes!$A$2:$K$486,11,FALSE) -> Persona Natural | AC602: =VLOOKUP(D602,Clientes!$A$2:$B$486,2,FALSE) -> Diego Portales | AF602: Si | AG602: =R602 -> 45505 | AH602: Ventas | AI602: =A602 -> Derivados | AJ602: =VLOOKUP(E602,Precios!Z$2:AA$941,2,FALSE) -> Transporte | AK602: =VLOOKUP(E602,Precios!Z$2:BB$941,3,FALSE)*F602 -> -1
A603: Papeleria | B603: Fernando Figueroa | C603: 45881 | D603: Gestica SpA | E603: OFERTA Pack 6 Toalla Jumbo SWAN D/H / 100 metros | F603: 1 | G603: =VLOOKUP(E603,Precios!B$2:N$941,12,FALSE) -> 18499.838 | H603: =G603*F603 -> 18499.838 | I603: Entregado | J603: Pagado | K603: Factura | L603: 104 | M603: =G603/1.19 -> 15546.083 | N603: =H603/1.19 -> 15546.083 | O603: =H603-N603 -> 2953.7557 | Q603: =YEAR(C603) -> 2025 | R603: =VLOOKUP(MONTH(C603),'Datos Maestros'!M$2:N$14,2,FALSE) -> 45505 | S603: =VLOOKUP(E603,Precios!B$2:W$941,3,FALSE) -> Toalla Papel SWAN | T603: =VLOOKUP(E603,Precios!B$2:N$941,4,FALSE)*F603 -> 100 | V603: =VLOOKUP(E603,Precios!B$2:N$941,13,FALSE)*F603 -> 4970.0826 | W603: =V603-X603 -> 4970.0826 | X603: =VLOOKUP(B603,'Datos Maestros'!$C$2:$D$7,2,FALSE)*V603 -> 0 | Y603: =C603-WEEKDAY(C603)+ IF(WEEKDAY(C603)=1,-5,2) -> 45880 | Z603: | | AA603: =VLOOKUP(D603,Clientes!$A$2:$J$486,9,FALSE) -> Frecuente | AB603: =VLOOKUP(D603,Clientes!$A$2:$K$486,11,FALSE) -> Empresa | AC603: =VLOOKUP(D603,Clientes!$A$2:$B$486,2,FALSE) -> Jardin de la viña | AF603: Si | AG603: =R603 -> 45505 | AH603: Ventas | AI603: =A603 -> Papeleria | AJ603: =VLOOKUP(E603,Precios!Z$2:AA$941,2,FALSE) -> Toalla Papel SWAN D/H NARANJA 100 metros | AK603: =VLOOKUP(E603,Precios!Z$2:BB$941,3,FALSE)*F603 -> -6
A604: Articulos de Aseo | B604: Fernando Figueroa | C604: 45881 | D604: Gestica SpA | E604: Jabon Ballerina - 750 ml | F604: 1 | G604: =VLOOKUP(E604,Precios!B$2:N$941,12,FALSE) -> 1650.365 | H604: =G604*F604 -> 1650.365 | I604: Entregado | J604: Pagado | K604: Factura | L604: 104 | M604: =G604/1.19 -> 1386.8613 | N604: =H604/1.19 -> 1386.8613 | O604: =H604-N604 -> 263.50365 | Q604: =YEAR(C604) -> 2025 | R604: =VLOOKUP(MONTH(C604),'Datos Maestros'!M$2:N$14,2,FALSE) -> 45505 | S604: =VLOOKUP(E604,Precios!B$2:W$941,3,FALSE) -> Jabon Liquido | T604: =VLOOKUP(E604,Precios!B$2:N$941,4,FALSE)*F604 -> 0 | V604: =VLOOKUP(E604,Precios!B$2:N$941,13,FALSE)*F604 -> 436.86131 | W604: =V604-X604 -> 436.86131 | X604: =VLOOKUP(B604,'Datos Maestros'!$C$2:$D$7,2,FALSE)*V604 -> 0 | Y604: =C604-WEEKDAY(C604)+ IF(WEEKDAY(C604)=1,-5,2) -> 45880 | Z604: | | AA604: =VLOOKUP(D604,Clientes!$A$2:$J$486,9,FALSE) -> Frecuente | AB604: =VLOOKUP(D604,Clientes!$A$2:$K$486,11,FALSE) -> Empresa | AC604: =VLOOKUP(D604,Clientes!$A$2:$B$486,2,FALSE) -> Jardin de la viña | AF604: Si | AG604: =R604 -> 45505 | AH604: Ventas | AI604: =A604 -> Articulos de Aseo | AJ604: =VLOOKUP(E604,Precios!Z$2:AA$941,2,FALSE) -> Jabón Lìquido BALLERINA | AK604: =VLOOKUP(E604,Precios!Z$2:BB$941,3,FALSE)*F604 -> -3
A605: Detergentes | B605: Fernando Figueroa | C605: 45881 | D605: Gestica SpA | E605: Pack 2 Magistral 500 cc | F605: 1 | G605: =VLOOKUP(E605,Precios!B$2:N$941,12,FALSE) -> 7000.3785 | H605: =G605*F605 -> 7000.3785 | I605: Entregado | J605: Pagado | K605: Factura | L605: 104 | M605: =G605/1.19 -> 5882.671 | N605: =H605/1.19 -> 5882.671 | O605: =H605-N605 -> 1117.7075 | Q605: =YEAR(C605) -> 2025 | R605: =VLOOKUP(MONTH(C605),'Datos Maestros'!M$2:N$14,2,FALSE) -> 45505 | S605: =VLOOKUP(E605,Precios!B$2:W$941,3,FALSE) -> Lavaloza | T605: =VLOOKUP(E605,Precios!B$2:N$941,4,FALSE)*F605 -> 0 | V605: =VLOOKUP(E605,Precios!B$2:N$941,13,FALSE)*F605 -> 1530.671 | W605: =V605-X605 -> 1530.671 | X605: =VLOOKUP(B605,'Datos Maestros'!$C$2:$D$7,2,FALSE)*V605 -> 0 | Y605: =C605-WEEKDAY(C605)+ IF(WEEKDAY(C605)=1,-5,2) -> 45880 | Z605: | | AA605: =VLOOKUP(D605,Clientes!$A$2:$J$486,9,FALSE) -> Frecuente | AB605: =VLOOKUP(D605,Clientes!$A$2:$K$486,11,FALSE) -> Empresa | AC605: =VLOOKUP(D605,Clientes!$A$2:$B$486,2,FALSE) -> Jardin de la viña | AF605: Si | AG605: =R605 -> 45505 | AH605: Ventas | AI605: =A605 -> Detergentes | AJ605: =VLOOKUP(E605,Precios!Z$2:AA$941,2,FALSE) -> Lavaloza MAGISTRAL 500 ml | AK605: =VLOOKUP(E605,Precios!Z$2:BB$941,3,FALSE)*F605 -> -2
A606: Articulos de Aseo | B606: Fernando Figueroa | C606: 45881 | D606: Gestica SpA | E606: Pack 3 Trapero Húmedo VIRGINIA | F606: 4 | G606: =VLOOKUP(E606,Precios!B$2:N$941,12,FALSE) -> 8000 | H606: =G606*F606 -> 32000 | I606: Entregado | J606: Pagado | K606: Factura | L606: 104 | M606: =G606/1.19 -> 6722.6891 | N606: =H606/1.19 -> 26890.756 | O606: =H606-N606 -> 5109.2437 | Q606: =YEAR(C606) -> 2025 | R606: =VLOOKUP(MONTH(C606),'Datos Maestros'!M$2:N$14,2,FALSE) -> 45505 | S606: =VLOOKUP(E606,Precios!B$2:W$941,3,FALSE) -> Trapero Húmedo | T606: =VLOOKUP(E606,Precios!B$2:N$941,4,FALSE)*F606 -> 0 | V606: =VLOOKUP(E606,Precios!B$2:N$941,13,FALSE)*F606 -> 7126.0504 | W606: =V606-X606 -> 7126.0504 | X606: =VLOOKUP(B606,'Datos Maestros'!$C$2:$D$7,2,FALSE)*V606 -> 0 | Y606: =C606-WEEKDAY(C606)+ IF(WEEKDAY(C606)=1,-5,2) -> 45880 | Z606: | | AA606: =VLOOKUP(D606,Clientes!$A$2:$J$486,9,FALSE) -> Frecuente | AB606: =VLOOKUP(D606,Clientes!$A$2:$K$486,11,FALSE) -> Empresa | AC606: =VLOOKUP(D606,Clientes!$A$2:$B$486,2,FALSE) -> Jardin de la viña | AF606: Si | AG606: =R606 -> 45505 | AH606: Ventas | AI606: =A606 -> Articulos de Aseo | AJ606: =VLOOKUP(E606,Precios!Z$2:AA$941,2,FALSE) -> Traperos Humedos VIRGINIA | AK606: =VLOOKUP(E606,Precios!Z$2:BB$941,3,FALSE)*F606 -> -12
A607: Articulos de Aseo | B607: Fernando Figueroa | C607: 45881 | D607: Gestica SpA | E607: 6 x Bolsa Basura Teddy 50x70 | F607: 2 | G607: =VLOOKUP(E607,Precios!B$2:N$941,12,FALSE) -> 3400 | H607: =G607*F607 -> 6800 | I607: Entregado | J607: Pagado | K607: Factura | L607: 104 | M607: =G607/1.19 -> 2857.1429 | N607: =H607/1.19 -> 5714.2857 | O607: =H607-N607 -> 1085.7143 | Q607: =YEAR(C607) -> 2025 | R607: =VLOOKUP(MONTH(C607),'Datos Maestros'!M$2:N$14,2,FALSE) -> 45505 | S607: =VLOOKUP(E607,Precios!B$2:W$941,3,FALSE) -> Bolsa Basura | T607: =VLOOKUP(E607,Precios!B$2:N$941,4,FALSE)*F607 -> 0 | V607: =VLOOKUP(E607,Precios!B$2:N$941,13,FALSE)*F607 -> 2510.2857 | W607: =V607-X607 -> 2510.2857 | X607: =VLOOKUP(B607,'Datos Maestros'!$C$2:$D$7,2,FALSE)*V607 -> 0 | Y607: =C607-WEEKDAY(C607)+ IF(WEEKDAY(C607)=1,-5,2) -> 45880 | Z607: | | AA607: =VLOOKUP(D607,Clientes!$A$2:$J$486,9,FALSE) -> Frecuente | AB607: =VLOOKUP(D607,Clientes!$A$2:$K$486,11,FALSE) -> Empresa | AC607: =VLOOKUP(D607,Clientes!$A$2:$B$486,2,FALSE) -> Jardin de la viña | AF607: Si | AG607: =R607 -> 45505 | AH607: Ventas | AI607: =A607 -> Articulos de Aseo | AJ607: =VLOOKUP(E607,Precios!Z$2:AA$941,2,FALSE) -> Bolsas Basura TEDDY 50x70 | AK607: =VLOOKUP(E607,Precios!Z$2:BB$941,3,FALSE)*F607 -> -12
A608: Papeleria | B608: Fernando Figueroa | C608: 45881 | D608: Gestica SpA | E608: OFERTA Papel Higiénico ELITE 32 rollos | F608: 1 | G608: =VLOOKUP(E608,Precios!B$2:N$941,12,FALSE) -> 20899.911 | H608: =G608*F608 -> 20899.911 | I608: Entregado | J608: Pagado | K608: Factura | L608: 104 | M608: =G608/1.19 -> 17562.951 | N608: =H608/1.19 -> 17562.951 | O608: =H608-N608 -> 3336.9606 | Q608: =YEAR(C608) -> 2025 | R608: =VLOOKUP(MONTH(C608),'Datos Maestros'!M$2:N$14,2,FALSE) -> 45505 | S608: =VLOOKUP(E608,Precios!B$2:W$941,3,FALSE) -> Papel Higiénico ELITE | T608: =VLOOKUP(E608,Precios!B$2:N$941,4,FALSE)*F608 -> 0 | V608: =VLOOKUP(E608,Precios!B$2:N$941,13,FALSE)*F608 -> 3117.9506 | W608: =V608-X608 -> 3117.9506 | X608: =VLOOKUP(B608,'Datos Maestros'!$C$2:$D$7,2,FALSE)*V608 -> 0 | Y608: =C608-WEEKDAY(C608)+ IF(WEEKDAY(C608)=1,-5,2) -> 45880 | Z608: | | AA608: =VLOOKUP(D608,Clientes!$A$2:$J$486,9,FALSE) -> Frecuente | AB608: =VLOOKUP(D608,Clientes!$A$2:$K$486,11,FALSE) -> Empresa | AC608: =VLOOKUP(D608,Clientes!$A$2:$B$486,2,FALSE) -> Jardin de la viña | AF608: Si | AG608: =R608 -> 45505 | AH608: Ventas | AI608: =A608 -> Papeleria | AJ608: =VLOOKUP(E608,Precios!Z$2:AA$941,2,FALSE) -> Papel Higienico ELITE 50 metros | AK608: =VLOOKUP(E608,Precios!Z$2:BB$941,3,FALSE)*F608 -> -8
...

Sheet Clientes
J1: Hola xx, cómo estás? Quería contarte que la oferta del papel higiénico he decidido mantenerla para algunas(os) clientas(es), independiente que la oferta no esté vigente. Cuándo necesites comprarla me envía un msg y la activamos. Te envío el flayer para que la tengas presente. Te aviso si en el correr del tiempo, pudiese sufrir algún ajuste en el precio.
A2: Cliente | B2: Sector Cliente | C2: Dirección | D2: Telefono | E2: Rut | F2: Fecha Creación | G2: Año | H2: Periodo | I2: Clasificacion Cliente | J2: Campaña Confort Activada | K2: Tipo Cliente | L2: Rut Empresa | M2: Razón Social | N2: Giro | O2: Dirección Facturación | P2: Correo | Q2: Rut Contacto | R2: Nombre Contacto
A3: Abuelita Lorenzo | B3: Marcela Paz | C3: Marcela Paz 8334 | F3: 45596 | G3: =TEXT(F3,"yyyy") -> 2024 | H3: =TEXT(F3,"mmmm") -> octubre | I3: Ocacional | J3: No Aplica | K3: Persona Natural
A4: Elizabeth Leyton | B4: Geronimo Alderete | C4: San Vicente de Paul 8186 la florida jardín alto | F4: 45910 | G4: =TEXT(F4,"yyyy") -> 2025 | H4: =TEXT(F4,"mmmm") -> septiembre | I4: Ocacional | J4: No Aplica | K4: Persona Natural
A5: Marcelo Clerc | B5: Araucana | C5: Rungue 8615 / Doblar en Santa Julia a mano derecha | F5: 45914 | G5: =TEXT(F5,"yyyy") -> 2025 | H5: =TEXT(F5,"mmmm") -> septiembre | I5: Ocacional | J5: No Aplica | K5: Persona Natural
A6: Lorena - Quilpolemu 7170 | B6: Palena | C6: Quilpolemu 7170 | F6: 45913 | G6: =TEXT(F6,"yyyy") -> 2025 | H6: =TEXT(F6,"mmmm") -> septiembre | I6: Ocacional | J6: No Aplica | K6: Persona Natural
A7: Sandra Arriagada | B7: Santa Amalia | C7: Tacora 9421 | F7: 45909 | G7: =TEXT(F7,"yyyy") -> 2025 | H7: =TEXT(F7,"mmmm") -> septiembre | I7: Ocacional | J7: No Aplica | K7: Persona Natural
A8: Yoli - Palena 2953 | B8: Palena | C8: Palena 2953 | F8: 45907 | G8: =TEXT(F8,"yyyy") -> 2025 | H8: =TEXT(F8,"mmmm") -> septiembre | I8: Ocacional | J8: No Aplica | K8: Persona Natural
A9: Pamela Medina - Palena 2656 | B9: Palena | C9: Palena 2656 | F9: 45907 | G9: =TEXT(F9,"yyyy") -> 2025 | H9: =TEXT(F9,"mmmm") -> septiembre | I9: Ocacional | J9: No Aplica | K9: Persona Natural
A10: Pilar Ortiz | B10: Geronimo Alderete | C10: San agustin 8165 | F10: 45906 | G10: =TEXT(F10,"yyyy") -> 2025 | H10: =TEXT(F10,"mmmm") -> septiembre | I10: Ocacional | J10: No Aplica | K10: Persona Natural
A11: TRAVEL ABROAD EXPERIENCE S.P.A | B11: Las Condes | C11: Avenida Suecia 0155, oficina 304, Providencia | F11: 45902 | G11: =TEXT(F11,"yyyy") -> 2025 | H11: =TEXT(F11,"mmmm") -> septiembre | I11: Ocacional | J11: No Aplica | K11: Empresa | L11: 77890961-8 | M11: TRAVEL ABROAD EXPERIENCE S.P.A | R11: Sebastian Romero
A12: Giselle Rojas | B12: Garcia Huidobro | C12: Vicente Huidobro 8268 la florida | F12: 45895 | G12: =TEXT(F12,"yyyy") -> 2025 | H12: =TEXT(F12,"mmmm") -> agosto | I12: Ocacional | J12: No Aplica | K12: Persona Natural
A13: Soledad Gingko Amarillo 8807 | B13: Jardines de la viña | C13: Gingko Amarillo #8807 | F13: 45895 | G13: =TEXT(F13,"yyyy") -> 2025 | H13: =TEXT(F13,"mmmm") -> agosto | I13: Ocacional | J13: No Aplica | K13: Persona Natural
A14: Luisa - Bosque Chileno 2418 | B14: Vecinal | C14: Bosque Chileno 2418 | F14: 45895 | G14: =TEXT(F14,"yyyy") -> 2025 | H14: =TEXT(F14,"mmmm") -> agosto | I14: Ocacional | J14: No Aplica | K14: Persona Natural
A15: Poli Azocar | B15: Los toros | C15: Portezuelo de colina 0870 | F15: 45892 | G15: =TEXT(F15,"yyyy") -> 2025 | H15: =TEXT(F15,"mmmm") -> agosto | I15: Ocacional | J15: No Aplica | K15: Persona Natural
A16: Estefania Iglesias | B16: Trinidad | C16: Río Nilahue 4637 | F16: 45892 | G16: =TEXT(F16,"yyyy") -> 2025 | H16: =TEXT(F16,"mmmm") -> agosto | I16: Ocacional | J16: No Aplica | K16: Persona Natural
A17: Stephie Ibañez | B17: Diego Portales | C17: Avenida la Florida 10671, depto 307. | F17: 45890 | G17: =TEXT(F17,"yyyy") -> 2025 | H17: =TEXT(F17,"mmmm") -> agosto | I17: Ocacional | J17: No Aplica | K17: Persona Natural
A18: Veronica Estay | B18: parque Coordillera | C18: Santa Rosa del Peral 4624.( problemas en numeracion de calle, está entre 4608 y 4620) | F18: 45888 | G18: =TEXT(F18,"yyyy") -> 2025 | H18: =TEXT(F18,"mmmm") -> agosto | I18: Ocacional | J18: No Aplica | K18: Persona Natural
A19: Roxana Villegas | B19: Ecuador | C19: Ecuador 8857 depto 32 | F19: 45884 | G19: =TEXT(F19,"yyyy") -> 2025 | H19: =TEXT(F19,"mmmm") -> agosto | I19: Ocacional | J19: No Aplica | K19: Persona Natural
A20: Manuel Cavero | B20: Alonso de Ercilla | C20: Húsares 1281 | F20: 45874 | G20: =TEXT(F20,"yyyy") -> 2025 | H20: =TEXT(F20,"mmmm") -> agosto | I20: Ocacional | J20: No Aplica | K20: Persona Natural
A21: Felipe Severino | B21: La Foresta | C21: Del huerto norte 3523 | F21: 45873 | G21: =TEXT(F21,"yyyy") -> 2025 | H21: =TEXT(F21,"mmmm") -> agosto | I21: Ocacional | J21: No Aplica | K21: Persona Natural
A22: Lucia Saucedo | B22: Jardin del eden | C22: Los tulipanes 8537 | F22: 45872 | G22: =TEXT(F22,"yyyy") -> 2025 | H22: =TEXT(F22,"mmmm") -> agosto | I22: Ocacional | J22: No Aplica | K22: Empresa | L22: 10172790-4 | M22: Salón de belleza Romina | N22: Otras actividades ventas al por menor | O22: Los tulipanes 8537
A23: Carla Liebsch | B23: Vicuña Mackena | C23: Santa Cruz 7966 / sector Geronimo Alderete con Vicuña Mackena | F23: 45869 | G23: =TEXT(F23,"yyyy") -> 2025 | H23: =TEXT(F23,"mmmm") -> julio | I23: Ocacional | J23: No Aplica | K23: Persona Natural
A24: COMITE DE ADELANTO BELLOTO AZUCENA II | B24: Jardines de la viña | C24: Caseta de Guardias | F24: 45868 | G24: =TEXT(F24,"yyyy") -> 2025 | H24: =TEXT(F24,"mmmm") -> julio | I24: regular | J24: No Aplica | K24: Empresa | L24: 65210252-2 | M24: COMITE DE ADELANTO BELLOTO AZUCENA II
A25: Paulina Schwarze | B25: Villa Santa Maria | C25: Pellahuén 7184 | F25: 45868 | G25: =TEXT(F25,"yyyy") -> 2025 | H25: =TEXT(F25,"mmmm") -> julio | I25: Ocacional | J25: No Aplica | K25: Persona Natural
A26: Paulina -Av Tobalaba 7321 | B26: Avenida Tobalaba | C26: Av Tobalaba 7321,dept 102 torre 4 | F26: 45853 | G26: =TEXT(F26,"yyyy") -> 2025 | H26: =TEXT(F26,"mmmm") -> julio | I26: Ocacional | J26: No Aplica | K26: Persona Natural
A27: Loreto - Perpetua Freira 250 | B27: Perpetua Freira | C27: Perpetua Freire 250 casa 18, condominio Jardines de Freire | F27: 45853 | G27: =TEXT(F27,"yyyy") -> 2025 | H27: =TEXT(F27,"mmmm") -> julio | I27: Ocacional | J27: No Aplica | K27: Persona Natural
A28: Andrea - Azahares 8470 | B28: Jardin del eden | C28: Azahares 8470 | F28: 45830 | G28: =TEXT(F28,"yyyy") -> 2025 | H28: =TEXT(F28,"mmmm") -> junio | I28: Ocacional | J28: No Aplica | K28: Persona Natural
A29: ClauMery - Galilea 7707 | B29: Jardin Alto | C29: Galilea 7707 | F29: 45830 | G29: =TEXT(F29,"yyyy") -> 2025 | H29: =TEXT(F29,"mmmm") -> junio | I29: Ocacional | J29: No Aplica | K29: Persona Natural
A30: jumpmanexclusive2 - Santa Ema 2445 | B30: Santa Delia | C30: Santa Ema 2445 | F30: 45818 | G30: =TEXT(F30,"yyyy") -> 2025 | H30: =TEXT(F30,"mmmm") -> junio | I30: Ocacional | J30: No Aplica | K30: Persona Natural
A31: Cammy Sinai 9774 | B31: Santa Amalia | C31: Sinai 9774 | F31: 45817 | G31: =TEXT(F31,"yyyy") -> 2025 | H31: =TEXT(F31,"mmmm") -> junio | I31: Ocacional | J31: No Aplica | K31: Persona Natural
A32: Adrian Jardin del Eden | B32: Jardin del eden | C32: Pitosporo 8628 | F32: 45451 | G32: =TEXT(F32,"yyyy") -> 2024 | H32: =TEXT(F32,"mmmm") -> junio | I32: Ocacional | J32: No Aplica | K32: Persona Natural
A33: Adriana Ascencio | B33: 5to C | C33: Pasaje Generosidad 0667. Puente Alto | F33: 45544 | G33: =TEXT(F33,"yyyy") -> 2024 | H33: =TEXT(F33,"mmmm") -> septiembre | I33: Ocacional | J33: No Aplica | K33: Persona Natural
A34: Ahorro y Calidad | B34: Sector Santa Julia | C34: Santa julia 2402 | F34: 45451 | G34: =TEXT(F34,"yyyy") -> 2024 | H34: =TEXT(F34,"mmmm") -> junio | I34: Ocacional | J34: No Aplica | K34: Persona Natural
A35: Alejandra Rosales | B35: Araucana | C35: Las Lomas 7860 | F35: 45547 | G35: =TEXT(F35,"yyyy") -> 2024 | H35: =TEXT(F35,"mmmm") -> septiembre | I35: Ocacional | J35: No Aplica | K35: Persona Natural
A36: Alejandra - Jardín del edén 3410 | B36: Jardin del eden | C36: Jardín del edén 3410 | F36: 45411 | G36: =TEXT(F36,"yyyy") -> 2024 | H36: =TEXT(F36,"mmmm") -> abril | I36: Ocacional | J36: No Aplica | K36: Persona Natural
A37: Alejandra Araya Herrera | B37: Familiar | F37: 45451 | G37: =TEXT(F37,"yyyy") -> 2024 | H37: =TEXT(F37,"mmmm") -> junio | I37: Ocacional | J37: No Aplica | K37: Persona Natural
A38: Alejandra Gacitua | B38: Sector Santa Delia | C38: Santa estela 2425 | F38: 45451 | G38: =TEXT(F38,"yyyy") -> 2024 | H38: =TEXT(F38,"mmmm") -> junio | I38: Ocacional | J38: No Aplica | K38: Persona Natural
A39: Alejandra Labraña | B39: San Miguel | C39: Universidad Autonoma Chile /Ramón Subercaseaux 1404, San Miguel (Metro San Miguel, Línea 2) | F39: 45545 | G39: =TEXT(F39,"yyyy") -> 2024 | H39: =TEXT(F39,"mmmm") -> septiembre | I39: Ocacional | J39: No Aplica | K39: Persona Natural
A40: Alejandra Paz Muñoz | B40: Las Cumbres | C40: Rojas magallanes 2312, dpto 433 | F40: 45596 | G40: =TEXT(F40,"yyyy") -> 2024 | H40: =TEXT(F40,"mmmm") -> octubre | I40: Ocacional | J40: No Aplica | K40: Persona Natural
A41: Alejandra Pino - Almuerzos | B41: Vecinal | C41: Coligual 2472 | F41: 45538 | G41: =TEXT(F41,"yyyy") -> 2024 | H41: =TEXT(F41,"mmmm") -> septiembre | I41: Ocacional | J41: No Aplica | K41: Persona Natural
A42: Alejandra Rios | B42: Jardines de la viña | C42: Azucena 9239 | F42: 45451 | G42: =TEXT(F42,"yyyy") -> 2024 | H42: =TEXT(F42,"mmmm") -> junio | I42: Frecuente | J42: OK | K42: Persona Natural
A43: Alexandra Gallardo | B43: Walker Martinez | C43: Walker Martínez 1612 , depto 78B | F43: 45735 | G43: =TEXT(F43,"yyyy") -> 2025 | H43: =TEXT(F43,"mmmm") -> marzo | I43: Ocacional | J43: No Aplica | K43: Persona Natural
A44: Alexis Deliz | B44: Enrique Olivares | C44: San Venancio 2819 | F44: 45604 | G44: =TEXT(F44,"yyyy") -> 2024 | H44: =TEXT(F44,"mmmm") -> noviembre | I44: Ocacional | J44: No Aplica | K44: Persona Natural
A45: Alonso | B45: Por definir | F45: 45508 | G45: =TEXT(F45,"yyyy") -> 2024 | H45: =TEXT(F45,"mmmm") -> agosto | I45: Ocacional | J45: No Aplica | K45: Persona Natural
A46: Alvaro Herrera | B46: Familiar | F46: 45451 | G46: =TEXT(F46,"yyyy") -> 2024 | H46: =TEXT(F46,"mmmm") -> junio | I46: Familiar | J46: OK | K46: Persona Natural
A47: Alvaro Saez | B47: Curso Amalia | C47: Garcia hurtado de Mendoza 7620 | F47: 45451 | G47: =TEXT(F47,"yyyy") -> 2024 | H47: =TEXT(F47,"mmmm") -> junio | I47: Ocacional | J47: No Aplica | K47: Persona Natural
A48: Amalia Herrera | B48: Familiar | F48: 45451 | G48: =TEXT(F48,"yyyy") -> 2024 | H48: =TEXT(F48,"mmmm") -> junio | I48: Ocacional | J48: No Aplica | K48: Persona Natural
A49: Amanda Godoy | B49: Jardines de la Viña | F49: 45451 | G49: =TEXT(F49,"yyyy") -> 2024 | H49: =TEXT(F49,"mmmm") -> junio | I49: Ocacional | J49: No Aplica | K49: Persona Natural
A50: Amanda Pacheco | B50: Jardin del eden | C50: Diamelos 8556 | F50: 45753 | G50: =TEXT(F50,"yyyy") -> 2025 | H50: =TEXT(F50,"mmmm") -> abril | I50: Ocacional | J50: No Aplica | K50: Persona Natural
A51: Andrea | F51: 45451 | G51: =TEXT(F51,"yyyy") -> 2024 | H51: =TEXT(F51,"mmmm") -> junio | I51: Ocacional | J51: No Aplica | K51: Persona Natural
A52: Andrea - El Arrayan 8453 | B52: Jardin del eden | C52: El Arrayan 8453 | F52: 45767 | G52: =TEXT(F52,"yyyy") -> 2025 | H52: =TEXT(F52,"mmmm") -> abril | I52: Ocacional | J52: No Aplica | K52: Persona Natural
A53: Andrea - Volcan Hornopiren 5853 | B53: Departamental | C53: Volcan Hornopiren 5853 | F53: 45710 | G53: =TEXT(F53,"yyyy") -> 2025 | H53: =TEXT(F53,"mmmm") -> febrero | I53: Ocacional | J53: No Aplica | K53: Persona Natural
A54: Andrea Alvarez | B54: Jardin del eden | C54: Diamelos 8453 | F54: 45477 | G54: =TEXT(F54,"yyyy") -> 2024 | H54: =TEXT(F54,"mmmm") -> julio | I54: Ocacional | J54: No Aplica | K54: Persona Natural
A55: Andrea Arelis Troncoso | B55: Jardin del eden | C55: Diamelos 8465 | F55: 45510 | G55: =TEXT(F55,"yyyy") -> 2024 | H55: =TEXT(F55,"mmmm") -> agosto | I55: Ocacional | J55: No Aplica | K55: Persona Natural
A56: Andrea Bravo | B56: Negrillo | C56: Pasaje Negrillo 9586 | F56: 45679 | G56: =TEXT(F56,"yyyy") -> 2025 | H56: =TEXT(F56,"mmmm") -> enero | I56: Ocacional | J56: No Aplica | K56: Persona Natural
A57: Andrea Marin | B57: Jardines de la Viña | C57: Azucena 9393 Villa Jardines de la viña | F57: 45451 | G57: =TEXT(F57,"yyyy") -> 2024 | H57: =TEXT(F57,"mmmm") -> junio | I57: Ocacional | J57: No Aplica | K57: Persona Natural
A58: Andrea Rubio | B58: Jardines de la viña | C58: Belloto del norte oriente 9357 | F58: 45451 | G58: =TEXT(F58,"yyyy") -> 2024 | H58: =TEXT(F58,"mmmm") -> junio | I58: Regular | J58: No Aplica | K58: Persona Natural
A59: Andrea Salas | B59: Santa Ines | C59: Inés de Suarez 7990 depto 312 | F59: 45671 | G59: =TEXT(F59,"yyyy") -> 2025 | H59: =TEXT(F59,"mmmm") -> enero | I59: Ocacional | J59: No Aplica | K59: Persona Natural
A60: Andres Gonzalez | B60: Colombia | C60: Yokohama 6916, La Florida | F60: 45595 | G60: =TEXT(F60,"yyyy") -> 2024 | H60: =TEXT(F60,"mmmm") -> octubre | I60: Ocacional | J60: No Aplica | K60: Persona Natural
A61: Andres Ramis | B61: Jardines de la viña | C61: Belloto del norte oriente 9286 | F61: 45451 | G61: =TEXT(F61,"yyyy") -> 2024 | H61: =TEXT(F61,"mmmm") -> junio | I61: Ocacional | J61: No Aplica | K61: Persona Natural
A62: Angela - Colegio Concepcion | B62: Colegio Concepción | F62: 45451 | G62: =TEXT(F62,"yyyy") -> 2024 | H62: =TEXT(F62,"mmmm") -> junio | I62: Ocacional | J62: No Aplica | K62: Persona Natural
A63: Angela Navarrete | B63: Santa Amalia | C63: Santa Amalia 3500 depto 21G | F63: 45451 | G63: =TEXT(F63,"yyyy") -> 2024 | H63: =TEXT(F63,"mmmm") -> junio | I63: Ocacional | J63: No Aplica | K63: Persona Natural
A64: Angela Neira Fritz | B64: Jardin del Eden | C64: Pasaje pitosporo 8581 | F64: 45451 | G64: =TEXT(F64,"yyyy") -> 2024 | H64: =TEXT(F64,"mmmm") -> junio | I64: Frecuente | J64: OK | K64: Persona Natural
A65: Anita - Tuliperos 3402 | B65: Jardin del eden | C65: Tuliperos 3402 | F65: 45645 | G65: =TEXT(F65,"yyyy") -> 2024 | H65: =TEXT(F65,"mmmm") -> diciembre | I65: Ocacional | J65: No Aplica | K65: Persona Natural
A66: Anita Maria Rifo | B66: Domo | F66: 45554 | G66: =TEXT(F66,"yyyy") -> 2024 | H66: =TEXT(F66,"mmmm") -> septiembre | I66: Ocacional | J66: No Aplica | K66: Persona Natural
A67: Anita Sandoval | B67: Curso Amalia | C67: Medellín 9797 | F67: 45451 | G67: =TEXT(F67,"yyyy") -> 2024 | H67: =TEXT(F67,"mmmm") -> junio | I67: Ocacional | J67: No Aplica | K67: Persona Natural
A68: Anita Vecina JC | B68: Sector Marcela Paz | F68: 45451 | G68: =TEXT(F68,"yyyy") -> 2024 | H68: =TEXT(F68,"mmmm") -> junio | I68: Ocacional | J68: No Aplica | K68: Persona Natural
A69: Antonio - oxford 9438 | B69: Sector Enrique Olivares | C69: oxford 9438 | F69: 45451 | G69: =TEXT(F69,"yyyy") -> 2024 | H69: =TEXT(F69,"mmmm") -> junio | I69: Ocacional | J69: No Aplica | K69: Persona Natural
